Workbook

Sheet SVI_MHDI
A1: city_name | B1: UF | C1: ibge_cod | D1: GADM_GID_2 | E1: pop_2020 | F1: MHDI_tot | G1: MHDI_long | H1: MHDI_edu | I1: MHDI_inc | J1: SVI_tot | K1: SVI_inf | L1: SVI_hum | M1: SVI_wrk | N1: SVI_quantiles
A2: =SVI!F2 -> Corumbiara/RO | B2: =INDEX(tb_SVI[],MATCH(Table3[[#This Row],[ibge_cod]],tb_SVI[Município],0),1) -> RO | C2: =INDEX(tb_SVI[],MATCH(Table3[[#This Row],[city_name]],tb_SVI[city_name_uf],0),3) -> 1100072 | D2: BRA.22.15_1 | E2: =INDEX(tb_SVI[],MATCH(Table3[[#This Row],[city_name]],tb_SVI[city_name_uf],0),5) -> 7220 | F2: =INDEX(tb_MHDI[],MATCH(Table3[[#This Row],[city_name]],tb_MHDI[mun_uf],0),5) -> 0.613 | G2: =INDEX(tb_MHDI[],MATCH(Table3[[#This Row],[city_name]],tb_MHDI[mun_uf],0),6) -> 0.63 | H2: =INDEX(tb_MHDI[],MATCH(Table3[[#This Row],[city_name]],tb_MHDI[mun_uf],0),7) -> 0.774 | I2: =INDEX(tb_MHDI[],MATCH(Table3[[#This Row],[city_name]],tb_MHDI[mun_uf],0),8) -> 0.473 | J2: =_xlfn.NUMBERVALUE(INDEX(tb_SVI[],MATCH(Table3[[#This Row],[city_name]],tb_SVI[city_name_uf],0),8),".") -> 0.336 | K2: =_xlfn.NUMBERVALUE(INDEX(tb_SVI[],MATCH(Table3[[#This Row],[city_name]],tb_SVI[city_name_uf],0),9),".") -> 0.201 | L2: =_xlfn.NUMBERVALUE(INDEX(tb_SVI[],MATCH(Table3[[#This Row],[city_name]],tb_SVI[city_name_uf],0),10),".") -> 0.427 | M2: =_xlfn.NUMBERVALUE(INDEX(tb_SVI[],MATCH(Table3[[#This Row],[city_name]],tb_SVI[city_name_uf],0),11),".") -> 0.381 | N2: =_xlfn.PERCENTRANK.INC(Table3[MHDI_tot],Table3[[#This Row],[MHDI_tot]],3) -> 0.305 | P2: min | Q2: =_xlfn.QUARTILE.INC(Table3[MHDI_tot],0) -> 0.418
A3: =SVI!F3 -> Colorado do Oeste/RO | B3: =INDEX(tb_SVI[],MATCH(Table3[[#This Row],[ibge_cod]],tb_SVI[Município],0),1) -> RO | C3: =INDEX(tb_SVI[],MATCH(Table3[[#This Row],[city_name]],tb_SVI[city_name_uf],0),3) -> 1100064 | D3: BRA.22.14_1 | E3: =INDEX(tb_SVI[],MATCH(Table3[[#This Row],[city_name]],tb_SVI[city_name_uf],0),5) -> 15544 | F3: =INDEX(tb_MHDI[],MATCH(Table3[[#This Row],[city_name]],tb_MHDI[mun_uf],0),5) -> 0.685 | G3: =INDEX(tb_MHDI[],MATCH(Table3[[#This Row],[city_name]],tb_MHDI[mun_uf],0),6) -> 0.676 | H3: =INDEX(tb_MHDI[],MATCH(Table3[[#This Row],[city_name]],tb_MHDI[mun_uf],0),7) -> 0.814 | I3: =INDEX(tb_MHDI[],MATCH(Table3[[#This Row],[city_name]],tb_MHDI[mun_uf],0),8) -> 0.584 | J3: =_xlfn.NUMBERVALUE(INDEX(tb_SVI[],MATCH(Table3[[#This Row],[city_name]],tb_SVI[city_name_uf],0),8),".") -> 0.28 | K3: =_xlfn.NUMBERVALUE(INDEX(tb_SVI[],MATCH(Table3[[#This Row],[city_name]],tb_SVI[city_name_uf],0),9),".") -> 0.114 | L3: =_xlfn.NUMBERVALUE(INDEX(tb_SVI[],MATCH(Table3[[#This Row],[city_name]],tb_SVI[city_name_uf],0),10),".") -> 0.394 | M3: =_xlfn.NUMBERVALUE(INDEX(tb_SVI[],MATCH(Table3[[#This Row],[city_name]],tb_SVI[city_name_uf],0),11),".") -> 0.333 | N3: =_xlfn.PERCENTRANK.INC(Table3[MHDI_tot],Table3[[#This Row],[MHDI_tot]],3) -> 0.581 | P3: 0.25 | Q3: =_xlfn.QUARTILE.INC(Table3[MHDI_tot],1) -> 0.599
A4: =SVI!F4 -> Chupinguaia/RO | B4: =INDEX(tb_SVI[],MATCH(Table3[[#This Row],[ibge_cod]],tb_SVI[Município],0),1) -> RO | C4: =INDEX(tb_SVI[],MATCH(Table3[[#This Row],[city_name]],tb_SVI[city_name_uf],0),3) -> 1100924 | D4: BRA.22.13_1 | E4: =INDEX(tb_SVI[],MATCH(Table3[[#This Row],[city_name]],tb_SVI[city_name_uf],0),5) -> 11472 | F4: =INDEX(tb_MHDI[],MATCH(Table3[[#This Row],[city_name]],tb_MHDI[mun_uf],0),5) -> 0.652 | G4: =INDEX(tb_MHDI[],MATCH(Table3[[#This Row],[city_name]],tb_MHDI[mun_uf],0),6) -> 0.659 | H4: =INDEX(tb_MHDI[],MATCH(Table3[[#This Row],[city_name]],tb_MHDI[mun_uf],0),7) -> 0.82 | I4: =INDEX(tb_MHDI[],MATCH(Table3[[#This Row],[city_name]],tb_MHDI[mun_uf],0),8) -> 0.514 | J4: =_xlfn.NUMBERVALUE(INDEX(tb_SVI[],MATCH(Table3[[#This Row],[city_name]],tb_SVI[city_name_uf],0),8),".") -> 0.338 | K4: =_xlfn.NUMBERVALUE(INDEX(tb_SVI[],MATCH(Table3[[#This Row],[city_name]],tb_SVI[city_name_uf],0),9),".") -> 0.285 | L4: =_xlfn.NUMBERVALUE(INDEX(tb_SVI[],MATCH(Table3[[#This Row],[city_name]],tb_SVI[city_name_uf],0),10),".") -> 0.383 | M4: =_xlfn.NUMBERVALUE(INDEX(tb_SVI[],MATCH(Table3[[#This Row],[city_name]],tb_SVI[city_name_uf],0),11),".") -> 0.347 | N4: =_xlfn.PERCENTRANK.INC(Table3[MHDI_tot],Table3[[#This Row],[MHDI_tot]],3) -> 0.445 | P4: 0.5 | Q4: =_xlfn.QUARTILE.INC(Table3[MHDI_tot],2) -> 0.665
A5: =SVI!F5 -> Vilhena/RO | B5: =INDEX(tb_SVI[],MATCH(Table3[[#This Row],[ibge_cod]],tb_SVI[Município],0),1) -> RO | C5: =INDEX(tb_SVI[],MATCH(Table3[[#This Row],[city_name]],tb_SVI[city_name_uf],0),3) -> 1100304 | D5: BRA.22.51_1 | E5: =INDEX(tb_SVI[],MATCH(Table3[[#This Row],[city_name]],tb_SVI[city_name_uf],0),5) -> 102211 | F5: =INDEX(tb_MHDI[],MATCH(Table3[[#This Row],[city_name]],tb_MHDI[mun_uf],0),5) -> 0.731 | G5: =INDEX(tb_MHDI[],MATCH(Table3[[#This Row],[city_name]],tb_MHDI[mun_uf],0),6) -> 0.734 | H5: =INDEX(tb_MHDI[],MATCH(Table3[[#This Row],[city_name]],tb_MHDI[mun_uf],0),7) -> 0.808 | I5: =INDEX(tb_MHDI[],MATCH(Table3[[#This Row],[city_name]],tb_MHDI[mun_uf],0),8) -> 0.659 | J5: =_xlfn.NUMBERVALUE(INDEX(tb_SVI[],MATCH(Table3[[#This Row],[city_name]],tb_SVI[city_name_uf],0),8),".") -> 0.239 | K5: =_xlfn.NUMBERVALUE(INDEX(tb_SVI[],MATCH(Table3[[#This Row],[city_name]],tb_SVI[city_name_uf],0),9),".") -> 0.103 | L5: =_xlfn.NUMBERVALUE(INDEX(tb_SVI[],MATCH(Table3[[#This Row],[city_name]],tb_SVI[city_name_uf],0),10),".") -> 0.339 | M5: =_xlfn.NUMBERVALUE(INDEX(tb_SVI[],MATCH(Table3[[#This Row],[city_name]],tb_SVI[city_name_uf],0),11),".") -> 0.274 | N5: =_xlfn.PERCENTRANK.INC(Table3[MHDI_tot],Table3[[#This Row],[MHDI_tot]],3) -> 0.816 | P5: 0.75 | Q5: =_xlfn.QUARTILE.INC(Table3[MHDI_tot],3) -> 0.718
A6: =SVI!F6 -> Vale do Paraíso/RO | B6: =INDEX(tb_SVI[],MATCH(Table3[[#This Row],[ibge_cod]],tb_SVI[Município],0),1) -> RO | C6: =INDEX(tb_SVI[],MATCH(Table3[[#This Row],[city_name]],tb_SVI[city_name_uf],0),3) -> 1101807 | D6: BRA.22.50_1 | E6: =INDEX(tb_SVI[],MATCH(Table3[[#This Row],[city_name]],tb_SVI[city_name_uf],0),5) -> 6656 | F6: =INDEX(tb_MHDI[],MATCH(Table3[[#This Row],[city_name]],tb_MHDI[mun_uf],0),5) -> 0.627 | G6: =INDEX(tb_MHDI[],MATCH(Table3[[#This Row],[city_name]],tb_MHDI[mun_uf],0),6) -> 0.641 | H6: =INDEX(tb_MHDI[],MATCH(Table3[[#This Row],[city_name]],tb_MHDI[mun_uf],0),7) -> 0.792 | I6: =INDEX(tb_MHDI[],MATCH(Table3[[#This Row],[city_name]],tb_MHDI[mun_uf],0),8) -> 0.485 | J6: =_xlfn.NUMBERVALUE(INDEX(tb_SVI[],MATCH(Table3[[#This Row],[city_name]],tb_SVI[city_name_uf],0),8),".") -> 0.309 | K6: =_xlfn.NUMBERVALUE(INDEX(tb_SVI[],MATCH(Table3[[#This Row],[city_name]],tb_SVI[city_name_uf],0),9),".") -> 0.131 | L6: =_xlfn.NUMBERVALUE(INDEX(tb_SVI[],MATCH(Table3[[#This Row],[city_name]],tb_SVI[city_name_uf],0),10),".") -> 0.438 | M6: =_xlfn.NUMBERVALUE(INDEX(tb_SVI[],MATCH(Table3[[#This Row],[city_name]],tb_SVI[city_name_uf],0),11),".") -> 0.358 | N6: =_xlfn.PERCENTRANK.INC(Table3[MHDI_tot],Table3[[#This Row],[MHDI_tot]],3) -> 0.36 | P6: max | Q6: =_xlfn.QUARTILE.INC(Table3[MHDI_tot],4) -> 0.862
A7: =SVI!F7 -> Vale do Anari/RO | B7: =INDEX(tb_SVI[],MATCH(Table3[[#This Row],[ibge_cod]],tb_SVI[Município],0),1) -> RO | C7: =INDEX(tb_SVI[],MATCH(Table3[[#This Row],[city_name]],tb_SVI[city_name_uf],0),3) -> 1101757 | D7: BRA.22.49_1 | E7: =INDEX(tb_SVI[],MATCH(Table3[[#This Row],[city_name]],tb_SVI[city_name_uf],0),5) -> 11377 | F7: =INDEX(tb_MHDI[],MATCH(Table3[[#This Row],[city_name]],tb_MHDI[mun_uf],0),5) -> 0.584 | G7: =INDEX(tb_MHDI[],MATCH(Table3[[#This Row],[city_name]],tb_MHDI[mun_uf],0),6) -> 0.626 | H7: =INDEX(tb_MHDI[],MATCH(Table3[[#This Row],[city_name]],tb_MHDI[mun_uf],0),7) -> 0.756 | I7: =INDEX(tb_MHDI[],MATCH(Table3[[#This Row],[city_name]],tb_MHDI[mun_uf],0),8) -> 0.421 | J7: =_xlfn.NUMBERVALUE(INDEX(tb_SVI[],MATCH(Table3[[#This Row],[city_name]],tb_SVI[city_name_uf],0),8),".") -> 0.402 | K7: =_xlfn.NUMBERVALUE(INDEX(tb_SVI[],MATCH(Table3[[#This Row],[city_name]],tb_SVI[city_name_uf],0),9),".") -> 0.2 | L7: =_xlfn.NUMBERVALUE(INDEX(tb_SVI[],MATCH(Table3[[#This Row],[city_name]],tb_SVI[city_name_uf],0),10),".") -> 0.526 | M7: =_xlfn.NUMBERVALUE(INDEX(tb_SVI[],MATCH(Table3[[#This Row],[city_name]],tb_SVI[city_name_uf],0),11),".") -> 0.481 | N7: =_xlfn.PERCENTRANK.INC(Table3[MHDI_tot],Table3[[#This Row],[MHDI_tot]],3) -> 0.18
A8: =SVI!F8 -> Urupá/RO | B8: =INDEX(tb_SVI[],MATCH(Table3[[#This Row],[ibge_cod]],tb_SVI[Município],0),1) -> RO | C8: =INDEX(tb_SVI[],MATCH(Table3[[#This Row],[city_name]],tb_SVI[city_name_uf],0),3) -> 1101708 | D8: BRA.22.48_1 | E8: =INDEX(tb_SVI[],MATCH(Table3[[#This Row],[city_name]],tb_SVI[city_name_uf],0),5) -> 11272 | F8: =INDEX(tb_MHDI[],MATCH(Table3[[#This Row],[city_name]],tb_MHDI[mun_uf],0),5) -> 0.609 | G8: =INDEX(tb_MHDI[],MATCH(Table3[[#This Row],[city_name]],tb_MHDI[mun_uf],0),6) -> 0.621 | H8: =INDEX(tb_MHDI[],MATCH(Table3[[#This Row],[city_name]],tb_MHDI[mun_uf],0),7) -> 0.772 | I8: =INDEX(tb_MHDI[],MATCH(Table3[[#This Row],[city_name]],tb_MHDI[mun_uf],0),8) -> 0.471 | J8: =_xlfn.NUMBERVALUE(INDEX(tb_SVI[],MATCH(Table3[[#This Row],[city_name]],tb_SVI[city_name_uf],0),8),".") -> 0.386 | K8: =_xlfn.NUMBERVALUE(INDEX(tb_SVI[],MATCH(Table3[[#This Row],[city_name]],tb_SVI[city_name_uf],0),9),".") -> 0.194 | L8: =_xlfn.NUMBERVALUE(INDEX(tb_SVI[],MATCH(Table3[[#This Row],[city_name]],tb_SVI[city_name_uf],0),10),".") -> 0.445 | M8: =_xlfn.NUMBERVALUE(INDEX(tb_SVI[],MATCH(Table3[[#This Row],[city_name]],tb_SVI[city_name_uf],0),11),".") -> 0.52 | N8: =_xlfn.PERCENTRANK.INC(Table3[MHDI_tot],Table3[[#This Row],[MHDI_tot]],3) -> 0.289
A9: =SVI!F9 -> Theobroma/RO | B9: =INDEX(tb_SVI[],MATCH(Table3[[#This Row],[ibge_cod]],tb_SVI[Município],0),1) -> RO | C9: =INDEX(tb_SVI[],MATCH(Table3[[#This Row],[city_name]],tb_SVI[city_name_uf],0),3) -> 1101609 | D9: BRA.22.47_1 | E9: =INDEX(tb_SVI[],MATCH(Table3[[#This Row],[city_name]],tb_SVI[city_name_uf],0),5) -> 10395 | F9: =INDEX(tb_MHDI[],MATCH(Table3[[#This Row],[city_name]],tb_MHDI[mun_uf],0),5) -> 0.589 | G9: =INDEX(tb_MHDI[],MATCH(Table3[[#This Row],[city_name]],tb_MHDI[mun_uf],0),6) -> 0.622 | H9: =INDEX(tb_MHDI[],MATCH(Table3[[#This Row],[city_name]],tb_MHDI[mun_uf],0),7) -> 0.757 | I9: =INDEX(tb_MHDI[],MATCH(Table3[[#This Row],[city_name]],tb_MHDI[mun_uf],0),8) -> 0.434 | J9: =_xlfn.NUMBERVALUE(INDEX(tb_SVI[],MATCH(Table3[[#This Row],[city_name]],tb_SVI[city_name_uf],0),8),".") -> 0.352 | K9: =_xlfn.NUMBERVALUE(INDEX(tb_SVI[],MATCH(Table3[[#This Row],[city_name]],tb_SVI[city_name_uf],0),9),".") -> 0.164 | L9: =_xlfn.NUMBERVALUE(INDEX(tb_SVI[],MATCH(Table3[[#This Row],[city_name]],tb_SVI[city_name_uf],0),10),".") -> 0.388 | M9: =_xlfn.NUMBERVALUE(INDEX(tb_SVI[],MATCH(Table3[[#This Row],[city_name]],tb_SVI[city_name_uf],0),11),".") -> 0.505 | N9: =_xlfn.PERCENTRANK.INC(Table3[MHDI_tot],Table3[[#This Row],[MHDI_tot]],3) -> 0.201
A10: =SVI!F10 -> Teixeirópolis/RO | B10: =INDEX(tb_SVI[],MATCH(Table3[[#This Row],[ibge_cod]],tb_SVI[Município],0),1) -> RO | C10: =INDEX(tb_SVI[],MATCH(Table3[[#This Row],[city_name]],tb_SVI[city_name_uf],0),3) -> 1101559 | D10: BRA.22.46_1 | E10: =INDEX(tb_SVI[],MATCH(Table3[[#This Row],[city_name]],tb_SVI[city_name_uf],0),5) -> 4233 | F10: =INDEX(tb_MHDI[],MATCH(Table3[[#This Row],[city_name]],tb_MHDI[mun_uf],0),5) -> 0.643 | G10: =INDEX(tb_MHDI[],MATCH(Table3[[#This Row],[city_name]],tb_MHDI[mun_uf],0),6) -> 0.653 | H10: =INDEX(tb_MHDI[],MATCH(Table3[[#This Row],[city_name]],tb_MHDI[mun_uf],0),7) -> 0.818 | I10: =INDEX(tb_MHDI[],MATCH(Table3[[#This Row],[city_name]],tb_MHDI[mun_uf],0),8) -> 0.498 | J10: =_xlfn.NUMBERVALUE(INDEX(tb_SVI[],MATCH(Table3[[#This Row],[city_name]],tb_SVI[city_name_uf],0),8),".") -> 0.299 | K10: =_xlfn.NUMBERVALUE(INDEX(tb_SVI[],MATCH(Table3[[#This Row],[city_name]],tb_SVI[city_name_uf],0),9),".") -> 0.197 | L10: =_xlfn.NUMBERVALUE(INDEX(tb_SVI[],MATCH(Table3[[#This Row],[city_name]],tb_SVI[city_name_uf],0),10),".") -> 0.322 | M10: =_xlfn.NUMBERVALUE(INDEX(tb_SVI[],MATCH(Table3[[#This Row],[city_name]],tb_SVI[city_name_uf],0),11),".") -> 0.377 | N10: =_xlfn.PERCENTRANK.INC(Table3[MHDI_tot],Table3[[#This Row],[MHDI_tot]],3) -> 0.415
A11: =SVI!F11 -> São Miguel do Guaporé/RO | B11: =INDEX(tb_SVI[],MATCH(Table3[[#This Row],[ibge_cod]],tb_SVI[Município],0),1) -> RO | C11: =INDEX(tb_SVI[],MATCH(Table3[[#This Row],[city_name]],tb_SVI[city_name_uf],0),3) -> 1100320 | D11: BRA.22.44_1 | E11: =INDEX(tb_SVI[],MATCH(Table3[[#This Row],[city_name]],tb_SVI[city_name_uf],0),5) -> 23077 | F11: =INDEX(tb_MHDI[],MATCH(Table3[[#This Row],[city_name]],tb_MHDI[mun_uf],0),5) -> 0.646 | G11: =INDEX(tb_MHDI[],MATCH(Table3[[#This Row],[city_name]],tb_MHDI[mun_uf],0),6) -> 0.644 | H11: =INDEX(tb_MHDI[],MATCH(Table3[[#This Row],[city_name]],tb_MHDI[mun_uf],0),7) -> 0.781 | I11: =INDEX(tb_MHDI[],MATCH(Table3[[#This Row],[city_name]],tb_MHDI[mun_uf],0),8) -> 0.537 | J11: =_xlfn.NUMBERVALUE(INDEX(tb_SVI[],MATCH(Table3[[#This Row],[city_name]],tb_SVI[city_name_uf],0),8),".") -> 0.338 | K11: =_xlfn.NUMBERVALUE(INDEX(tb_SVI[],MATCH(Table3[[#This Row],[city_name]],tb_SVI[city_name_uf],0),9),".") -> 0.127 | L11: =_xlfn.NUMBERVALUE(INDEX(tb_SVI[],MATCH(Table3[[#This Row],[city_name]],tb_SVI[city_name_uf],0),10),".") -> 0.466 | M11: =_xlfn.NUMBERVALUE(INDEX(tb_SVI[],MATCH(Table3[[#This Row],[city_name]],tb_SVI[city_name_uf],0),11),".") -> 0.421 | N11: =_xlfn.PERCENTRANK.INC(Table3[MHDI_tot],Table3[[#This Row],[MHDI_tot]],3) -> 0.425
A12: =SVI!F12 -> São Francisco do Guaporé/RO | B12: =INDEX(tb_SVI[],MATCH(Table3[[#This Row],[ibge_cod]],tb_SVI[Município],0),1) -> RO | C12: =INDEX(tb_SVI[],MATCH(Table3[[#This Row],[city_name]],tb_SVI[city_name_uf],0),3) -> 1101492 | D12: BRA.22.43_1 | E12: =INDEX(tb_SVI[],MATCH(Table3[[#This Row],[city_name]],tb_SVI[city_name_uf],0),5) -> 20681 | F12: =INDEX(tb_MHDI[],MATCH(Table3[[#This Row],[city_name]],tb_MHDI[mun_uf],0),5) -> 0.611 | G12: =INDEX(tb_MHDI[],MATCH(Table3[[#This Row],[city_name]],tb_MHDI[mun_uf],0),6) -> 0.657 | H12: =INDEX(tb_MHDI[],MATCH(Table3[[#This Row],[city_name]],tb_MHDI[mun_uf],0),7) -> 0.751 | I12: =INDEX(tb_MHDI[],MATCH(Table3[[#This Row],[city_name]],tb_MHDI[mun_uf],0),8) -> 0.462 | J12: =_xlfn.NUMBERVALUE(INDEX(tb_SVI[],MATCH(Table3[[#This Row],[city_name]],tb_SVI[city_name_uf],0),8),".") -> 0.429 | K12: =_xlfn.NUMBERVALUE(INDEX(tb_SVI[],MATCH(Table3[[#This Row],[city_name]],tb_SVI[city_name_uf],0),9),".") -> 0.282 | L12: =_xlfn.NUMBERVALUE(INDEX(tb_SVI[],MATCH(Table3[[#This Row],[city_name]],tb_SVI[city_name_uf],0),10),".") -> 0.554 | M12: =_xlfn.NUMBERVALUE(INDEX(tb_SVI[],MATCH(Table3[[#This Row],[city_name]],tb_SVI[city_name_uf],0),11),".") -> 0.451 | N12: =_xlfn.PERCENTRANK.INC(Table3[MHDI_tot],Table3[[#This Row],[MHDI_tot]],3) -> 0.299
A13: =SVI!F13 -> São Felipe D'Oeste/RO | B13: =INDEX(tb_SVI[],MATCH(Table3[[#This Row],[ibge_cod]],tb_SVI[Município],0),1) -> RO | C13: =INDEX(tb_SVI[],MATCH(Table3[[#This Row],[city_name]],tb_SVI[city_name_uf],0),3) -> 1101484 | D13: BRA.22.42_1 | E13: =INDEX(tb_SVI[],MATCH(Table3[[#This Row],[city_name]],tb_SVI[city_name_uf],0),5) -> 5066 | F13: =INDEX(tb_MHDI[],MATCH(Table3[[#This Row],[city_name]],tb_MHDI[mun_uf],0),5) -> 0.649 | G13: =INDEX(tb_MHDI[],MATCH(Table3[[#This Row],[city_name]],tb_MHDI[mun_uf],0),6) -> 0.615 | H13: =INDEX(tb_MHDI[],MATCH(Table3[[#This Row],[city_name]],tb_MHDI[mun_uf],0),7) -> 0.78 | I13: =INDEX(tb_MHDI[],MATCH(Table3[[#This Row],[city_name]],tb_MHDI[mun_uf],0),8) -> 0.571 | J13: =_xlfn.NUMBERVALUE(INDEX(tb_SVI[],MATCH(Table3[[#This Row],[city_name]],tb_SVI[city_name_uf],0),8),".") -> 0.338 | K13: =_xlfn.NUMBERVALUE(INDEX(tb_SVI[],MATCH(Table3[[#This Row],[city_name]],tb_SVI[city_name_uf],0),9),".") -> 0.159 | L13: =_xlfn.NUMBERVALUE(INDEX(tb_SVI[],MATCH(Table3[[#This Row],[city_name]],tb_SVI[city_name_uf],0),10),".") -> 0.447 | M13: =_xlfn.NUMBERVALUE(INDEX(tb_SVI[],MATCH(Table3[[#This Row],[city_name]],tb_SVI[city_name_uf],0),11),".") -> 0.407 | N13: =_xlfn.PERCENTRANK.INC(Table3[MHDI_tot],Table3[[#This Row],[MHDI_tot]],3) -> 0.433
A14: =SVI!F14 -> Seringueiras/RO | B14: =INDEX(tb_SVI[],MATCH(Table3[[#This Row],[ibge_cod]],tb_SVI[Município],0),1) -> RO | C14: =INDEX(tb_SVI[],MATCH(Table3[[#This Row],[city_name]],tb_SVI[city_name_uf],0),3) -> 1101500 | D14: BRA.22.45_1 | E14: =INDEX(tb_SVI[],MATCH(Table3[[#This Row],[city_name]],tb_SVI[city_name_uf],0),5) -> 11851 | F14: =INDEX(tb_MHDI[],MATCH(Table3[[#This Row],[city_name]],tb_MHDI[mun_uf],0),5) -> 0.598 | G14: =INDEX(tb_MHDI[],MATCH(Table3[[#This Row],[city_name]],tb_MHDI[mun_uf],0),6) -> 0.644 | H14: =INDEX(tb_MHDI[],MATCH(Table3[[#This Row],[city_name]],tb_MHDI[mun_uf],0),7) -> 0.779 | I14: =INDEX(tb_MHDI[],MATCH(Table3[[#This Row],[city_name]],tb_MHDI[mun_uf],0),8) -> 0.427 | J14: =_xlfn.NUMBERVALUE(INDEX(tb_SVI[],MATCH(Table3[[#This Row],[city_name]],tb_SVI[city_name_uf],0),8),".") -> 0.401 | K14: =_xlfn.NUMBERVALUE(INDEX(tb_SVI[],MATCH(Table3[[#This Row],[city_name]],tb_SVI[city_name_uf],0),9),".") -> 0.194 | L14: =_xlfn.NUMBERVALUE(INDEX(tb_SVI[],MATCH(Table3[[#This Row],[city_name]],tb_SVI[city_name_uf],0),10),".") -> 0.447 | M14: =_xlfn.NUMBERVALUE(INDEX(tb_SVI[],MATCH(Table3[[#This Row],[city_name]],tb_SVI[city_name_uf],0),11),".") -> 0.563 | N14: =_xlfn.PERCENTRANK.INC(Table3[MHDI_tot],Table3[[#This Row],[MHDI_tot]],3) -> 0.242
A15: =SVI!F15 -> Santa Luzia D'Oeste/RO | B15: =INDEX(tb_SVI[],MATCH(Table3[[#This Row],[ibge_cod]],tb_SVI[Município],0),1) -> RO | C15: =INDEX(tb_SVI[],MATCH(Table3[[#This Row],[city_name]],tb_SVI[city_name_uf],0),3) -> 1100296 | D15: BRA.22.41_1 | E15: =INDEX(tb_SVI[],MATCH(Table3[[#This Row],[city_name]],tb_SVI[city_name_uf],0),5) -> 6216 | F15: =INDEX(tb_MHDI[],MATCH(Table3[[#This Row],[city_name]],tb_MHDI[mun_uf],0),5) -> 0.67 | G15: =INDEX(tb_MHDI[],MATCH(Table3[[#This Row],[city_name]],tb_MHDI[mun_uf],0),6) -> 0.657 | H15: =INDEX(tb_MHDI[],MATCH(Table3[[#This Row],[city_name]],tb_MHDI[mun_uf],0),7) -> 0.812 | I15: =INDEX(tb_MHDI[],MATCH(Table3[[#This Row],[city_name]],tb_MHDI[mun_uf],0),8) -> 0.564 | J15: =_xlfn.NUMBERVALUE(INDEX(tb_SVI[],MATCH(Table3[[#This Row],[city_name]],tb_SVI[city_name_uf],0),8),".") -> 0.364 | K15: =_xlfn.NUMBERVALUE(INDEX(tb_SVI[],MATCH(Table3[[#This Row],[city_name]],tb_SVI[city_name_uf],0),9),".") -> 0.254 | L15: =_xlfn.NUMBERVALUE(INDEX(tb_SVI[],MATCH(Table3[[#This Row],[city_name]],tb_SVI[city_name_uf],0),10),".") -> 0.375 | M15: =_xlfn.NUMBERVALUE(INDEX(tb_SVI[],MATCH(Table3[[#This Row],[city_name]],tb_SVI[city_name_uf],0),11),".") -> 0.463 | N15: =_xlfn.PERCENTRANK.INC(Table3[MHDI_tot],Table3[[#This Row],[MHDI_tot]],3) -> 0.516
A16: =SVI!F16 -> Rolim de Moura/RO | B16: =INDEX(tb_SVI[],MATCH(Table3[[#This Row],[ibge_cod]],tb_SVI[Município],0),1) -> RO | C16: =INDEX(tb_SVI[],MATCH(Table3[[#This Row],[city_name]],tb_SVI[city_name_uf],0),3) -> 1100288 | D16: BRA.22.40_1 | E16: =INDEX(tb_SVI[],MATCH(Table3[[#This Row],[city_name]],tb_SVI[city_name_uf],0),5) -> 55407 | F16: =INDEX(tb_MHDI[],MATCH(Table3[[#This Row],[city_name]],tb_MHDI[mun_uf],0),5) -> 0.7 | G16: =INDEX(tb_MHDI[],MATCH(Table3[[#This Row],[city_name]],tb_MHDI[mun_uf],0),6) -> 0.709 | H16: =INDEX(tb_MHDI[],MATCH(Table3[[#This Row],[city_name]],tb_MHDI[mun_uf],0),7) -> 0.808 | I16: =INDEX(tb_MHDI[],MATCH(Table3[[#This Row],[city_name]],tb_MHDI[mun_uf],0),8) -> 0.598 | J16: =_xlfn.NUMBERVALUE(INDEX(tb_SVI[],MATCH(Table3[[#This Row],[city_name]],tb_SVI[city_name_uf],0),8),".") -> 0.264 | K16: =_xlfn.NUMBERVALUE(INDEX(tb_SVI[],MATCH(Table3[[#This Row],[city_name]],tb_SVI[city_name_uf],0),9),".") -> 0.101 | L16: =_xlfn.NUMBERVALUE(INDEX(tb_SVI[],MATCH(Table3[[#This Row],[city_name]],tb_SVI[city_name_uf],0),10),".") -> 0.384 | M16: =_xlfn.NUMBERVALUE(INDEX(tb_SVI[],MATCH(Table3[[#This Row],[city_name]],tb_SVI[city_name_uf],0),11),".") -> 0.308 | N16: =_xlfn.PERCENTRANK.INC(Table3[MHDI_tot],Table3[[#This Row],[MHDI_tot]],3) -> 0.652
A17: =SVI!F17 -> Rio Crespo/RO | B17: =INDEX(tb_SVI[],MATCH(Table3[[#This Row],[ibge_cod]],tb_SVI[Município],0),1) -> RO | C17: =INDEX(tb_SVI[],MATCH(Table3[[#This Row],[city_name]],tb_SVI[city_name_uf],0),3) -> 1100262 | D17: BRA.22.39_1 | E17: =INDEX(tb_SVI[],MATCH(Table3[[#This Row],[city_name]],tb_SVI[city_name_uf],0),5) -> 3804 | F17: =INDEX(tb_MHDI[],MATCH(Table3[[#This Row],[city_name]],tb_MHDI[mun_uf],0),5) -> 0.643 | G17: =INDEX(tb_MHDI[],MATCH(Table3[[#This Row],[city_name]],tb_MHDI[mun_uf],0),6) -> 0.637 | H17: =INDEX(tb_MHDI[],MATCH(Table3[[#This Row],[city_name]],tb_MHDI[mun_uf],0),7) -> 0.813 | I17: =INDEX(tb_MHDI[],MATCH(Table3[[#This Row],[city_name]],tb_MHDI[mun_uf],0),8) -> 0.513 | J17: =_xlfn.NUMBERVALUE(INDEX(tb_SVI[],MATCH(Table3[[#This Row],[city_name]],tb_SVI[city_name_uf],0),8),".") -> 0.348 | K17: =_xlfn.NUMBERVALUE(INDEX(tb_SVI[],MATCH(Table3[[#This Row],[city_name]],tb_SVI[city_name_uf],0),9),".") -> 0.169 | L17: =_xlfn.NUMBERVALUE(INDEX(tb_SVI[],MATCH(Table3[[#This Row],[city_name]],tb_SVI[city_name_uf],0),10),".") -> 0.459 | M17: =_xlfn.NUMBERVALUE(INDEX(tb_SVI[],MATCH(Table3[[#This Row],[city_name]],tb_SVI[city_name_uf],0),11),".") -> 0.415 | N17: =_xlfn.PERCENTRANK.INC(Table3[MHDI_tot],Table3[[#This Row],[MHDI_tot]],3) -> 0.415
A18: =SVI!F18 -> Primavera de Rondônia/RO | B18: =INDEX(tb_SVI[],MATCH(Table3[[#This Row],[ibge_cod]],tb_SVI[Município],0),1) -> RO | C18: =INDEX(tb_SVI[],MATCH(Table3[[#This Row],[city_name]],tb_SVI[city_name_uf],0),3) -> 1101476 | D18: BRA.22.38_1 | E18: =INDEX(tb_SVI[],MATCH(Table3[[#This Row],[city_name]],tb_SVI[city_name_uf],0),5) -> 2776 | F18: =INDEX(tb_MHDI[],MATCH(Table3[[#This Row],[city_name]],tb_MHDI[mun_uf],0),5) -> 0.641 | G18: =INDEX(tb_MHDI[],MATCH(Table3[[#This Row],[city_name]],tb_MHDI[mun_uf],0),6) -> 0.645 | H18: =INDEX(tb_MHDI[],MATCH(Table3[[#This Row],[city_name]],tb_MHDI[mun_uf],0),7) -> 0.799 | I18: =INDEX(tb_MHDI[],MATCH(Table3[[#This Row],[city_name]],tb_MHDI[mun_uf],0),8) -> 0.512 | J18: =_xlfn.NUMBERVALUE(INDEX(tb_SVI[],MATCH(Table3[[#This Row],[city_name]],tb_SVI[city_name_uf],0),8),".") -> 0.298 | K18: =_xlfn.NUMBERVALUE(INDEX(tb_SVI[],MATCH(Table3[[#This Row],[city_name]],tb_SVI[city_name_uf],0),9),".") -> 0.067 | L18: =_xlfn.NUMBERVALUE(INDEX(tb_SVI[],MATCH(Table3[[#This Row],[city_name]],tb_SVI[city_name_uf],0),10),".") -> 0.364 | M18: =_xlfn.NUMBERVALUE(INDEX(tb_SVI[],MATCH(Table3[[#This Row],[city_name]],tb_SVI[city_name_uf],0),11),".") -> 0.463 | N18: =_xlfn.PERCENTRANK.INC(Table3[MHDI_tot],Table3[[#This Row],[MHDI_tot]],3) -> 0.408
... A44: =SVI!F44 -> Campo Novo de Rondônia/RO | B44: =INDEX(tb_SVI[],MATCH(Table3[[#This Row],[ibge_cod]],tb_SVI[Município],0),1) -> RO | C44: =INDEX(tb_SVI[],MATCH(Table3[[#This Row],[city_name]],tb_SVI[city_name_uf],0),3) -> 1100700 | D44: BRA.22.9_1 | E44: =INDEX(tb_SVI[],MATCH(Table3[[#This Row],[city_name]],tb_SVI[city_name_uf],0),5) -> 14266 | F44: =INDEX(tb_MHDI[],MATCH(Table3[[#This Row],[city_name]],tb_MHDI[mun_uf],0),5) -> 0.593 | G44: =INDEX(tb_MHDI[],MATCH(Table3[[#This Row],[city_name]],tb_MHDI[mun_uf],0),6) -> 0.667 | H44: =INDEX(tb_MHDI[],MATCH(Table3[[#This Row],[city_name]],tb_MHDI[mun_uf],0),7) -> 0.772 | I44: =INDEX(tb_MHDI[],MATCH(Table3[[#This Row],[city_name]],tb_MHDI[mun_uf],0),8) -> 0.404 | J44: =_xlfn.NUMBERVALUE(INDEX(tb_SVI[],MATCH(Table3[[#This Row],[city_name]],tb_SVI[city_name_uf],0),8),".") -> 0.482 | K44: =_xlfn.NUMBERVALUE(INDEX(tb_SVI[],MATCH(Table3[[#This Row],[city_name]],tb_SVI[city_name_uf],0),9),".") -> 0.407 | L44: =_xlfn.NUMBERVALUE(INDEX(tb_SVI[],MATCH(Table3[[#This Row],[city_name]],tb_SVI[city_name_uf],0),10),".") -> 0.622 | M44: =_xlfn.NUMBERVALUE(INDEX(tb_SVI[],MATCH(Table3[[#This Row],[city_name]],tb_SVI[city_name_uf],0),11),".") -> 0.417 | N44: =_xlfn.PERCENTRANK.INC(Table3[MHDI_tot],Table3[[#This Row],[MHDI_tot]],3) -> 0.221
A45: =SVI!F67 -> Jordão/AC | B45: =INDEX(tb_SVI[],MATCH(Table3[[#This Row],[ibge_cod]],tb_SVI[Município],0),1) -> AC | C45: =INDEX(tb_SVI[],MATCH(Table3[[#This Row],[city_name]],tb_SVI[city_name_uf],0),3) -> 1200328 | D45: BRA.1.9_1 | E45: =INDEX(tb_SVI[],MATCH(Table3[[#This Row],[city_name]],tb_SVI[city_name_uf],0),5) -> 8473 | F45: =INDEX(tb_MHDI[],MATCH(Table3[[#This Row],[city_name]],tb_MHDI[mun_uf],0),5) -> 0.469 | G45: =INDEX(tb_MHDI[],MATCH(Table3[[#This Row],[city_name]],tb_MHDI[mun_uf],0),6) -> 0.499 | H45: =INDEX(tb_MHDI[],MATCH(Table3[[#This Row],[city_name]],tb_MHDI[mun_uf],0),7) -> 0.731 | I45: =INDEX(tb_MHDI[],MATCH(Table3[[#This Row],[city_name]],tb_MHDI[mun_uf],0),8) -> 0.283 | J45: =_xlfn.NUMBERVALUE(INDEX(tb_SVI[],MATCH(Table3[[#This Row],[city_name]],tb_SVI[city_name_uf],0),8),".") -> 0.584 | K45: =_xlfn.NUMBERVALUE(INDEX(tb_SVI[],MATCH(Table3[[#This Row],[city_name]],tb_SVI[city_name_uf],0),9),".") -> 0.437 | L45: =_xlfn.NUMBERVALUE(INDEX(tb_SVI[],MATCH(Table3[[#This Row],[city_name]],tb_SVI[city_name_uf],0),10),".") -> 0.779 | M45: =_xlfn.NUMBERVALUE(INDEX(tb_SVI[],MATCH(Table3[[#This Row],[city_name]],tb_SVI[city_name_uf],0),11),".") -> 0.535 | N45: =_xlfn.PERCENTRANK.INC(Table3[MHDI_tot],Table3[[#This Row],[MHDI_tot]],3) -> 0.001
A46: =SVI!F46 -> Cacaulândia/RO | B46: =INDEX(tb_SVI[],MATCH(Table3[[#This Row],[ibge_cod]],tb_SVI[Município],0),1) -> RO | C46: =INDEX(tb_SVI[],MATCH(Table3[[#This Row],[city_name]],tb_SVI[city_name_uf],0),3) -> 1100601 | D46: BRA.22.7_1 | E46: =INDEX(tb_SVI[],MATCH(Table3[[#This Row],[city_name]],tb_SVI[city_name_uf],0),5) -> 6269 | F46: =INDEX(tb_MHDI[],MATCH(Table3[[#This Row],[city_name]],tb_MHDI[mun_uf],0),5) -> 0.646 | G46: =INDEX(tb_MHDI[],MATCH(Table3[[#This Row],[city_name]],tb_MHDI[mun_uf],0),6) -> 0.664 | H46: =INDEX(tb_MHDI[],MATCH(Table3[[#This Row],[city_name]],tb_MHDI[mun_uf],0),7) -> 0.801 | I46: =INDEX(tb_MHDI[],MATCH(Table3[[#This Row],[city_name]],tb_MHDI[mun_uf],0),8) -> 0.506 | J46: =_xlfn.NUMBERVALUE(INDEX(tb_SVI[],MATCH(Table3[[#This Row],[city_name]],tb_SVI[city_name_uf],0),8),".") -> 0.335 | K46: =_xlfn.NUMBERVALUE(INDEX(tb_SVI[],MATCH(Table3[[#This Row],[city_name]],tb_SVI[city_name_uf],0),9),".") -> 0.131 | L46: =_xlfn.NUMBERVALUE(INDEX(tb_SVI[],MATCH(Table3[[#This Row],[city_name]],tb_SVI[city_name_uf],0),10),".") -> 0.47 | M46: =_xlfn.NUMBERVALUE(INDEX(tb_SVI[],MATCH(Table3[[#This Row],[city_name]],tb_SVI[city_name_uf],0),11),".") -> 0.405 | N46: =_xlfn.PERCENTRANK.INC(Table3[MHDI_tot],Table3[[#This Row],[MHDI_tot]],3) -> 0.425
A47: =SVI!F47 -> Cabixi/RO | B47: =INDEX(tb_SVI[],MATCH(Table3[[#This Row],[ibge_cod]],tb_SVI[Município],0),1) -> RO | C47: =INDEX(tb_SVI[],MATCH(Table3[[#This Row],[city_name]],tb_SVI[city_name_uf],0),3) -> 1100031 | D47: BRA.12.19_1 | E47: =INDEX(tb_SVI[],MATCH(Table3[[#This Row],[city_name]],tb_SVI[city_name_uf],0),5) -> 5188 | F47: =INDEX(tb_MHDI[],MATCH(Table3[[#This Row],[city_name]],tb_MHDI[mun_uf],0),5) -> 0.65 | G47: =INDEX(tb_MHDI[],MATCH(Table3[[#This Row],[city_name]],tb_MHDI[mun_uf],0),6) -> 0.65 | H47: =INDEX(tb_MHDI[],MATCH(Table3[[#This Row],[city_name]],tb_MHDI[mun_uf],0),7) -> 0.757 | I47: =INDEX(tb_MHDI[],MATCH(Table3[[#This Row],[city_name]],tb_MHDI[mun_uf],0),8) -> 0.559 | J47: =_xlfn.NUMBERVALUE(INDEX(tb_SVI[],MATCH(Table3[[#This Row],[city_name]],tb_SVI[city_name_uf],0),8),".") -> 0.3 | K47: =_xlfn.NUMBERVALUE(INDEX(tb_SVI[],MATCH(Table3[[#This Row],[city_name]],tb_SVI[city_name_uf],0),9),".") -> 0.128 | L47: =_xlfn.NUMBERVALUE(INDEX(tb_SVI[],MATCH(Table3[[#This Row],[city_name]],tb_SVI[city_name_uf],0),10),".") -> 0.389 | M47: =_xlfn.NUMBERVALUE(INDEX(tb_SVI[],MATCH(Table3[[#This Row],[city_name]],tb_SVI[city_name_uf],0),11),".") -> 0.383 | N47: =_xlfn.PERCENTRANK.INC(Table3[MHDI_tot],Table3[[#This Row],[MHDI_tot]],3) -> 0.436
A48: =SVI!F48 -> Buritis/RO | B48: =INDEX(tb_SVI[],MATCH(Table3[[#This Row],[ibge_cod]],tb_SVI[Município],0),1) -> RO | C48: =INDEX(tb_SVI[],MATCH(Table3[[#This Row],[city_name]],tb_SVI[city_name_uf],0),3) -> 1100452 | D48: BRA.22.6_1 | E48: =INDEX(tb_SVI[],MATCH(Table3[[#This Row],[city_name]],tb_SVI[city_name_uf],0),5) -> 40356 | F48: =INDEX(tb_MHDI[],MATCH(Table3[[#This Row],[city_name]],tb_MHDI[mun_uf],0),5) -> 0.616 | G48: =INDEX(tb_MHDI[],MATCH(Table3[[#This Row],[city_name]],tb_MHDI[mun_uf],0),6) -> 0.65 | H48: =INDEX(tb_MHDI[],MATCH(Table3[[#This Row],[city_name]],tb_MHDI[mun_uf],0),7) -> 0.751 | I48: =INDEX(tb_MHDI[],MATCH(Table3[[#This Row],[city_name]],tb_MHDI[mun_uf],0),8) -> 0.479 | J48: =_xlfn.NUMBERVALUE(INDEX(tb_SVI[],MATCH(Table3[[#This Row],[city_name]],tb_SVI[city_name_uf],0),8),".") -> 0.38 | K48: =_xlfn.NUMBERVALUE(INDEX(tb_SVI[],MATCH(Table3[[#This Row],[city_name]],tb_SVI[city_name_uf],0),9),".") -> 0.191 | L48: =_xlfn.NUMBERVALUE(INDEX(tb_SVI[],MATCH(Table3[[#This Row],[city_name]],tb_SVI[city_name_uf],0),10),".") -> 0.487 | M48: =_xlfn.NUMBERVALUE(INDEX(tb_SVI[],MATCH(Table3[[#This Row],[city_name]],tb_SVI[city_name_uf],0),11),".") -> 0.462 | N48: =_xlfn.PERCENTRANK.INC(Table3[MHDI_tot],Table3[[#This Row],[MHDI_tot]],3) -> 0.318
A49: =SVI!F49 -> Ariquemes/RO | B49: =INDEX(tb_SVI[],MATCH(Table3[[#This Row],[ibge_cod]],tb_SVI[Município],0),1) -> RO | C49: =INDEX(tb_SVI[],MATCH(Table3[[#This Row],[city_name]],tb_SVI[city_name_uf],0),3) -> 1100023 | D49: BRA.22.5_1 | E49: =INDEX(tb_SVI[],MATCH(Table3[[#This Row],[city_name]],tb_SVI[city_name_uf],0),5) -> 109523 | F49: =INDEX(tb_MHDI[],MATCH(Table3[[#This Row],[city_name]],tb_MHDI[mun_uf],0),5) -> 0.702 | G49: =INDEX(tb_MHDI[],MATCH(Table3[[#This Row],[city_name]],tb_MHDI[mun_uf],0),6) -> 0.716 | H49: =INDEX(tb_MHDI[],MATCH(Table3[[#This Row],[city_name]],tb_MHDI[mun_uf],0),7) -> 0.806 | I49: =INDEX(tb_MHDI[],MATCH(Table3[[#This Row],[city_name]],tb_MHDI[mun_uf],0),8) -> 0.6 | J49: =_xlfn.NUMBERVALUE(INDEX(tb_SVI[],MATCH(Table3[[#This Row],[city_name]],tb_SVI[city_name_uf],0),8),".") -> 0.268 | K49: =_xlfn.NUMBERVALUE(INDEX(tb_SVI[],MATCH(Table3[[#This Row],[city_name]],tb_SVI[city_name_uf],0),9),".") -> 0.149 | L49: =_xlfn.NUMBERVALUE(INDEX(tb_SVI[],MATCH(Table3[[#This Row],[city_name]],tb_SVI[city_name_uf],0),10),".") -> 0.384 | M49: =_xlfn.NUMBERVALUE(INDEX(tb_SVI[],MATCH(Table3[[#This Row],[city_name]],tb_SVI[city_name_uf],0),11),".") -> 0.271 | N49: =_xlfn.PERCENTRANK.INC(Table3[MHDI_tot],Table3[[#This Row],[MHDI_tot]],3) -> 0.664
A50: =SVI!F50 -> Alvorada D'Oeste/RO | B50: =INDEX(tb_SVI[],MATCH(Table3[[#This Row],[ibge_cod]],tb_SVI[Município],0),1) -> RO | C50: =INDEX(tb_SVI[],MATCH(Table3[[#This Row],[city_name]],tb_SVI[city_name_uf],0),3) -> 1100346 | D50: BRA.22.4_1 | E50: =INDEX(tb_SVI[],MATCH(Table3[[#This Row],[city_name]],tb_SVI[city_name_uf],0),5) -> 14106 | F50: =INDEX(tb_MHDI[],MATCH(Table3[[#This Row],[city_name]],tb_MHDI[mun_uf],0),5) -> 0.643 | G50: =INDEX(tb_MHDI[],MATCH(Table3[[#This Row],[city_name]],tb_MHDI[mun_uf],0),6) -> 0.654 | H50: =INDEX(tb_MHDI[],MATCH(Table3[[#This Row],[city_name]],tb_MHDI[mun_uf],0),7) -> 0.763 | I50: =INDEX(tb_MHDI[],MATCH(Table3[[#This Row],[city_name]],tb_MHDI[mun_uf],0),8) -> 0.534 | J50: =_xlfn.NUMBERVALUE(INDEX(tb_SVI[],MATCH(Table3[[#This Row],[city_name]],tb_SVI[city_name_uf],0),8),".") -> 0.346 | K50: =_xlfn.NUMBERVALUE(INDEX(tb_SVI[],MATCH(Table3[[#This Row],[city_name]],tb_SVI[city_name_uf],0),9),".") -> 0.232 | L50: =_xlfn.NUMBERVALUE(INDEX(tb_SVI[],MATCH(Table3[[#This Row],[city_name]],tb_SVI[city_name_uf],0),10),".") -> 0.411 | M50: =_xlfn.NUMBERVALUE(INDEX(tb_SVI[],MATCH(Table3[[#This Row],[city_name]],tb_SVI[city_name_uf],0),11),".") -> 0.394 | N50: =_xlfn.PERCENTRANK.INC(Table3[MHDI_tot],Table3[[#This Row],[MHDI_tot]],3) -> 0.415
A51: =SVI!F51 -> Alto Paraíso/RO | B51: =INDEX(tb_SVI[],MATCH(Table3[[#This Row],[ibge_cod]],tb_SVI[Município],0),1) -> RO | C51: =INDEX(tb_SVI[],MATCH(Table3[[#This Row],[city_name]],tb_SVI[city_name_uf],0),3) -> 1100403 | D51: BRA.22.3_1 | E51: =INDEX(tb_SVI[],MATCH(Table3[[#This Row],[city_name]],tb_SVI[city_name_uf],0),5) -> 21847 | F51: =INDEX(tb_MHDI[],MATCH(Table3[[#This Row],[city_name]],tb_MHDI[mun_uf],0),5) -> 0.625 | G51: =INDEX(tb_MHDI[],MATCH(Table3[[#This Row],[city_name]],tb_MHDI[mun_uf],0),6) -> 0.664 | H51: =INDEX(tb_MHDI[],MATCH(Table3[[#This Row],[city_name]],tb_MHDI[mun_uf],0),7) -> 0.804 | I51: =INDEX(tb_MHDI[],MATCH(Table3[[#This Row],[city_name]],tb_MHDI[mun_uf],0),8) -> 0.457 | J51: =_xlfn.NUMBERVALUE(INDEX(tb_SVI[],MATCH(Table3[[#This Row],[city_name]],tb_SVI[city_name_uf],0),8),".") -> 0.372 | K51: =_xlfn.NUMBERVALUE(INDEX(tb_SVI[],MATCH(Table3[[#This Row],[city_name]],tb_SVI[city_name_uf],0),9),".") -> 0.23 | L51: =_xlfn.NUMBERVALUE(INDEX(tb_SVI[],MATCH(Table3[[#This Row],[city_name]],tb_SVI[city_name_uf],0),10),".") -> 0.453 | M51: =_xlfn.NUMBERVALUE(INDEX(tb_SVI[],MATCH(Table3[[#This Row],[city_name]],tb_SVI[city_name_uf],0),11),".") -> 0.432 | N51: =_xlfn.PERCENTRANK.INC(Table3[MHDI_tot],Table3[[#This Row],[MHDI_tot]],3) -> 0.352
A52: =SVI!F52 -> Alto Alegre dos Parecis/RO | B52: =INDEX(tb_SVI[],MATCH(Table3[[#This Row],[ibge_cod]],tb_SVI[Município],0),1) -> RO | C52: =INDEX(tb_SVI[],MATCH(Table3[[#This Row],[city_name]],tb_SVI[city_name_uf],0),3) -> 1100379 | D52: BRA.22.2_1 | E52: =INDEX(tb_SVI[],MATCH(Table3[[#This Row],[city_name]],tb_SVI[city_name_uf],0),5) -> 13255 | F52: =INDEX(tb_MHDI[],MATCH(Table3[[#This Row],[city_name]],tb_MHDI[mun_uf],0),5) -> 0.592 | G52: =INDEX(tb_MHDI[],MATCH(Table3[[#This Row],[city_name]],tb_MHDI[mun_uf],0),6) -> 0.603 | H52: =INDEX(tb_MHDI[],MATCH(Table3[[#This Row],[city_name]],tb_MHDI[mun_uf],0),7) -> 0.777 | I52: =INDEX(tb_MHDI[],MATCH(Table3[[#This Row],[city_name]],tb_MHDI[mun_uf],0),8) -> 0.443 | J52: =_xlfn.NUMBERVALUE(INDEX(tb_SVI[],MATCH(Table3[[#This Row],[city_name]],tb_SVI[city_name_uf],0),8),".") -> 0.418 | K52: =_xlfn.NUMBERVALUE(INDEX(tb_SVI[],MATCH(Table3[[#This Row],[city_name]],tb_SVI[city_name_uf],0),9),".") -> 0.24 | L52: =_xlfn.NUMBERVALUE(INDEX(tb_SVI[],MATCH(Table3[[#This Row],[city_name]],tb_SVI[city_name_uf],0),10),".") -> 0.477 | M52: =_xlfn.NUMBERVALUE(INDEX(tb_SVI[],MATCH(Table3[[#This Row],[city_name]],tb_SVI[city_name_uf],0),11),".") -> 0.537 | N52: =_xlfn.PERCENTRANK.INC(Table3[MHDI_tot],Table3[[#This Row],[MHDI_tot]],3) -> 0.214
A53: =SVI!F53 -> Alta Floresta D'Oeste/RO | B53: =INDEX(tb_SVI[],MATCH(Table3[[#This Row],[ibge_cod]],tb_SVI[Município],0),1) -> RO | C53: =INDEX(tb_SVI[],MATCH(Table3[[#This Row],[city_name]],tb_SVI[city_name_uf],0),3) -> 1100015 | D53: BRA.22.1_1 | E53: =INDEX(tb_SVI[],MATCH(Table3[[#This Row],[city_name]],tb_SVI[city_name_uf],0),5) -> 22728 | F53: =INDEX(tb_MHDI[],MATCH(Table3[[#This Row],[city_name]],tb_MHDI[mun_uf],0),5) -> 0.641 | G53: =INDEX(tb_MHDI[],MATCH(Table3[[#This Row],[city_name]],tb_MHDI[mun_uf],0),6) -> 0.657 | H53: =INDEX(tb_MHDI[],MATCH(Table3[[#This Row],[city_name]],tb_MHDI[mun_uf],0),7) -> 0.763 | I53: =INDEX(tb_MHDI[],MATCH(Table3[[#This Row],[city_name]],tb_MHDI[mun_uf],0),8) -> 0.526 | J53: =_xlfn.NUMBERVALUE(INDEX(tb_SVI[],MATCH(Table3[[#This Row],[city_name]],tb_SVI[city_name_uf],0),8),".") -> 0.376 | K53: =_xlfn.NUMBERVALUE(INDEX(tb_SVI[],MATCH(Table3[[#This Row],[city_name]],tb_SVI[city_name_uf],0),9),".") -> 0.306 | L53: =_xlfn.NUMBERVALUE(INDEX(tb_SVI[],MATCH(Table3[[#This Row],[city_name]],tb_SVI[city_name_uf],0),10),".") -> 0.45 | M53: =_xlfn.NUMBERVALUE(INDEX(tb_SVI[],MATCH(Table3[[#This Row],[city_name]],tb_SVI[city_name_uf],0),11),".") -> 0.373 | N53: =_xlfn.PERCENTRANK.INC(Table3[MHDI_tot],Table3[[#This Row],[MHDI_tot]],3) -> 0.408
A54: =SVI!F54 -> Xapuri/AC | B54: =INDEX(tb_SVI[],MATCH(Table3[[#This Row],[ibge_cod]],tb_SVI[Município],0),1) -> AC | C54: =INDEX(tb_SVI[],MATCH(Table3[[#This Row],[city_name]],tb_SVI[city_name_uf],0),3) -> 1200708 | D54: BRA.1.22_1 | E54: =INDEX(tb_SVI[],MATCH(Table3[[#This Row],[city_name]],tb_SVI[city_name_uf],0),5) -> 19596 | F54: =INDEX(tb_MHDI[],MATCH(Table3[[#This Row],[city_name]],tb_MHDI[mun_uf],0),5) -> 0.599 | G54: =INDEX(tb_MHDI[],MATCH(Table3[[#This Row],[city_name]],tb_MHDI[mun_uf],0),6) -> 0.621 | H54: =INDEX(tb_MHDI[],MATCH(Table3[[#This Row],[city_name]],tb_MHDI[mun_uf],0),7) -> 0.773 | I54: =INDEX(tb_MHDI[],MATCH(Table3[[#This Row],[city_name]],tb_MHDI[mun_uf],0),8) -> 0.448 | J54: =_xlfn.NUMBERVALUE(INDEX(tb_SVI[],MATCH(Table3[[#This Row],[city_name]],tb_SVI[city_name_uf],0),8),".") -> 0.49 | K54: =_xlfn.NUMBERVALUE(INDEX(tb_SVI[],MATCH(Table3[[#This Row],[city_name]],tb_SVI[city_name_uf],0),9),".") -> 0.341 | L54: =_xlfn.NUMBERVALUE(INDEX(tb_SVI[],MATCH(Table3[[#This Row],[city_name]],tb_SVI[city_name_uf],0),10),".") -> 0.661 | M54: =_xlfn.NUMBERVALUE(INDEX(tb_SVI[],MATCH(Table3[[#This Row],[city_name]],tb_SVI[city_name_uf],0),11),".") -> 0.468 | N54: =_xlfn.PERCENTRANK.INC(Table3[MHDI_tot],Table3[[#This Row],[MHDI_tot]],3) -> 0.245
A55: =SVI!F55 -> Tarauacá/AC | B55: =INDEX(tb_SVI[],MATCH(Table3[[#This Row],[ibge_cod]],tb_SVI[Município],0),1) -> AC | C55: =INDEX(tb_SVI[],MATCH(Table3[[#This Row],[city_name]],tb_SVI[city_name_uf],0),3) -> 1200609 | D55: BRA.1.21_1 | E55: =INDEX(tb_SVI[],MATCH(Table3[[#This Row],[city_name]],tb_SVI[city_name_uf],0),5) -> 43151 | F55: =INDEX(tb_MHDI[],MATCH(Table3[[#This Row],[city_name]],tb_MHDI[mun_uf],0),5) -> 0.539 | G55: =INDEX(tb_MHDI[],MATCH(Table3[[#This Row],[city_name]],tb_MHDI[mun_uf],0),6) -> 0.554 | H55: =INDEX(tb_MHDI[],MATCH(Table3[[#This Row],[city_name]],tb_MHDI[mun_uf],0),7) -> 0.72 | I55: =INDEX(tb_MHDI[],MATCH(Table3[[#This Row],[city_name]],tb_MHDI[mun_uf],0),8) -> 0.392 | J55: =_xlfn.NUMBERVALUE(INDEX(tb_SVI[],MATCH(Table3[[#This Row],[city_name]],tb_SVI[city_name_uf],0),8),".") -> 0.585 | K55: =_xlfn.NUMBERVALUE(INDEX(tb_SVI[],MATCH(Table3[[#This Row],[city_name]],tb_SVI[city_name_uf],0),9),".") -> 0.46 | L55: =_xlfn.NUMBERVALUE(INDEX(tb_SVI[],MATCH(Table3[[#This Row],[city_name]],tb_SVI[city_name_uf],0),10),".") -> 0.773 | M55: =_xlfn.NUMBERVALUE(INDEX(tb_SVI[],MATCH(Table3[[#This Row],[city_name]],tb_SVI[city_name_uf],0),11),".") -> 0.522 | N55: =_xlfn.PERCENTRANK.INC(Table3[MHDI_tot],Table3[[#This Row],[MHDI_tot]],3) -> 0.04
A56: =SVI!F56 -> Senador Guiomard/AC | B56: =INDEX(tb_SVI[],MATCH(Table3[[#This Row],[ibge_cod]],tb_SVI[Município],0),1) -> AC | C56: =INDEX(tb_SVI[],MATCH(Table3[[#This Row],[city_name]],tb_SVI[city_name_uf],0),3) -> 1200450 | D56: BRA.1.20_1 | E56: =INDEX(tb_SVI[],MATCH(Table3[[#This Row],[city_name]],tb_SVI[city_name_uf],0),5) -> 23236 | F56: =INDEX(tb_MHDI[],MATCH(Table3[[#This Row],[city_name]],tb_MHDI[mun_uf],0),5) -> 0.64 | G56: =INDEX(tb_MHDI[],MATCH(Table3[[#This Row],[city_name]],tb_MHDI[mun_uf],0),6) -> 0.649 | H56: =INDEX(tb_MHDI[],MATCH(Table3[[#This Row],[city_name]],tb_MHDI[mun_uf],0),7) -> 0.786 | I56: =INDEX(tb_MHDI[],MATCH(Table3[[#This Row],[city_name]],tb_MHDI[mun_uf],0),8) -> 0.513 | J56: =_xlfn.NUMBERVALUE(INDEX(tb_SVI[],MATCH(Table3[[#This Row],[city_name]],tb_SVI[city_name_uf],0),8),".") -> 0.431 | K56: =_xlfn.NUMBERVALUE(INDEX(tb_SVI[],MATCH(Table3[[#This Row],[city_name]],tb_SVI[city_name_uf],0),9),".") -> 0.335 | L56: =_xlfn.NUMBERVALUE(INDEX(tb_SVI[],MATCH(Table3[[#This Row],[city_name]],tb_SVI[city_name_uf],0),10),".") -> 0.574 | M56: =_xlfn.NUMBERVALUE(INDEX(tb_SVI[],MATCH(Table3[[#This Row],[city_name]],tb_SVI[city_name_uf],0),11),".") -> 0.384 | N56: =_xlfn.PERCENTRANK.INC(Table3[MHDI_tot],Table3[[#This Row],[MHDI_tot]],3) -> 0.405
A57: =SVI!F57 -> Sena Madureira/AC | B57: =INDEX(tb_SVI[],MATCH(Table3[[#This Row],[ibge_cod]],tb_SVI[Município],0),1) -> AC | C57: =INDEX(tb_SVI[],MATCH(Table3[[#This Row],[city_name]],tb_SVI[city_name_uf],0),3) -> 1200500 | D57: BRA.1.19_1 | E57: =INDEX(tb_SVI[],MATCH(Table3[[#This Row],[city_name]],tb_SVI[city_name_uf],0),5) -> 46511 | F57: =INDEX(tb_MHDI[],MATCH(Table3[[#This Row],[city_name]],tb_MHDI[mun_uf],0),5) -> 0.603 | G57: =INDEX(tb_MHDI[],MATCH(Table3[[#This Row],[city_name]],tb_MHDI[mun_uf],0),6) -> 0.593 | H57: =INDEX(tb_MHDI[],MATCH(Table3[[#This Row],[city_name]],tb_MHDI[mun_uf],0),7) -> 0.81 | I57: =INDEX(tb_MHDI[],MATCH(Table3[[#This Row],[city_name]],tb_MHDI[mun_uf],0),8) -> 0.456 | J57: =_xlfn.NUMBERVALUE(INDEX(tb_SVI[],MATCH(Table3[[#This Row],[city_name]],tb_SVI[city_name_uf],0),8),".") -> 0.563 | K57: =_xlfn.NUMBERVALUE(INDEX(tb_SVI[],MATCH(Table3[[#This Row],[city_name]],tb_SVI[city_name_uf],0),9),".") -> 0.475 | L57: =_xlfn.NUMBERVALUE(INDEX(tb_SVI[],MATCH(Table3[[#This Row],[city_name]],tb_SVI[city_name_uf],0),10),".") -> 0.715 | M57: =_xlfn.NUMBERVALUE(INDEX(tb_SVI[],MATCH(Table3[[#This Row],[city_name]],tb_SVI[city_name_uf],0),11),".") -> 0.498 | N57: =_xlfn.PERCENTRANK.INC(Table3[MHDI_tot],Table3[[#This Row],[MHDI_tot]],3) -> 0.263
... A66: =SVI!F66 -> Manoel Urbano/AC | B66: =INDEX(tb_SVI[],MATCH(Table3[[#This Row],[ibge_cod]],tb_SVI[Município],0),1) -> AC | C66: =INDEX(tb_SVI[],MATCH(Table3[[#This Row],[city_name]],tb_SVI[city_name_uf],0),3) -> 1200344 | D66: BRA.1.11_1 | E66: =INDEX(tb_SVI[],MATCH(Table3[[#This Row],[city_name]],tb_SVI[city_name_uf],0),5) -> 9581 | F66: =INDEX(tb_MHDI[],MATCH(Table3[[#This Row],[city_name]],tb_MHDI[mun_uf],0),5) -> 0.551 | G66: =INDEX(tb_MHDI[],MATCH(Table3[[#This Row],[city_name]],tb_MHDI[mun_uf],0),6) -> 0.586 | H66: =INDEX(tb_MHDI[],MATCH(Table3[[#This Row],[city_name]],tb_MHDI[mun_uf],0),7) -> 0.767 | I66: =INDEX(tb_MHDI[],MATCH(Table3[[#This Row],[city_name]],tb_MHDI[mun_uf],0),8) -> 0.373 | J66: =_xlfn.NUMBERVALUE(INDEX(tb_SVI[],MATCH(Table3[[#This Row],[city_name]],tb_SVI[city_name_uf],0),8),".") -> 0.589 | K66: =_xlfn.NUMBERVALUE(INDEX(tb_SVI[],MATCH(Table3[[#This Row],[city_name]],tb_SVI[city_name_uf],0),9),".") -> 0.531 | L66: =_xlfn.NUMBERVALUE(INDEX(tb_SVI[],MATCH(Table3[[#This Row],[city_name]],tb_SVI[city_name_uf],0),10),".") -> 0.775 | M66: =_xlfn.NUMBERVALUE(INDEX(tb_SVI[],MATCH(Table3[[#This Row],[city_name]],tb_SVI[city_name_uf],0),11),".") -> 0.461 | N66: =_xlfn.PERCENTRANK.INC(Table3[MHDI_tot],Table3[[#This Row],[MHDI_tot]],3) -> 0.066
A67: =SVI!F180 -> Bagre/PA | B67: =INDEX(tb_SVI[],MATCH(Table3[[#This Row],[ibge_cod]],tb_SVI[Município],0),1) -> PA | C67: =INDEX(tb_SVI[],MATCH(Table3[[#This Row],[city_name]],tb_SVI[city_name_uf],0),3) -> 1501105 | D67: BRA.14.15_1 | E67: =INDEX(tb_SVI[],MATCH(Table3[[#This Row],[city_name]],tb_SVI[city_name_uf],0),5) -> 31325 | F67: =INDEX(tb_MHDI[],MATCH(Table3[[#This Row],[city_name]],tb_MHDI[mun_uf],0),5) -> 0.471 | G67: =INDEX(tb_MHDI[],MATCH(Table3[[#This Row],[city_name]],tb_MHDI[mun_uf],0),6) -> 0.481 | H67: =INDEX(tb_MHDI[],MATCH(Table3[[#This Row],[city_name]],tb_MHDI[mun_uf],0),7) -> 0.777 | I67: =INDEX(tb_MHDI[],MATCH(Table3[[#This Row],[city_name]],tb_MHDI[mun_uf],0),8) -> 0.28 | J67: =_xlfn.NUMBERVALUE(INDEX(tb_SVI[],MATCH(Table3[[#This Row],[city_name]],tb_SVI[city_name_uf],0),8),".") -> 0.676 | K67: =_xlfn.NUMBERVALUE(INDEX(tb_SVI[],MATCH(Table3[[#This Row],[city_name]],tb_SVI[city_name_uf],0),9),".") -> 0.617 | L67: =_xlfn.NUMBERVALUE(INDEX(tb_SVI[],MATCH(Table3[[#This Row],[city_name]],tb_SVI[city_name_uf],0),10),".") -> 0.74 | M67: =_xlfn.NUMBERVALUE(INDEX(tb_SVI[],MATCH(Table3[[#This Row],[city_name]],tb_SVI[city_name_uf],0),11),".") -> 0.672 | N67: =_xlfn.PERCENTRANK.INC(Table3[MHDI_tot],Table3[[#This Row],[MHDI_tot]],3) -> 0.001
A68: =SVI!F68 -> Feijó/AC | B68: =INDEX(tb_SVI[],MATCH(Table3[[#This Row],[ibge_cod]],tb_SVI[Município],0),1) -> AC | C68: =INDEX(tb_SVI[],MATCH(Table3[[#This Row],[city_name]],tb_SVI[city_name_uf],0),3) -> 1200302 | D68: BRA.1.8_1 | E68: =INDEX(tb_SVI[],MATCH(Table3[[#This Row],[city_name]],tb_SVI[city_name_uf],0),5) -> 34884 | F68: =INDEX(tb_MHDI[],MATCH(Table3[[#This Row],[city_name]],tb_MHDI[mun_uf],0),5) -> 0.539 | G68: =INDEX(tb_MHDI[],MATCH(Table3[[#This Row],[city_name]],tb_MHDI[mun_uf],0),6) -> 0.559 | H68: =INDEX(tb_MHDI[],MATCH(Table3[[#This Row],[city_name]],tb_MHDI[mun_uf],0),7) -> 0.723 | I68: =INDEX(tb_MHDI[],MATCH(Table3[[#This Row],[city_name]],tb_MHDI[mun_uf],0),8) -> 0.388 | J68: =_xlfn.NUMBERVALUE(INDEX(tb_SVI[],MATCH(Table3[[#This Row],[city_name]],tb_SVI[city_name_uf],0),8),".") -> 0.639 | K68: =_xlfn.NUMBERVALUE(INDEX(tb_SVI[],MATCH(Table3[[#This Row],[city_name]],tb_SVI[city_name_uf],0),9),".") -> 0.511 | L68: =_xlfn.NUMBERVALUE(INDEX(tb_SVI[],MATCH(Table3[[#This Row],[city_name]],tb_SVI[city_name_uf],0),10),".") -> 0.799 | M68: =_xlfn.NUMBERVALUE(INDEX(tb_SVI[],MATCH(Table3[[#This Row],[city_name]],tb_SVI[city_name_uf],0),11),".") -> 0.607 | N68: =_xlfn.PERCENTRANK.INC(Table3[MHDI_tot],Table3[[#This Row],[MHDI_tot]],3) -> 0.04
A69: =SVI!F69 -> Epitaciolândia/AC | B69: =INDEX(tb_SVI[],MATCH(Table3[[#This Row],[ibge_cod]],tb_SVI[Município],0),1) -> AC | C69: =INDEX(tb_SVI[],MATCH(Table3[[#This Row],[city_name]],tb_SVI[city_name_uf],0),3) -> 1200252 | D69: BRA.1.7_1 | E69: =INDEX(tb_SVI[],MATCH(Table3[[#This Row],[city_name]],tb_SVI[city_name_uf],0),5) -> 18696 | F69: =INDEX(tb_MHDI[],MATCH(Table3[[#This Row],[city_name]],tb_MHDI[mun_uf],0),5) -> 0.653 | G69: =INDEX(tb_MHDI[],MATCH(Table3[[#This Row],[city_name]],tb_MHDI[mun_uf],0),6) -> 0.654 | H69: =INDEX(tb_MHDI[],MATCH(Table3[[#This Row],[city_name]],tb_MHDI[mun_uf],0),7) -> 0.771 | I69: =INDEX(tb_MHDI[],MATCH(Table3[[#This Row],[city_name]],tb_MHDI[mun_uf],0),8) -> 0.553 | J69: =_xlfn.NUMBERVALUE(INDEX(tb_SVI[],MATCH(Table3[[#This Row],[city_name]],tb_SVI[city_name_uf],0),8),".") -> 0.441 | K69: =_xlfn.NUMBERVALUE(INDEX(tb_SVI[],MATCH(Table3[[#This Row],[city_name]],tb_SVI[city_name_uf],0),9),".") -> 0.379 | L69: =_xlfn.NUMBERVALUE(INDEX(tb_SVI[],MATCH(Table3[[#This Row],[city_name]],tb_SVI[city_name_uf],0),10),".") -> 0.517 | M69: =_xlfn.NUMBERVALUE(INDEX(tb_SVI[],MATCH(Table3[[#This Row],[city_name]],tb_SVI[city_name_uf],0),11),".") -> 0.427 | N69: =_xlfn.PERCENTRANK.INC(Table3[MHDI_tot],Table3[[#This Row],[MHDI_tot]],3) -> 0.448
A70: =SVI!F70 -> Cruzeiro do Sul/AC | B70: =INDEX(tb_SVI[],MATCH(Table3[[#This Row],[ibge_cod]],tb_SVI[Município],0),1) -> AC | C70: =INDEX(tb_SVI[],MATCH(Table3[[#This Row],[city_name]],tb_SVI[city_name_uf],0),3) -> 1200203 | D70: BRA.1.6_1 | E70: =INDEX(tb_SVI[],MATCH(Table3[[#This Row],[city_name]],tb_SVI[city_name_uf],0),5) -> 89072 | F70: =INDEX(tb_MHDI[],MATCH(Table3[[#This Row],[city_name]],tb_MHDI[mun_uf],0),5) -> 0.664 | G70: =INDEX(tb_MHDI[],MATCH(Table3[[#This Row],[city_name]],tb_MHDI[mun_uf],0),6) -> 0.648 | H70: =INDEX(tb_MHDI[],MATCH(Table3[[#This Row],[city_name]],tb_MHDI[mun_uf],0),7) -> 0.776 | I70: =INDEX(tb_MHDI[],MATCH(Table3[[#This Row],[city_name]],tb_MHDI[mun_uf],0),8) -> 0.582 | J70: =_xlfn.NUMBERVALUE(INDEX(tb_SVI[],MATCH(Table3[[#This Row],[city_name]],tb_SVI[city_name_uf],0),8),".") -> 0.475 | K70: =_xlfn.NUMBERVALUE(INDEX(tb_SVI[],MATCH(Table3[[#This Row],[city_name]],tb_SVI[city_name_uf],0),9),".") -> 0.445 | L70: =_xlfn.NUMBERVALUE(INDEX(tb_SVI[],MATCH(Table3[[#This Row],[city_name]],tb_SVI[city_name_uf],0),10),".") -> 0.559 | M70: =_xlfn.NUMBERVALUE(INDEX(tb_SVI[],MATCH(Table3[[#This Row],[city_name]],tb_SVI[city_name_uf],0),11),".") -> 0.42 | N70: =_xlfn.PERCENTRANK.INC(Table3[MHDI_tot],Table3[[#This Row],[MHDI_tot]],3) -> 0.492
A71: =SVI!F71 -> Capixaba/AC | B71: =INDEX(tb_SVI[],MATCH(Table3[[#This Row],[ibge_cod]],tb_SVI[Município],0),1) -> AC | C71: =INDEX(tb_SVI[],MATCH(Table3[[#This Row],[city_name]],tb_SVI[city_name_uf],0),3) -> 1200179 | D71: BRA.1.5_1 | E71: =INDEX(tb_SVI[],MATCH(Table3[[#This Row],[city_name]],tb_SVI[city_name_uf],0),5) -> 12008 | F71: =INDEX(tb_MHDI[],MATCH(Table3[[#This Row],[city_name]],tb_MHDI[mun_uf],0),5) -> 0.575 | G71: =INDEX(tb_MHDI[],MATCH(Table3[[#This Row],[city_name]],tb_MHDI[mun_uf],0),6) -> 0.601 | H71: =INDEX(tb_MHDI[],MATCH(Table3[[#This Row],[city_name]],tb_MHDI[mun_uf],0),7) -> 0.794 | I71: =INDEX(tb_MHDI[],MATCH(Table3[[#This Row],[city_name]],tb_MHDI[mun_uf],0),8) -> 0.398 | J71: =_xlfn.NUMBERVALUE(INDEX(tb_SVI[],MATCH(Table3[[#This Row],[city_name]],tb_SVI[city_name_uf],0),8),".") -> 0.469 | K71: =_xlfn.NUMBERVALUE(INDEX(tb_SVI[],MATCH(Table3[[#This Row],[city_name]],tb_SVI[city_name_uf],0),9),".") -> 0.302 | L71: =_xlfn.NUMBERVALUE(INDEX(tb_SVI[],MATCH(Table3[[#This Row],[city_name]],tb_SVI[city_name_uf],0),10),".") -> 0.612 | M71: =_xlfn.NUMBERVALUE(INDEX(tb_SVI[],MATCH(Table3[[#This Row],[city_name]],tb_SVI[city_name_uf],0),11),".") -> 0.493 | N71: =_xlfn.PERCENTRANK.INC(Table3[MHDI_tot],Table3[[#This Row],[MHDI_tot]],3) -> 0.144
A72: =SVI!F72 -> Bujari/AC | B72: =INDEX(tb_SVI[],MATCH(Table3[[#This Row],[ibge_cod]],tb_SVI[Município],0),1) -> AC | C72: =INDEX(tb_SVI[],MATCH(Table3[[#This Row],[city_name]],tb_SVI[city_name_uf],0),3) -> 1200138 | D72: BRA.1.4_1 | E72: =INDEX(tb_SVI[],MATCH(Table3[[#This Row],[city_name]],tb_SVI[city_name_uf],0),5) -> 10420 | F72: =INDEX(tb_MHDI[],MATCH(Table3[[#This Row],[city_name]],tb_MHDI[mun_uf],0),5) -> 0.589 | G72: =INDEX(tb_MHDI[],MATCH(Table3[[#This Row],[city_name]],tb_MHDI[mun_uf],0),6) -> 0.603 | H72: =INDEX(tb_MHDI[],MATCH(Table3[[#This Row],[city_name]],tb_MHDI[mun_uf],0),7) -> 0.772 | I72: =INDEX(tb_MHDI[],MATCH(Table3[[#This Row],[city_name]],tb_MHDI[mun_uf],0),8) -> 0.439 | J72: =_xlfn.NUMBERVALUE(INDEX(tb_SVI[],MATCH(Table3[[#This Row],[city_name]],tb_SVI[city_name_uf],0),8),".") -> 0.459 | K72: =_xlfn.NUMBERVALUE(INDEX(tb_SVI[],MATCH(Table3[[#This Row],[city_name]],tb_SVI[city_name_uf],0),9),".") -> 0.35 | L72: =_xlfn.NUMBERVALUE(INDEX(tb_SVI[],MATCH(Table3[[#This Row],[city_name]],tb_SVI[city_name_uf],0),10),".") -> 0.603 | M72: =_xlfn.NUMBERVALUE(INDEX(tb_SVI[],MATCH(Table3[[#This Row],[city_name]],tb_SVI[city_name_uf],0),11),".") -> 0.425 | N72: =_xlfn.PERCENTRANK.INC(Table3[MHDI_tot],Table3[[#This Row],[MHDI_tot]],3) -> 0.201
A73: =SVI!F73 -> Brasiléia/AC | B73: =INDEX(tb_SVI[],MATCH(Table3[[#This Row],[ibge_cod]],tb_SVI[Município],0),1) -> AC | C73: =INDEX(tb_SVI[],MATCH(Table3[[#This Row],[city_name]],tb_SVI[city_name_uf],0),3) -> 1200104 | D73: BRA.1.3_1 | E73: =INDEX(tb_SVI[],MATCH(Table3[[#This Row],[city_name]],tb_SVI[city_name_uf],0),5) -> 26702 | F73: =INDEX(tb_MHDI[],MATCH(Table3[[#This Row],[city_name]],tb_MHDI[mun_uf],0),5) -> 0.614 | G73: =INDEX(tb_MHDI[],MATCH(Table3[[#This Row],[city_name]],tb_MHDI[mun_uf],0),6) -> 0.619 | H73: =INDEX(tb_MHDI[],MATCH(Table3[[#This Row],[city_name]],tb_MHDI[mun_uf],0),7) -> 0.77 | I73: =INDEX(tb_MHDI[],MATCH(Table3[[#This Row],[city_name]],tb_MHDI[mun_uf],0),8) -> 0.485 | J73: =_xlfn.NUMBERVALUE(INDEX(tb_SVI[],MATCH(Table3[[#This Row],[city_name]],tb_SVI[city_name_uf],0),8),".") -> 0.462 | K73: =_xlfn.NUMBERVALUE(INDEX(tb_SVI[],MATCH(Table3[[#This Row],[city_name]],tb_SVI[city_name_uf],0),9),".") -> 0.32 | L73: =_xlfn.NUMBERVALUE(INDEX(tb_SVI[],MATCH(Table3[[#This Row],[city_name]],tb_SVI[city_name_uf],0),10),".") -> 0.593 | M73: =_xlfn.NUMBERVALUE(INDEX(tb_SVI[],MATCH(Table3[[#This Row],[city_name]],tb_SVI[city_name_uf],0),11),".") -> 0.473 | N73: =_xlfn.PERCENTRANK.INC(Table3[MHDI_tot],Table3[[#This Row],[MHDI_tot]],3) -> 0.308
A74: =SVI!F74 -> Assis Brasil/AC | B74: =INDEX(tb_SVI[],MATCH(Table3[[#This Row],[ibge_cod]],tb_SVI[Município],0),1) -> AC | C74: =INDEX(tb_SVI[],MATCH(Table3[[#This Row],[city_name]],tb_SVI[city_name_uf],0),3) -> 1200054 | D74: BRA.1.2_1 | E74: =INDEX(tb_SVI[],MATCH(Table3[[#This Row],[city_name]],tb_SVI[city_name_uf],0),5) -> 7534 | F74: =INDEX(tb_MHDI[],MATCH(Table3[[#This Row],[city_name]],tb_MHDI[mun_uf],0),5) -> 0.588 | G74: =INDEX(tb_MHDI[],MATCH(Table3[[#This Row],[city_name]],tb_MHDI[mun_uf],0),6) -> 0.578 | H74: =INDEX(tb_MHDI[],MATCH(Table3[[#This Row],[city_name]],tb_MHDI[mun_uf],0),7) -> 0.77 | I74: =INDEX(tb_MHDI[],MATCH(Table3[[#This Row],[city_name]],tb_MHDI[mun_uf],0),8) -> 0.456 | J74: =_xlfn.NUMBERVALUE(INDEX(tb_SVI[],MATCH(Table3[[#This Row],[city_name]],tb_SVI[city_name_uf],0),8),".") -> 0.5 | K74: =_xlfn.NUMBERVALUE(INDEX(tb_SVI[],MATCH(Table3[[#This Row],[city_name]],tb_SVI[city_name_uf],0),9),".") -> 0.317 | L74: =_xlfn.NUMBERVALUE(INDEX(tb_SVI[],MATCH(Table3[[#This Row],[city_name]],tb_SVI[city_name_uf],0),10),".") -> 0.7 | M74: =_xlfn.NUMBERVALUE(INDEX(tb_SVI[],MATCH(Table3[[#This Row],[city_name]],tb_SVI[city_name_uf],0),11),".") -> 0.484 | N74: =_xlfn.PERCENTRANK.INC(Table3[MHDI_tot],Table3[[#This Row],[MHDI_tot]],3) -> 0.197
A75: =SVI!F75 -> Acrelândia/AC | B75: =INDEX(tb_SVI[],MATCH(Table3[[#This Row],[ibge_cod]],tb_SVI[Município],0),1) -> AC | C75: =INDEX(tb_SVI[],MATCH(Table3[[#This Row],[city_name]],tb_SVI[city_name_uf],0),3) -> 1200013 | D75: BRA.1.1_1 | E75: =INDEX(tb_SVI[],MATCH(Table3[[#This Row],[city_name]],tb_SVI[city_name_uf],0),5) -> 15490 | F75: =INDEX(tb_MHDI[],MATCH(Table3[[#This Row],[city_name]],tb_MHDI[mun_uf],0),5) -> 0.604 | G75: =INDEX(tb_MHDI[],MATCH(Table3[[#This Row],[city_name]],tb_MHDI[mun_uf],0),6) -> 0.584 | H75: =INDEX(tb_MHDI[],MATCH(Table3[[#This Row],[city_name]],tb_MHDI[mun_uf],0),7) -> 0.808 | I75: =INDEX(tb_MHDI[],MATCH(Table3[[#This Row],[city_name]],tb_MHDI[mun_uf],0),8) -> 0.466 | J75: =_xlfn.NUMBERVALUE(INDEX(tb_SVI[],MATCH(Table3[[#This Row],[city_name]],tb_SVI[city_name_uf],0),8),".") -> 0.448 | K75: =_xlfn.NUMBERVALUE(INDEX(tb_SVI[],MATCH(Table3[[#This Row],[city_name]],tb_SVI[city_name_uf],0),9),".") -> 0.281 | L75: =_xlfn.NUMBERVALUE(INDEX(tb_SVI[],MATCH(Table3[[#This Row],[city_name]],tb_SVI[city_name_uf],0),10),".") -> 0.577 | M75: =_xlfn.NUMBERVALUE(INDEX(tb_SVI[],MATCH(Table3[[#This Row],[city_name]],tb_SVI[city_name_uf],0),11),".") -> 0.485 | N75: =_xlfn.PERCENTRANK.INC(Table3[MHDI_tot],Table3[[#This Row],[MHDI_tot]],3) -> 0.266
A76: =SVI!F3201 -> Mesquita/RJ | B76: =INDEX(tb_SVI[],MATCH(Table3[[#This Row],[ibge_cod]],tb_SVI[Município],0),1) -> RJ | C76: =INDEX(tb_SVI[],MATCH(Table3[[#This Row],[city_name]],tb_SVI[city_name_uf],0),3) -> 3302858 | D76: #N/A | E76: =INDEX(tb_SVI[],MATCH(Table3[[#This Row],[city_name]],tb_SVI[city_name_uf],0),5) -> 176569 | F76: =INDEX(tb_MHDI[],MATCH(Table3[[#This Row],[city_name]],tb_MHDI[mun_uf],0),5) -> 0.737 | G76: =INDEX(tb_MHDI[],MATCH(Table3[[#This Row],[city_name]],tb_MHDI[mun_uf],0),6) -> 0.704 | H76: =INDEX(tb_MHDI[],MATCH(Table3[[#This Row],[city_name]],tb_MHDI[mun_uf],0),7) -> 0.839 | I76: =INDEX(tb_MHDI[],MATCH(Table3[[#This Row],[city_name]],tb_MHDI[mun_uf],0),8) -> 0.678 | J76: =_xlfn.NUMBERVALUE(INDEX(tb_SVI[],MATCH(Table3[[#This Row],[city_name]],tb_SVI[city_name_uf],0),8),".") -> 0.318 | K76: =_xlfn.NUMBERVALUE(INDEX(tb_SVI[],MATCH(Table3[[#This Row],[city_name]],tb_SVI[city_name_uf],0),9),".") -> 0.412 | L76: =_xlfn.NUMBERVALUE(INDEX(tb_SVI[],MATCH(Table3[[#This Row],[city_name]],tb_SVI[city_name_uf],0),10),".") -> 0.262 | M76: =_xlfn.NUMBERVALUE(INDEX(tb_SVI[],MATCH(Table3[[#This Row],[city_name]],tb_SVI[city_name_uf],0),11),".") -> 0.281 | N76: =_xlfn.PERCENTRANK.INC(Table3[MHDI_tot],Table3[[#This Row],[MHDI_tot]],3) -> 0.842
A77: =SVI!F165 -> Cachoeira do Piriá/PA | B77: =INDEX(tb_SVI[],MATCH(Table3[[#This Row],[ibge_cod]],tb_SVI[Município],0),1) -> PA | C77: =INDEX(tb_SVI[],MATCH(Table3[[#This Row],[city_name]],tb_SVI[city_name_uf],0),3) -> 1501956 | D77: BRA.14.31_1 | E77: =INDEX(tb_SVI[],MATCH(Table3[[#This Row],[city_name]],tb_SVI[city_name_uf],0),5) -> 34609 | F77: =INDEX(tb_MHDI[],MATCH(Table3[[#This Row],[city_name]],tb_MHDI[mun_uf],0),5) -> 0.473 | G77: =INDEX(tb_MHDI[],MATCH(Table3[[#This Row],[city_name]],tb_MHDI[mun_uf],0),6) -> 0.449 | H77: =INDEX(tb_MHDI[],MATCH(Table3[[#This Row],[city_name]],tb_MHDI[mun_uf],0),7) -> 0.779 | I77: =INDEX(tb_MHDI[],MATCH(Table3[[#This Row],[city_name]],tb_MHDI[mun_uf],0),8) -> 0.303 | J77: =_xlfn.NUMBERVALUE(INDEX(tb_SVI[],MATCH(Table3[[#This Row],[city_name]],tb_SVI[city_name_uf],0),8),".") -> 0.668 | K77: =_xlfn.NUMBERVALUE(INDEX(tb_SVI[],MATCH(Table3[[#This Row],[city_name]],tb_SVI[city_name_uf],0),9),".") -> 0.697 | L77: =_xlfn.NUMBERVALUE(INDEX(tb_SVI[],MATCH(Table3[[#This Row],[city_name]],tb_SVI[city_name_uf],0),10),".") -> 0.759 | M77: =_xlfn.NUMBERVALUE(INDEX(tb_SVI[],MATCH(Table3[[#This Row],[city_name]],tb_SVI[city_name_uf],0),11),".") -> 0.549 | N77: =_xlfn.PERCENTRANK.INC(Table3[MHDI_tot],Table3[[#This Row],[MHDI_tot]],3) -> 0.001
A78: =SVI!F78 -> Ipixuna/AM | B78: =INDEX(tb_SVI[],MATCH(Table3[[#This Row],[ibge_cod]],tb_SVI[Município],0),1) -> AM | C78: =INDEX(tb_SVI[],MATCH(Table3[[#This Row],[city_name]],tb_SVI[city_name_uf],0),3) -> 1301803 | D78: BRA.4.27_1 | E78: =INDEX(tb_SVI[],MATCH(Table3[[#This Row],[city_name]],tb_SVI[city_name_uf],0),5) -> 30436 | F78: =INDEX(tb_MHDI[],MATCH(Table3[[#This Row],[city_name]],tb_MHDI[mun_uf],0),5) -> 0.481 | G78: =INDEX(tb_MHDI[],MATCH(Table3[[#This Row],[city_name]],tb_MHDI[mun_uf],0),6) -> 0.476 | H78: =INDEX(tb_MHDI[],MATCH(Table3[[#This Row],[city_name]],tb_MHDI[mun_uf],0),7) -> 0.772 | I78: =INDEX(tb_MHDI[],MATCH(Table3[[#This Row],[city_name]],tb_MHDI[mun_uf],0),8) -> 0.302 | J78: =_xlfn.NUMBERVALUE(INDEX(tb_SVI[],MATCH(Table3[[#This Row],[city_name]],tb_SVI[city_name_uf],0),8),".") -> 0.706 | K78: =_xlfn.NUMBERVALUE(INDEX(tb_SVI[],MATCH(Table3[[#This Row],[city_name]],tb_SVI[city_name_uf],0),9),".") -> 0.708 | L78: =_xlfn.NUMBERVALUE(INDEX(tb_SVI[],MATCH(Table3[[#This Row],[city_name]],tb_SVI[city_name_uf],0),10),".") -> 0.768 | M78: =_xlfn.NUMBERVALUE(INDEX(tb_SVI[],MATCH(Table3[[#This Row],[city_name]],tb_SVI[city_name_uf],0),11),".") -> 0.643 | N78: =_xlfn.PERCENTRANK.INC(Table3[MHDI_tot],Table3[[#This Row],[MHDI_tot]],3) -> 0.001
A79: =SVI!F79 -> Humaitá/AM | B79: =INDEX(tb_SVI[],MATCH(Table3[[#This Row],[ibge_cod]],tb_SVI[Município],0),1) -> AM | C79: =INDEX(tb_SVI[],MATCH(Table3[[#This Row],[city_name]],tb_SVI[city_name_uf],0),3) -> 1301704 | D79: BRA.4.26_1 | E79: =INDEX(tb_SVI[],MATCH(Table3[[#This Row],[city_name]],tb_SVI[city_name_uf],0),5) -> 56144 | F79: =INDEX(tb_MHDI[],MATCH(Table3[[#This Row],[city_name]],tb_MHDI[mun_uf],0),5) -> 0.605 | G79: =INDEX(tb_MHDI[],MATCH(Table3[[#This Row],[city_name]],tb_MHDI[mun_uf],0),6) -> 0.621 | H79: =INDEX(tb_MHDI[],MATCH(Table3[[#This Row],[city_name]],tb_MHDI[mun_uf],0),7) -> 0.791 | I79: =INDEX(tb_MHDI[],MATCH(Table3[[#This Row],[city_name]],tb_MHDI[mun_uf],0),8) -> 0.451 | J79: =_xlfn.NUMBERVALUE(INDEX(tb_SVI[],MATCH(Table3[[#This Row],[city_name]],tb_SVI[city_name_uf],0),8),".") -> 0.477 | K79: =_xlfn.NUMBERVALUE(INDEX(tb_SVI[],MATCH(Table3[[#This Row],[city_name]],tb_SVI[city_name_uf],0),9),".") -> 0.306 | L79: =_xlfn.NUMBERVALUE(INDEX(tb_SVI[],MATCH(Table3[[#This Row],[city_name]],tb_SVI[city_name_uf],0),10),".") -> 0.636 | M79: =_xlfn.NUMBERVALUE(INDEX(tb_SVI[],MATCH(Table3[[#This Row],[city_name]],tb_SVI[city_name_uf],0),11),".") -> 0.488 | N79: =_xlfn.PERCENTRANK.INC(Table3[MHDI_tot],Table3[[#This Row],[MHDI_tot]],3) -> 0.271
A80: =SVI!F80 -> Guajará/AM | B80: =INDEX(tb_SVI[],MATCH(Table3[[#This Row],[ibge_cod]],tb_SVI[Município],0),1) -> AM | C80: =INDEX(tb_SVI[],MATCH(Table3[[#This Row],[city_name]],tb_SVI[city_name_uf],0),3) -> 1301654 | D80: BRA.4.25_1 | E80: =INDEX(tb_SVI[],MATCH(Table3[[#This Row],[city_name]],tb_SVI[city_name_uf],0),5) -> 16937 | F80: =INDEX(tb_MHDI[],MATCH(Table3[[#This Row],[city_name]],tb_MHDI[mun_uf],0),5) -> 0.532 | G80: =INDEX(tb_MHDI[],MATCH(Table3[[#This Row],[city_name]],tb_MHDI[mun_uf],0),6) -> 0.51 | H80: =INDEX(tb_MHDI[],MATCH(Table3[[#This Row],[city_name]],tb_MHDI[mun_uf],0),7) -> 0.762 | I80: =INDEX(tb_MHDI[],MATCH(Table3[[#This Row],[city_name]],tb_MHDI[mun_uf],0),8) -> 0.387 | J80: =_xlfn.NUMBERVALUE(INDEX(tb_SVI[],MATCH(Table3[[#This Row],[city_name]],tb_SVI[city_name_uf],0),8),".") -> 0.555 | K80: =_xlfn.NUMBERVALUE(INDEX(tb_SVI[],MATCH(Table3[[#This Row],[city_name]],tb_SVI[city_name_uf],0),9),".") -> 0.484 | L80: =_xlfn.NUMBERVALUE(INDEX(tb_SVI[],MATCH(Table3[[#This Row],[city_name]],tb_SVI[city_name_uf],0),10),".") -> 0.679 | M80: =_xlfn.NUMBERVALUE(INDEX(tb_SVI[],MATCH(Table3[[#This Row],[city_name]],tb_SVI[city_name_uf],0),11),".") -> 0.503 | N80: =_xlfn.PERCENTRANK.INC(Table3[MHDI_tot],Table3[[#This Row],[MHDI_tot]],3) -> 0.031
A81: =SVI!F81 -> Fonte Boa/AM | B81: =INDEX(tb_SVI[],MATCH(Table3[[#This Row],[ibge_cod]],tb_SVI[Município],0),1) -> AM | C81: =INDEX(tb_SVI[],MATCH(Table3[[#This Row],[city_name]],tb_SVI[city_name_uf],0),3) -> 1301605 | D81: BRA.4.24_1 | E81: =INDEX(tb_SVI[],MATCH(Table3[[#This Row],[city_name]],tb_SVI[city_name_uf],0),5) -> 17005 | F81: =INDEX(tb_MHDI[],MATCH(Table3[[#This Row],[city_name]],tb_MHDI[mun_uf],0),5) -> 0.53 | G81: =INDEX(tb_MHDI[],MATCH(Table3[[#This Row],[city_name]],tb_MHDI[mun_uf],0),6) -> 0.518 | H81: =INDEX(tb_MHDI[],MATCH(Table3[[#This Row],[city_name]],tb_MHDI[mun_uf],0),7) -> 0.719 | I81: =INDEX(tb_MHDI[],MATCH(Table3[[#This Row],[city_name]],tb_MHDI[mun_uf],0),8) -> 0.4 | J81: =_xlfn.NUMBERVALUE(INDEX(tb_SVI[],MATCH(Table3[[#This Row],[city_name]],tb_SVI[city_name_uf],0),8),".") -> 0.726 | K81: =_xlfn.NUMBERVALUE(INDEX(tb_SVI[],MATCH(Table3[[#This Row],[city_name]],tb_SVI[city_name_uf],0),9),".") -> 0.767 | L81: =_xlfn.NUMBERVALUE(INDEX(tb_SVI[],MATCH(Table3[[#This Row],[city_name]],tb_SVI[city_name_uf],0),10),".") -> 0.763 | M81: =_xlfn.NUMBERVALUE(INDEX(tb_SVI[],MATCH(Table3[[#This Row],[city_name]],tb_SVI[city_name_uf],0),11),".") -> 0.648 | N81: =_xlfn.PERCENTRANK.INC(Table3[MHDI_tot],Table3[[#This Row],[MHDI_tot]],3) -> 0.029
A82: =SVI!F82 -> Envira/AM | B82: =INDEX(tb_SVI[],MATCH(Table3[[#This Row],[ibge_cod]],tb_SVI[Município],0),1) -> AM | C82: =INDEX(tb_SVI[],MATCH(Table3[[#This Row],[city_name]],tb_SVI[city_name_uf],0),3) -> 1301506 | D82: BRA.4.23_1 | E82: =INDEX(tb_SVI[],MATCH(Table3[[#This Row],[city_name]],tb_SVI[city_name_uf],0),5) -> 20393 | F82: =INDEX(tb_MHDI[],MATCH(Table3[[#This Row],[city_name]],tb_MHDI[mun_uf],0),5) -> 0.509 | G82: =INDEX(tb_MHDI[],MATCH(Table3[[#This Row],[city_name]],tb_MHDI[mun_uf],0),6) -> 0.521 | H82: =INDEX(tb_MHDI[],MATCH(Table3[[#This Row],[city_name]],tb_MHDI[mun_uf],0),7) -> 0.727 | I82: =INDEX(tb_MHDI[],MATCH(Table3[[#This Row],[city_name]],tb_MHDI[mun_uf],0),8) -> 0.349 | J82: =_xlfn.NUMBERVALUE(INDEX(tb_SVI[],MATCH(Table3[[#This Row],[city_name]],tb_SVI[city_name_uf],0),8),".") -> 0.667 | K82: =_xlfn.NUMBERVALUE(INDEX(tb_SVI[],MATCH(Table3[[#This Row],[city_name]],tb_SVI[city_name_uf],0),9),".") -> 0.57 | L82: =_xlfn.NUMBERVALUE(INDEX(tb_SVI[],MATCH(Table3[[#This Row],[city_name]],tb_SVI[city_name_uf],0),10),".") -> 0.801 | M82: =_xlfn.NUMBERVALUE(INDEX(tb_SVI[],MATCH(Table3[[#This Row],[city_name]],tb_SVI[city_name_uf],0),11),".") -> 0.629 | N82: =_xlfn.PERCENTRANK.INC(Table3[MHDI_tot],Table3[[#This Row],[MHDI_tot]],3) -> 0.01
A83: =SVI!F83 -> Eirunepé/AM | B83: =INDEX(tb_SVI[],MATCH(Table3[[#This Row],[ibge_cod]],tb_SVI[Município],0),1) -> AM | C83: =INDEX(tb_SVI[],MATCH(Table3[[#This Row],[city_name]],tb_SVI[city_name_uf],0),3) -> 1301407 | D83: BRA.4.22_1 | E83: =INDEX(tb_SVI[],MATCH(Table3[[#This Row],[city_name]],tb_SVI[city_name_uf],0),5) -> 35700 | F83: =INDEX(tb_MHDI[],MATCH(Table3[[#This Row],[city_name]],tb_MHDI[mun_uf],0),5) -> 0.563 | G83: =INDEX(tb_MHDI[],MATCH(Table3[[#This Row],[city_name]],tb_MHDI[mun_uf],0),6) -> 0.548 | H83: =INDEX(tb_MHDI[],MATCH(Table3[[#This Row],[city_name]],tb_MHDI[mun_uf],0),7) -> 0.756 | I83: =INDEX(tb_MHDI[],MATCH(Table3[[#This Row],[city_name]],tb_MHDI[mun_uf],0),8) -> 0.431 | J83: =_xlfn.NUMBERVALUE(INDEX(tb_SVI[],MATCH(Table3[[#This Row],[city_name]],tb_SVI[city_name_uf],0),8),".") -> 0.706 | K83: =_xlfn.NUMBERVALUE(INDEX(tb_SVI[],MATCH(Table3[[#This Row],[city_name]],tb_SVI[city_name_uf],0),9),".") -> 0.791 | L83: =_xlfn.NUMBERVALUE(INDEX(tb_SVI[],MATCH(Table3[[#This Row],[city_name]],tb_SVI[city_name_uf],0),10),".") -> 0.736 | M83: =_xlfn.NUMBERVALUE(INDEX(tb_SVI[],MATCH(Table3[[#This Row],[city_name]],tb_SVI[city_name_uf],0),11),".") -> 0.591 | N83: =_xlfn.PERCENTRANK.INC(Table3[MHDI_tot],Table3[[#This Row],[MHDI_tot]],3) -> 0.101
A84: =SVI!F84 -> Codajás/AM | B84: =INDEX(tb_SVI[],MATCH(Table3[[#This Row],[ibge_cod]],tb_SVI[Município],0),1) -> AM | C84: =INDEX(tb_SVI[],MATCH(Table3[[#This Row],[city_name]],tb_SVI[city_name_uf],0),3) -> 1301308 | D84: BRA.4.21_1 | E84: =INDEX(tb_SVI[],MATCH(Table3[[#This Row],[city_name]],tb_SVI[city_name_uf],0),5) -> 29168 | F84: =INDEX(tb_MHDI[],MATCH(Table3[[#This Row],[city_name]],tb_MHDI[mun_uf],0),5) -> 0.563 | G84: =INDEX(tb_MHDI[],MATCH(Table3[[#This Row],[city_name]],tb_MHDI[mun_uf],0),6) -> 0.546 | H84: =INDEX(tb_MHDI[],MATCH(Table3[[#This Row],[city_name]],tb_MHDI[mun_uf],0),7) -> 0.775 | I84: =INDEX(tb_MHDI[],MATCH(Table3[[#This Row],[city_name]],tb_MHDI[mun_uf],0),8) -> 0.421 | J84: =_xlfn.NUMBERVALUE(INDEX(tb_SVI[],MATCH(Table3[[#This Row],[city_name]],tb_SVI[city_name_uf],0),8),".") -> 0.557 | K84: =_xlfn.NUMBERVALUE(INDEX(tb_SVI[],MATCH(Table3[[#This Row],[city_name]],tb_SVI[city_name_uf],0),9),".") -> 0.445 | L84: =_xlfn.NUMBERVALUE(INDEX(tb_SVI[],MATCH(Table3[[#This Row],[city_name]],tb_SVI[city_name_uf],0),10),".") -> 0.68 | M84: =_xlfn.NUMBERVALUE(INDEX(tb_SVI[],MATCH(Table3[[#This Row],[city_name]],tb_SVI[city_name_uf],0),11),".") -> 0.546 | N84: =_xlfn.PERCENTRANK.INC(Table3[MHDI_tot],Table3[[#This Row],[MHDI_tot]],3) -> 0.101
A85: =SVI!F85 -> Coari/AM | B85: =INDEX(tb_SVI[],MATCH(Table3[[#This Row],[ibge_cod]],tb_SVI[Município],0),1) -> AM | C85: =INDEX(tb_SVI[],MATCH(Table3[[#This Row],[city_name]],tb_SVI[city_name_uf],0),3) -> 1301209 | D85: BRA.4.20_1 | E85: =INDEX(tb_SVI[],MATCH(Table3[[#This Row],[city_name]],tb_SVI[city_name_uf],0),5) -> 85910 | F85: =INDEX(tb_MHDI[],MATCH(Table3[[#This Row],[city_name]],tb_MHDI[mun_uf],0),5) -> 0.586 | G85: =INDEX(tb_MHDI[],MATCH(Table3[[#This Row],[city_name]],tb_MHDI[mun_uf],0),6) -> 0.606 | H85: =INDEX(tb_MHDI[],MATCH(Table3[[#This Row],[city_name]],tb_MHDI[mun_uf],0),7) -> 0.78 | I85: =INDEX(tb_MHDI[],MATCH(Table3[[#This Row],[city_name]],tb_MHDI[mun_uf],0),8) -> 0.425 | J85: =_xlfn.NUMBERVALUE(INDEX(tb_SVI[],MATCH(Table3[[#This Row],[city_name]],tb_SVI[city_name_uf],0),8),".") -> 0.564 | K85: =_xlfn.NUMBERVALUE(INDEX(tb_SVI[],MATCH(Table3[[#This Row],[city_name]],tb_SVI[city_name_uf],0),9),".") -> 0.434 | L85: =_xlfn.NUMBERVALUE(INDEX(tb_SVI[],MATCH(Table3[[#This Row],[city_name]],tb_SVI[city_name_uf],0),10),".") -> 0.697 | M85: =_xlfn.NUMBERVALUE(INDEX(tb_SVI[],MATCH(Table3[[#This Row],[city_name]],tb_SVI[city_name_uf],0),11),".") -> 0.562 | N85: =_xlfn.PERCENTRANK.INC(Table3[MHDI_tot],Table3[[#This Row],[MHDI_tot]],3) -> 0.188
A86: =SVI!F86 -> Careiro/AM | B86: =INDEX(tb_SVI[],MATCH(Table3[[#This Row],[ibge_cod]],tb_SVI[Município],0),1) -> AM | C86: =INDEX(tb_SVI[],MATCH(Table3[[#This Row],[city_name]],tb_SVI[city_name_uf],0),3) -> 1301100 | D86: BRA.4.19_1 | E86: =INDEX(tb_SVI[],MATCH(Table3[[#This Row],[city_name]],tb_SVI[city_name_uf],0),5) -> 38348 | F86: =INDEX(tb_MHDI[],MATCH(Table3[[#This Row],[city_name]],tb_MHDI[mun_uf],0),5) -> 0.557 | G86: =INDEX(tb_MHDI[],MATCH(Table3[[#This Row],[city_name]],tb_MHDI[mun_uf],0),6) -> 0.515 | H86: =INDEX(tb_MHDI[],MATCH(Table3[[#This Row],[city_name]],tb_MHDI[mun_uf],0),7) -> 0.779 | I86: =INDEX(tb_MHDI[],MATCH(Table3[[#This Row],[city_name]],tb_MHDI[mun_uf],0),8) -> 0.431 | J86: =_xlfn.NUMBERVALUE(INDEX(tb_SVI[],MATCH(Table3[[#This Row],[city_name]],tb_SVI[city_name_uf],0),8),".") -> 0.543 | K86: =_xlfn.NUMBERVALUE(INDEX(tb_SVI[],MATCH(Table3[[#This Row],[city_name]],tb_SVI[city_name_uf],0),9),".") -> 0.417 | L86: =_xlfn.NUMBERVALUE(INDEX(tb_SVI[],MATCH(Table3[[#This Row],[city_name]],tb_SVI[city_name_uf],0),10),".") -> 0.641 | M86: =_xlfn.NUMBERVALUE(INDEX(tb_SVI[],MATCH(Table3[[#This Row],[city_name]],tb_SVI[city_name_uf],0),11),".") -> 0.572 | N86: =_xlfn.PERCENTRANK.INC(Table3[MHDI_tot],Table3[[#This Row],[MHDI_tot]],3) -> 0.08
A87: =SVI!F87 -> Carauari/AM | B87: =INDEX(tb_SVI[],MATCH(Table3[[#This Row],[ibge_cod]],tb_SVI[Município],0),1) -> AM | C87: =INDEX(tb_SVI[],MATCH(Table3[[#This Row],[city_name]],tb_SVI[city_name_uf],0),3) -> 1301001 | D87: BRA.4.17_1 | E87: =INDEX(tb_SVI[],MATCH(Table3[[#This Row],[city_name]],tb_SVI[city_name_uf],0),5) -> 28508 | F87: =INDEX(tb_MHDI[],MATCH(Table3[[#This Row],[city_name]],tb_MHDI[mun_uf],0),5) -> 0.549 | G87: =INDEX(tb_MHDI[],MATCH(Table3[[#This Row],[city_name]],tb_MHDI[mun_uf],0),6) -> 0.534 | H87: =INDEX(tb_MHDI[],MATCH(Table3[[#This Row],[city_name]],tb_MHDI[mun_uf],0),7) -> 0.745 | I87: =INDEX(tb_MHDI[],MATCH(Table3[[#This Row],[city_name]],tb_MHDI[mun_uf],0),8) -> 0.416 | J87: =_xlfn.NUMBERVALUE(INDEX(tb_SVI[],MATCH(Table3[[#This Row],[city_name]],tb_SVI[city_name_uf],0),8),".") -> 0.659 | K87: =_xlfn.NUMBERVALUE(INDEX(tb_SVI[],MATCH(Table3[[#This Row],[city_name]],tb_SVI[city_name_uf],0),9),".") -> 0.736 | L87: =_xlfn.NUMBERVALUE(INDEX(tb_SVI[],MATCH(Table3[[#This Row],[city_name]],tb_SVI[city_name_uf],0),10),".") -> 0.715 | M87: =_xlfn.NUMBERVALUE(INDEX(tb_SVI[],MATCH(Table3[[#This Row],[city_name]],tb_SVI[city_name_uf],0),11),".") -> 0.525 | N87: =_xlfn.PERCENTRANK.INC(Table3[MHDI_tot],Table3[[#This Row],[MHDI_tot]],3) -> 0.061
A88: =SVI!F88 -> Canutama/AM | B88: =INDEX(tb_SVI[],MATCH(Table3[[#This Row],[ibge_cod]],tb_SVI[Município],0),1) -> AM | C88: =INDEX(tb_SVI[],MATCH(Table3[[#This Row],[city_name]],tb_SVI[city_name_uf],0),3) -> 1300904 | D88: BRA.4.16_1 | E88: =INDEX(tb_SVI[],MATCH(Table3[[#This Row],[city_name]],tb_SVI[city_name_uf],0),5) -> 15807 | F88: =INDEX(tb_MHDI[],MATCH(Table3[[#This Row],[city_name]],tb_MHDI[mun_uf],0),5) -> 0.53 | G88: =INDEX(tb_MHDI[],MATCH(Table3[[#This Row],[city_name]],tb_MHDI[mun_uf],0),6) -> 0.522 | H88: =INDEX(tb_MHDI[],MATCH(Table3[[#This Row],[city_name]],tb_MHDI[mun_uf],0),7) -> 0.752 | I88: =INDEX(tb_MHDI[],MATCH(Table3[[#This Row],[city_name]],tb_MHDI[mun_uf],0),8) -> 0.379 | J88: =_xlfn.NUMBERVALUE(INDEX(tb_SVI[],MATCH(Table3[[#This Row],[city_name]],tb_SVI[city_name_uf],0),8),".") -> 0.62 | K88: =_xlfn.NUMBERVALUE(INDEX(tb_SVI[],MATCH(Table3[[#This Row],[city_name]],tb_SVI[city_name_uf],0),9),".") -> 0.603 | L88: =_xlfn.NUMBERVALUE(INDEX(tb_SVI[],MATCH(Table3[[#This Row],[city_name]],tb_SVI[city_name_uf],0),10),".") -> 0.687 | M88: =_xlfn.NUMBERVALUE(INDEX(tb_SVI[],MATCH(Table3[[#This Row],[city_name]],tb_SVI[city_name_uf],0),11),".") -> 0.569 | N88: =_xlfn.PERCENTRANK.INC(Table3[MHDI_tot],Table3[[#This Row],[MHDI_tot]],3) -> 0.029
A89: =SVI!F89 -> Caapiranga/AM | B89: =INDEX(tb_SVI[],MATCH(Table3[[#This Row],[ibge_cod]],tb_SVI[Município],0),1) -> AM | C89: =INDEX(tb_SVI[],MATCH(Table3[[#This Row],[city_name]],tb_SVI[city_name_uf],0),3) -> 1300839 | D89: BRA.4.15_1 | E89: =INDEX(tb_SVI[],MATCH(Table3[[#This Row],[city_name]],tb_SVI[city_name_uf],0),5) -> 13283 | F89: =INDEX(tb_MHDI[],MATCH(Table3[[#This Row],[city_name]],tb_MHDI[mun_uf],0),5) -> 0.569 | G89: =INDEX(tb_MHDI[],MATCH(Table3[[#This Row],[city_name]],tb_MHDI[mun_uf],0),6) -> 0.544 | H89: =INDEX(tb_MHDI[],MATCH(Table3[[#This Row],[city_name]],tb_MHDI[mun_uf],0),7) -> 0.775 | I89: =INDEX(tb_MHDI[],MATCH(Table3[[#This Row],[city_name]],tb_MHDI[mun_uf],0),8) -> 0.436 | J89: =_xlfn.NUMBERVALUE(INDEX(tb_SVI[],MATCH(Table3[[#This Row],[city_name]],tb_SVI[city_name_uf],0),8),".") -> 0.614 | K89: =_xlfn.NUMBERVALUE(INDEX(tb_SVI[],MATCH(Table3[[#This Row],[city_name]],tb_SVI[city_name_uf],0),9),".") -> 0.696 | L89: =_xlfn.NUMBERVALUE(INDEX(tb_SVI[],MATCH(Table3[[#This Row],[city_name]],tb_SVI[city_name_uf],0),10),".") -> 0.632 | M89: =_xlfn.NUMBERVALUE(INDEX(tb_SVI[],MATCH(Table3[[#This Row],[city_name]],tb_SVI[city_name_uf],0),11),".") -> 0.514 | N89: =_xlfn.PERCENTRANK.INC(Table3[MHDI_tot],Table3[[#This Row],[MHDI_tot]],3) -> 0.122
... A116: =SVI!F116 -> Presidente Figueiredo/AM | B116: =INDEX(tb_SVI[],MATCH(Table3[[#This Row],[ibge_cod]],tb_SVI[Município],0),1) -> AM | C116: =INDEX(tb_SVI[],MATCH(Table3[[#This Row],[city_name]],tb_SVI[city_name_uf],0),3) -> 1303536 | D116: BRA.4.46_1 | E116: =INDEX(tb_SVI[],MATCH(Table3[[#This Row],[city_name]],tb_SVI[city_name_uf],0),5) -> 37193 | F116: =INDEX(tb_MHDI[],MATCH(Table3[[#This Row],[city_name]],tb_MHDI[mun_uf],0),5) -> 0.647 | G116: =INDEX(tb_MHDI[],MATCH(Table3[[#This Row],[city_name]],tb_MHDI[mun_uf],0),6) -> 0.627 | H116: =INDEX(tb_MHDI[],MATCH(Table3[[#This Row],[city_name]],tb_MHDI[mun_uf],0),7) -> 0.802 | I116: =INDEX(tb_MHDI[],MATCH(Table3[[#This Row],[city_name]],tb_MHDI[mun_uf],0),8) -> 0.538 | J116: =_xlfn.NUMBERVALUE(INDEX(tb_SVI[],MATCH(Table3[[#This Row],[city_name]],tb_SVI[city_name_uf],0),8),".") -> 0.426 | K116: =_xlfn.NUMBERVALUE(INDEX(tb_SVI[],MATCH(Table3[[#This Row],[city_name]],tb_SVI[city_name_uf],0),9),".") -> 0.393 | L116: =_xlfn.NUMBERVALUE(INDEX(tb_SVI[],MATCH(Table3[[#This Row],[city_name]],tb_SVI[city_name_uf],0),10),".") -> 0.53 | M116: =_xlfn.NUMBERVALUE(INDEX(tb_SVI[],MATCH(Table3[[#This Row],[city_name]],tb_SVI[city_name_uf],0),11),".") -> 0.354 | N116: =_xlfn.PERCENTRANK.INC(Table3[MHDI_tot],Table3[[#This Row],[MHDI_tot]],3) -> 0.427
A117: =SVI!F77 -> Itamarati/AM | B117: =INDEX(tb_SVI[],MATCH(Table3[[#This Row],[ibge_cod]],tb_SVI[Município],0),1) -> AM | C117: =INDEX(tb_SVI[],MATCH(Table3[[#This Row],[city_name]],tb_SVI[city_name_uf],0),3) -> 1301951 | D117: BRA.4.30_1 | E117: =INDEX(tb_SVI[],MATCH(Table3[[#This Row],[city_name]],tb_SVI[city_name_uf],0),5) -> 7814 | F117: =INDEX(tb_MHDI[],MATCH(Table3[[#This Row],[city_name]],tb_MHDI[mun_uf],0),5) -> 0.477 | G117: =INDEX(tb_MHDI[],MATCH(Table3[[#This Row],[city_name]],tb_MHDI[mun_uf],0),6) -> 0.529 | H117: =INDEX(tb_MHDI[],MATCH(Table3[[#This Row],[city_name]],tb_MHDI[mun_uf],0),7) -> 0.772 | I117: =INDEX(tb_MHDI[],MATCH(Table3[[#This Row],[city_name]],tb_MHDI[mun_uf],0),8) -> 0.266 | J117: =_xlfn.NUMBERVALUE(INDEX(tb_SVI[],MATCH(Table3[[#This Row],[city_name]],tb_SVI[city_name_uf],0),8),".") -> 0.702 | K117: =_xlfn.NUMBERVALUE(INDEX(tb_SVI[],MATCH(Table3[[#This Row],[city_name]],tb_SVI[city_name_uf],0),9),".") -> 0.718 | L117: =_xlfn.NUMBERVALUE(INDEX(tb_SVI[],MATCH(Table3[[#This Row],[city_name]],tb_SVI[city_name_uf],0),10),".") -> 0.795 | M117: =_xlfn.NUMBERVALUE(INDEX(tb_SVI[],MATCH(Table3[[#This Row],[city_name]],tb_SVI[city_name_uf],0),11),".") -> 0.592 | N117: =_xlfn.PERCENTRANK.INC(Table3[MHDI_tot],Table3[[#This Row],[MHDI_tot]],3) -> 0.001
A118: =SVI!F118 -> Rio Preto da Eva/AM | B118: =INDEX(tb_SVI[],MATCH(Table3[[#This Row],[ibge_cod]],tb_SVI[Município],0),1) -> AM | C118: =INDEX(tb_SVI[],MATCH(Table3[[#This Row],[city_name]],tb_SVI[city_name_uf],0),3) -> 1303569 | D118: BRA.4.47_1 | E118: =INDEX(tb_SVI[],MATCH(Table3[[#This Row],[city_name]],tb_SVI[city_name_uf],0),5) -> 34106 | F118: =INDEX(tb_MHDI[],MATCH(Table3[[#This Row],[city_name]],tb_MHDI[mun_uf],0),5) -> 0.611 | G118: =INDEX(tb_MHDI[],MATCH(Table3[[#This Row],[city_name]],tb_MHDI[mun_uf],0),6) -> 0.59 | H118: =INDEX(tb_MHDI[],MATCH(Table3[[#This Row],[city_name]],tb_MHDI[mun_uf],0),7) -> 0.785 | I118: =INDEX(tb_MHDI[],MATCH(Table3[[#This Row],[city_name]],tb_MHDI[mun_uf],0),8) -> 0.493 | J118: =_xlfn.NUMBERVALUE(INDEX(tb_SVI[],MATCH(Table3[[#This Row],[city_name]],tb_SVI[city_name_uf],0),8),".") -> 0.474 | K118: =_xlfn.NUMBERVALUE(INDEX(tb_SVI[],MATCH(Table3[[#This Row],[city_name]],tb_SVI[city_name_uf],0),9),".") -> 0.326 | L118: =_xlfn.NUMBERVALUE(INDEX(tb_SVI[],MATCH(Table3[[#This Row],[city_name]],tb_SVI[city_name_uf],0),10),".") -> 0.554 | M118: =_xlfn.NUMBERVALUE(INDEX(tb_SVI[],MATCH(Table3[[#This Row],[city_name]],tb_SVI[city_name_uf],0),11),".") -> 0.541 | N118: =_xlfn.PERCENTRANK.INC(Table3[MHDI_tot],Table3[[#This Row],[MHDI_tot]],3) -> 0.299
A119: =SVI!F119 -> Pauini/AM | B119: =INDEX(tb_SVI[],MATCH(Table3[[#This Row],[ibge_cod]],tb_SVI[Município],0),1) -> AM | C119: =INDEX(tb_SVI[],MATCH(Table3[[#This Row],[city_name]],tb_SVI[city_name_uf],0),3) -> 1303502 | D119: BRA.4.45_1 | E119: =INDEX(tb_SVI[],MATCH(Table3[[#This Row],[city_name]],tb_SVI[city_name_uf],0),5) -> 19522 | F119: =INDEX(tb_MHDI[],MATCH(Table3[[#This Row],[city_name]],tb_MHDI[mun_uf],0),5) -> 0.496 | G119: =INDEX(tb_MHDI[],MATCH(Table3[[#This Row],[city_name]],tb_MHDI[mun_uf],0),6) -> 0.531 | H119: =INDEX(tb_MHDI[],MATCH(Table3[[#This Row],[city_name]],tb_MHDI[mun_uf],0),7) -> 0.724 | I119: =INDEX(tb_MHDI[],MATCH(Table3[[#This Row],[city_name]],tb_MHDI[mun_uf],0),8) -> 0.317 | J119: =_xlfn.NUMBERVALUE(INDEX(tb_SVI[],MATCH(Table3[[#This Row],[city_name]],tb_SVI[city_name_uf],0),8),".") -> 0.713 | K119: =_xlfn.NUMBERVALUE(INDEX(tb_SVI[],MATCH(Table3[[#This Row],[city_name]],tb_SVI[city_name_uf],0),9),".") -> 0.674 | L119: =_xlfn.NUMBERVALUE(INDEX(tb_SVI[],MATCH(Table3[[#This Row],[city_name]],tb_SVI[city_name_uf],0),10),".") -> 0.776 | M119: =_xlfn.NUMBERVALUE(INDEX(tb_SVI[],MATCH(Table3[[#This Row],[city_name]],tb_SVI[city_name_uf],0),11),".") -> 0.688 | N119: =_xlfn.PERCENTRANK.INC(Table3[MHDI_tot],Table3[[#This Row],[MHDI_tot]],3) -> 0.004
A120: =SVI!F120 -> Parintins/AM | B120: =INDEX(tb_SVI[],MATCH(Table3[[#This Row],[ibge_cod]],tb_SVI[Município],0),1) -> AM | C120: =INDEX(tb_SVI[],MATCH(Table3[[#This Row],[city_name]],tb_SVI[city_name_uf],0),3) -> 1303403 | D120: BRA.4.44_1 | E120: =INDEX(tb_SVI[],MATCH(Table3[[#This Row],[city_name]],tb_SVI[city_name_uf],0),5) -> 115363 | F120: =INDEX(tb_MHDI[],MATCH(Table3[[#This Row],[city_name]],tb_MHDI[mun_uf],0),5) -> 0.658 | G120: =INDEX(tb_MHDI[],MATCH(Table3[[#This Row],[city_name]],tb_MHDI[mun_uf],0),6) -> 0.589 | H120: =INDEX(tb_MHDI[],MATCH(Table3[[#This Row],[city_name]],tb_MHDI[mun_uf],0),7) -> 0.8 | I120: =INDEX(tb_MHDI[],MATCH(Table3[[#This Row],[city_name]],tb_MHDI[mun_uf],0),8) -> 0.605 | J120: =_xlfn.NUMBERVALUE(INDEX(tb_SVI[],MATCH(Table3[[#This Row],[city_name]],tb_SVI[city_name_uf],0),8),".") -> 0.489 | K120: =_xlfn.NUMBERVALUE(INDEX(tb_SVI[],MATCH(Table3[[#This Row],[city_name]],tb_SVI[city_name_uf],0),9),".") -> 0.509 | L120: =_xlfn.NUMBERVALUE(INDEX(tb_SVI[],MATCH(Table3[[#This Row],[city_name]],tb_SVI[city_name_uf],0),10),".") -> 0.465 | M120: =_xlfn.NUMBERVALUE(INDEX(tb_SVI[],MATCH(Table3[[#This Row],[city_name]],tb_SVI[city_name_uf],0),11),".") -> 0.494 | N120: =_xlfn.PERCENTRANK.INC(Table3[MHDI_tot],Table3[[#This Row],[MHDI_tot]],3) -> 0.467
A121: =SVI!F121 -> Novo Aripuanã/AM | B121: =INDEX(tb_SVI[],MATCH(Table3[[#This Row],[ibge_cod]],tb_SVI[Município],0),1) -> AM | C121: =INDEX(tb_SVI[],MATCH(Table3[[#This Row],[city_name]],tb_SVI[city_name_uf],0),3) -> 1303304 | D121: BRA.4.43_1 | E121: =INDEX(tb_SVI[],MATCH(Table3[[#This Row],[city_name]],tb_SVI[city_name_uf],0),5) -> 26046 | F121: =INDEX(tb_MHDI[],MATCH(Table3[[#This Row],[city_name]],tb_MHDI[mun_uf],0),5) -> 0.554 | G121: =INDEX(tb_MHDI[],MATCH(Table3[[#This Row],[city_name]],tb_MHDI[mun_uf],0),6) -> 0.532 | H121: =INDEX(tb_MHDI[],MATCH(Table3[[#This Row],[city_name]],tb_MHDI[mun_uf],0),7) -> 0.759 | I121: =INDEX(tb_MHDI[],MATCH(Table3[[#This Row],[city_name]],tb_MHDI[mun_uf],0),8) -> 0.421 | J121: =_xlfn.NUMBERVALUE(INDEX(tb_SVI[],MATCH(Table3[[#This Row],[city_name]],tb_SVI[city_name_uf],0),8),".") -> 0.698 | K121: =_xlfn.NUMBERVALUE(INDEX(tb_SVI[],MATCH(Table3[[#This Row],[city_name]],tb_SVI[city_name_uf],0),9),".") -> 0.815 | L121: =_xlfn.NUMBERVALUE(INDEX(tb_SVI[],MATCH(Table3[[#This Row],[city_name]],tb_SVI[city_name_uf],0),10),".") -> 0.657 | M121: =_xlfn.NUMBERVALUE(INDEX(tb_SVI[],MATCH(Table3[[#This Row],[city_name]],tb_SVI[city_name_uf],0),11),".") -> 0.621 | N121: =_xlfn.PERCENTRANK.INC(Table3[MHDI_tot],Table3[[#This Row],[MHDI_tot]],3) -> 0.073
A122: =SVI!F122 -> Nova Olinda do Norte/AM | B122: =INDEX(tb_SVI[],MATCH(Table3[[#This Row],[ibge_cod]],tb_SVI[Município],0),1) -> AM | C122: =INDEX(tb_SVI[],MATCH(Table3[[#This Row],[city_name]],tb_SVI[city_name_uf],0),3) -> 1303106 | D122: BRA.4.41_1 | E122: =INDEX(tb_SVI[],MATCH(Table3[[#This Row],[city_name]],tb_SVI[city_name_uf],0),5) -> 38026 | F122: =INDEX(tb_MHDI[],MATCH(Table3[[#This Row],[city_name]],tb_MHDI[mun_uf],0),5) -> 0.558 | G122: =INDEX(tb_MHDI[],MATCH(Table3[[#This Row],[city_name]],tb_MHDI[mun_uf],0),6) -> 0.541 | H122: =INDEX(tb_MHDI[],MATCH(Table3[[#This Row],[city_name]],tb_MHDI[mun_uf],0),7) -> 0.78 | I122: =INDEX(tb_MHDI[],MATCH(Table3[[#This Row],[city_name]],tb_MHDI[mun_uf],0),8) -> 0.412 | J122: =_xlfn.NUMBERVALUE(INDEX(tb_SVI[],MATCH(Table3[[#This Row],[city_name]],tb_SVI[city_name_uf],0),8),".") -> 0.543 | K122: =_xlfn.NUMBERVALUE(INDEX(tb_SVI[],MATCH(Table3[[#This Row],[city_name]],tb_SVI[city_name_uf],0),9),".") -> 0.387 | L122: =_xlfn.NUMBERVALUE(INDEX(tb_SVI[],MATCH(Table3[[#This Row],[city_name]],tb_SVI[city_name_uf],0),10),".") -> 0.592 | M122: =_xlfn.NUMBERVALUE(INDEX(tb_SVI[],MATCH(Table3[[#This Row],[city_name]],tb_SVI[city_name_uf],0),11),".") -> 0.649 | N122: =_xlfn.PERCENTRANK.INC(Table3[MHDI_tot],Table3[[#This Row],[MHDI_tot]],3) -> 0.084
A123: =SVI!F123 -> Nhamundá/AM | B123: =INDEX(tb_SVI[],MATCH(Table3[[#This Row],[ibge_cod]],tb_SVI[Município],0),1) -> AM | C123: =INDEX(tb_SVI[],MATCH(Table3[[#This Row],[city_name]],tb_SVI[city_name_uf],0),3) -> 1303007 | D123: BRA.4.40_1 | E123: =INDEX(tb_SVI[],MATCH(Table3[[#This Row],[city_name]],tb_SVI[city_name_uf],0),5) -> 21443 | F123: =INDEX(tb_MHDI[],MATCH(Table3[[#This Row],[city_name]],tb_MHDI[mun_uf],0),5) -> 0.586 | G123: =INDEX(tb_MHDI[],MATCH(Table3[[#This Row],[city_name]],tb_MHDI[mun_uf],0),6) -> 0.513 | H123: =INDEX(tb_MHDI[],MATCH(Table3[[#This Row],[city_name]],tb_MHDI[mun_uf],0),7) -> 0.779 | I123: =INDEX(tb_MHDI[],MATCH(Table3[[#This Row],[city_name]],tb_MHDI[mun_uf],0),8) -> 0.503 | J123: =_xlfn.NUMBERVALUE(INDEX(tb_SVI[],MATCH(Table3[[#This Row],[city_name]],tb_SVI[city_name_uf],0),8),".") -> 0.615 | K123: =_xlfn.NUMBERVALUE(INDEX(tb_SVI[],MATCH(Table3[[#This Row],[city_name]],tb_SVI[city_name_uf],0),9),".") -> 0.652 | L123: =_xlfn.NUMBERVALUE(INDEX(tb_SVI[],MATCH(Table3[[#This Row],[city_name]],tb_SVI[city_name_uf],0),10),".") -> 0.531 | M123: =_xlfn.NUMBERVALUE(INDEX(tb_SVI[],MATCH(Table3[[#This Row],[city_name]],tb_SVI[city_name_uf],0),11),".") -> 0.662 | N123: =_xlfn.PERCENTRANK.INC(Table3[MHDI_tot],Table3[[#This Row],[MHDI_tot]],3) -> 0.188
A124: =SVI!F5201 -> Sorriso/MT | B124: =INDEX(tb_SVI[],MATCH(Table3[[#This Row],[ibge_cod]],tb_SVI[Município],0),1) -> MT | C124: =INDEX(tb_SVI[],MATCH(Table3[[#This Row],[city_name]],tb_SVI[city_name_uf],0),3) -> 5107925 | D124: #N/A | E124: =INDEX(tb_SVI[],MATCH(Table3[[#This Row],[city_name]],tb_SVI[city_name_uf],0),5) -> 92769 | F124: =INDEX(tb_MHDI[],MATCH(Table3[[#This Row],[city_name]],tb_MHDI[mun_uf],0),5) -> 0.744 | G124: =INDEX(tb_MHDI[],MATCH(Table3[[#This Row],[city_name]],tb_MHDI[mun_uf],0),6) -> 0.774 | H124: =INDEX(tb_MHDI[],MATCH(Table3[[#This Row],[city_name]],tb_MHDI[mun_uf],0),7) -> 0.839 | I124: =INDEX(tb_MHDI[],MATCH(Table3[[#This Row],[city_name]],tb_MHDI[mun_uf],0),8) -> 0.635 | J124: =_xlfn.NUMBERVALUE(INDEX(tb_SVI[],MATCH(Table3[[#This Row],[city_name]],tb_SVI[city_name_uf],0),8),".") -> 0.22 | K124: =_xlfn.NUMBERVALUE(INDEX(tb_SVI[],MATCH(Table3[[#This Row],[city_name]],tb_SVI[city_name_uf],0),9),".") -> 0.038 | L124: =_xlfn.NUMBERVALUE(INDEX(tb_SVI[],MATCH(Table3[[#This Row],[city_name]],tb_SVI[city_name_uf],0),10),".") -> 0.371 | M124: =_xlfn.NUMBERVALUE(INDEX(tb_SVI[],MATCH(Table3[[#This Row],[city_name]],tb_SVI[city_name_uf],0),11),".") -> 0.252 | N124: =_xlfn.PERCENTRANK.INC(Table3[MHDI_tot],Table3[[#This Row],[MHDI_tot]],3) -> 0.875
A125: =SVI!F125 -> Maraã/AM | B125: =INDEX(tb_SVI[],MATCH(Table3[[#This Row],[ibge_cod]],tb_SVI[Município],0),1) -> AM | C125: =INDEX(tb_SVI[],MATCH(Table3[[#This Row],[city_name]],tb_SVI[city_name_uf],0),3) -> 1302801 | D125: BRA.4.38_1 | E125: =INDEX(tb_SVI[],MATCH(Table3[[#This Row],[city_name]],tb_SVI[city_name_uf],0),5) -> 18261 | F125: =INDEX(tb_MHDI[],MATCH(Table3[[#This Row],[city_name]],tb_MHDI[mun_uf],0),5) -> 0.498 | G125: =INDEX(tb_MHDI[],MATCH(Table3[[#This Row],[city_name]],tb_MHDI[mun_uf],0),6) -> 0.466 | H125: =INDEX(tb_MHDI[],MATCH(Table3[[#This Row],[city_name]],tb_MHDI[mun_uf],0),7) -> 0.763 | I125: =INDEX(tb_MHDI[],MATCH(Table3[[#This Row],[city_name]],tb_MHDI[mun_uf],0),8) -> 0.348 | J125: =_xlfn.NUMBERVALUE(INDEX(tb_SVI[],MATCH(Table3[[#This Row],[city_name]],tb_SVI[city_name_uf],0),8),".") -> 0.682 | K125: =_xlfn.NUMBERVALUE(INDEX(tb_SVI[],MATCH(Table3[[#This Row],[city_name]],tb_SVI[city_name_uf],0),9),".") -> 0.601 | L125: =_xlfn.NUMBERVALUE(INDEX(tb_SVI[],MATCH(Table3[[#This Row],[city_name]],tb_SVI[city_name_uf],0),10),".") -> 0.722 | M125: =_xlfn.NUMBERVALUE(INDEX(tb_SVI[],MATCH(Table3[[#This Row],[city_name]],tb_SVI[city_name_uf],0),11),".") -> 0.724 | N125: =_xlfn.PERCENTRANK.INC(Table3[MHDI_tot],Table3[[#This Row],[MHDI_tot]],3) -> 0.005
A126: =SVI!F126 -> Manicoré/AM | B126: =INDEX(tb_SVI[],MATCH(Table3[[#This Row],[ibge_cod]],tb_SVI[Município],0),1) -> AM | C126: =INDEX(tb_SVI[],MATCH(Table3[[#This Row],[city_name]],tb_SVI[city_name_uf],0),3) -> 1302702 | D126: BRA.4.37_1 | E126: =INDEX(tb_SVI[],MATCH(Table3[[#This Row],[city_name]],tb_SVI[city_name_uf],0),5) -> 56583 | F126: =INDEX(tb_MHDI[],MATCH(Table3[[#This Row],[city_name]],tb_MHDI[mun_uf],0),5) -> 0.582 | G126: =INDEX(tb_MHDI[],MATCH(Table3[[#This Row],[city_name]],tb_MHDI[mun_uf],0),6) -> 0.58 | H126: =INDEX(tb_MHDI[],MATCH(Table3[[#This Row],[city_name]],tb_MHDI[mun_uf],0),7) -> 0.747 | I126: =INDEX(tb_MHDI[],MATCH(Table3[[#This Row],[city_name]],tb_MHDI[mun_uf],0),8) -> 0.456 | J126: =_xlfn.NUMBERVALUE(INDEX(tb_SVI[],MATCH(Table3[[#This Row],[city_name]],tb_SVI[city_name_uf],0),8),".") -> 0.547 | K126: =_xlfn.NUMBERVALUE(INDEX(tb_SVI[],MATCH(Table3[[#This Row],[city_name]],tb_SVI[city_name_uf],0),9),".") -> 0.464 | L126: =_xlfn.NUMBERVALUE(INDEX(tb_SVI[],MATCH(Table3[[#This Row],[city_name]],tb_SVI[city_name_uf],0),10),".") -> 0.604 | M126: =_xlfn.NUMBERVALUE(INDEX(tb_SVI[],MATCH(Table3[[#This Row],[city_name]],tb_SVI[city_name_uf],0),11),".") -> 0.574 | N126: =_xlfn.PERCENTRANK.INC(Table3[MHDI_tot],Table3[[#This Row],[MHDI_tot]],3) -> 0.171
A127: =SVI!F127 -> Manaquiri/AM | B127: =INDEX(tb_SVI[],MATCH(Table3[[#This Row],[ibge_cod]],tb_SVI[Município],0),1) -> AM | C127: =INDEX(tb_SVI[],MATCH(Table3[[#This Row],[city_name]],tb_SVI[city_name_uf],0),3) -> 1302553 | D127: BRA.4.36_1 | E127: =INDEX(tb_SVI[],MATCH(Table3[[#This Row],[city_name]],tb_SVI[city_name_uf],0),5) -> 33049 | F127: =INDEX(tb_MHDI[],MATCH(Table3[[#This Row],[city_name]],tb_MHDI[mun_uf],0),5) -> 0.596 | G127: =INDEX(tb_MHDI[],MATCH(Table3[[#This Row],[city_name]],tb_MHDI[mun_uf],0),6) -> 0.556 | H127: =INDEX(tb_MHDI[],MATCH(Table3[[#This Row],[city_name]],tb_MHDI[mun_uf],0),7) -> 0.748 | I127: =INDEX(tb_MHDI[],MATCH(Table3[[#This Row],[city_name]],tb_MHDI[mun_uf],0),8) -> 0.51 | J127: =_xlfn.NUMBERVALUE(INDEX(tb_SVI[],MATCH(Table3[[#This Row],[city_name]],tb_SVI[city_name_uf],0),8),".") -> 0.535 | K127: =_xlfn.NUMBERVALUE(INDEX(tb_SVI[],MATCH(Table3[[#This Row],[city_name]],tb_SVI[city_name_uf],0),9),".") -> 0.552 | L127: =_xlfn.NUMBERVALUE(INDEX(tb_SVI[],MATCH(Table3[[#This Row],[city_name]],tb_SVI[city_name_uf],0),10),".") -> 0.504 | M127: =_xlfn.NUMBERVALUE(INDEX(tb_SVI[],MATCH(Table3[[#This Row],[city_name]],tb_SVI[city_name_uf],0),11),".") -> 0.549 | N127: =_xlfn.PERCENTRANK.INC(Table3[MHDI_tot],Table3[[#This Row],[MHDI_tot]],3) -> 0.235
A128: =SVI!F128 -> Lábrea/AM | B128: =INDEX(tb_SVI[],MATCH(Table3[[#This Row],[ibge_cod]],tb_SVI[Município],0),1) -> AM | C128: =INDEX(tb_SVI[],MATCH(Table3[[#This Row],[city_name]],tb_SVI[city_name_uf],0),3) -> 1302405 | D128: BRA.4.34_1 | E128: =INDEX(tb_SVI[],MATCH(Table3[[#This Row],[city_name]],tb_SVI[city_name_uf],0),5) -> 46882 | F128: =INDEX(tb_MHDI[],MATCH(Table3[[#This Row],[city_name]],tb_MHDI[mun_uf],0),5) -> 0.531 | G128: =INDEX(tb_MHDI[],MATCH(Table3[[#This Row],[city_name]],tb_MHDI[mun_uf],0),6) -> 0.538 | H128: =INDEX(tb_MHDI[],MATCH(Table3[[#This Row],[city_name]],tb_MHDI[mun_uf],0),7) -> 0.744 | I128: =INDEX(tb_MHDI[],MATCH(Table3[[#This Row],[city_name]],tb_MHDI[mun_uf],0),8) -> 0.374 | J128: =_xlfn.NUMBERVALUE(INDEX(tb_SVI[],MATCH(Table3[[#This Row],[city_name]],tb_SVI[city_name_uf],0),8),".") -> 0.654 | K128: =_xlfn.NUMBERVALUE(INDEX(tb_SVI[],MATCH(Table3[[#This Row],[city_name]],tb_SVI[city_name_uf],0),9),".") -> 0.552 | L128: =_xlfn.NUMBERVALUE(INDEX(tb_SVI[],MATCH(Table3[[#This Row],[city_name]],tb_SVI[city_name_uf],0),10),".") -> 0.788 | M128: =_xlfn.NUMBERVALUE(INDEX(tb_SVI[],MATCH(Table3[[#This Row],[city_name]],tb_SVI[city_name_uf],0),11),".") -> 0.623 | N128: =_xlfn.PERCENTRANK.INC(Table3[MHDI_tot],Table3[[#This Row],[MHDI_tot]],3) -> 0.03
A129: =SVI!F129 -> Jutaí/AM | B129: =INDEX(tb_SVI[],MATCH(Table3[[#This Row],[ibge_cod]],tb_SVI[Município],0),1) -> AM | C129: =INDEX(tb_SVI[],MATCH(Table3[[#This Row],[city_name]],tb_SVI[city_name_uf],0),3) -> 1302306 | D129: BRA.4.33_1 | E129: =INDEX(tb_SVI[],MATCH(Table3[[#This Row],[city_name]],tb_SVI[city_name_uf],0),5) -> 13886 | F129: =INDEX(tb_MHDI[],MATCH(Table3[[#This Row],[city_name]],tb_MHDI[mun_uf],0),5) -> 0.516 | G129: =INDEX(tb_MHDI[],MATCH(Table3[[#This Row],[city_name]],tb_MHDI[mun_uf],0),6) -> 0.528 | H129: =INDEX(tb_MHDI[],MATCH(Table3[[#This Row],[city_name]],tb_MHDI[mun_uf],0),7) -> 0.766 | I129: =INDEX(tb_MHDI[],MATCH(Table3[[#This Row],[city_name]],tb_MHDI[mun_uf],0),8) -> 0.34 | J129: =_xlfn.NUMBERVALUE(INDEX(tb_SVI[],MATCH(Table3[[#This Row],[city_name]],tb_SVI[city_name_uf],0),8),".") -> 0.743 | K129: =_xlfn.NUMBERVALUE(INDEX(tb_SVI[],MATCH(Table3[[#This Row],[city_name]],tb_SVI[city_name_uf],0),9),".") -> 0.808 | L129: =_xlfn.NUMBERVALUE(INDEX(tb_SVI[],MATCH(Table3[[#This Row],[city_name]],tb_SVI[city_name_uf],0),10),".") -> 0.724 | M129: =_xlfn.NUMBERVALUE(INDEX(tb_SVI[],MATCH(Table3[[#This Row],[city_name]],tb_SVI[city_name_uf],0),11),".") -> 0.696 | N129: =_xlfn.PERCENTRANK.INC(Table3[MHDI_tot],Table3[[#This Row],[MHDI_tot]],3) -> 0.015
A130: =SVI!F130 -> Juruá/AM | B130: =INDEX(tb_SVI[],MATCH(Table3[[#This Row],[ibge_cod]],tb_SVI[Município],0),1) -> AM | C130: =INDEX(tb_SVI[],MATCH(Table3[[#This Row],[city_name]],tb_SVI[city_name_uf],0),3) -> 1302207 | D130: BRA.4.32_1 | E130: =INDEX(tb_SVI[],MATCH(Table3[[#This Row],[city_name]],tb_SVI[city_name_uf],0),5) -> 15106 | F130: =INDEX(tb_MHDI[],MATCH(Table3[[#This Row],[city_name]],tb_MHDI[mun_uf],0),5) -> 0.522 | G130: =INDEX(tb_MHDI[],MATCH(Table3[[#This Row],[city_name]],tb_MHDI[mun_uf],0),6) -> 0.538 | H130: =INDEX(tb_MHDI[],MATCH(Table3[[#This Row],[city_name]],tb_MHDI[mun_uf],0),7) -> 0.704 | I130: =INDEX(tb_MHDI[],MATCH(Table3[[#This Row],[city_name]],tb_MHDI[mun_uf],0),8) -> 0.376 | J130: =_xlfn.NUMBERVALUE(INDEX(tb_SVI[],MATCH(Table3[[#This Row],[city_name]],tb_SVI[city_name_uf],0),8),".") -> 0.673 | K130: =_xlfn.NUMBERVALUE(INDEX(tb_SVI[],MATCH(Table3[[#This Row],[city_name]],tb_SVI[city_name_uf],0),9),".") -> 0.649 | L130: =_xlfn.NUMBERVALUE(INDEX(tb_SVI[],MATCH(Table3[[#This Row],[city_name]],tb_SVI[city_name_uf],0),10),".") -> 0.741 | M130: =_xlfn.NUMBERVALUE(INDEX(tb_SVI[],MATCH(Table3[[#This Row],[city_name]],tb_SVI[city_name_uf],0),11),".") -> 0.628 | N130: =_xlfn.PERCENTRANK.INC(Table3[MHDI_tot],Table3[[#This Row],[MHDI_tot]],3) -> 0.02
A131: =SVI!F131 -> Japurá/AM | B131: =INDEX(tb_SVI[],MATCH(Table3[[#This Row],[ibge_cod]],tb_SVI[Município],0),1) -> AM | C131: =INDEX(tb_SVI[],MATCH(Table3[[#This Row],[city_name]],tb_SVI[city_name_uf],0),3) -> 1302108 | D131: BRA.4.31_1 | E131: =INDEX(tb_SVI[],MATCH(Table3[[#This Row],[city_name]],tb_SVI[city_name_uf],0),5) -> 2251 | F131: =INDEX(tb_MHDI[],MATCH(Table3[[#This Row],[city_name]],tb_MHDI[mun_uf],0),5) -> 0.522 | G131: =INDEX(tb_MHDI[],MATCH(Table3[[#This Row],[city_name]],tb_MHDI[mun_uf],0),6) -> 0.552 | H131: =INDEX(tb_MHDI[],MATCH(Table3[[#This Row],[city_name]],tb_MHDI[mun_uf],0),7) -> 0.748 | I131: =INDEX(tb_MHDI[],MATCH(Table3[[#This Row],[city_name]],tb_MHDI[mun_uf],0),8) -> 0.345 | J131: =_xlfn.NUMBERVALUE(INDEX(tb_SVI[],MATCH(Table3[[#This Row],[city_name]],tb_SVI[city_name_uf],0),8),".") -> 0.636 | K131: =_xlfn.NUMBERVALUE(INDEX(tb_SVI[],MATCH(Table3[[#This Row],[city_name]],tb_SVI[city_name_uf],0),9),".") -> 0.573 | L131: =_xlfn.NUMBERVALUE(INDEX(tb_SVI[],MATCH(Table3[[#This Row],[city_name]],tb_SVI[city_name_uf],0),10),".") -> 0.743 | M131: =_xlfn.NUMBERVALUE(INDEX(tb_SVI[],MATCH(Table3[[#This Row],[city_name]],tb_SVI[city_name_uf],0),11),".") -> 0.591 | N131: =_xlfn.PERCENTRANK.INC(Table3[MHDI_tot],Table3[[#This Row],[MHDI_tot]],3) -> 0.02
A132: =SVI!F132 -> Tabatinga/AM | B132: =INDEX(tb_SVI[],MATCH(Table3[[#This Row],[ibge_cod]],tb_SVI[Município],0),1) -> AM | C132: =INDEX(tb_SVI[],MATCH(Table3[[#This Row],[city_name]],tb_SVI[city_name_uf],0),3) -> 1304062 | D132: BRA.4.54_1 | E132: =INDEX(tb_SVI[],MATCH(Table3[[#This Row],[city_name]],tb_SVI[city_name_uf],0),5) -> 67182 | F132: =INDEX(tb_MHDI[],MATCH(Table3[[#This Row],[city_name]],tb_MHDI[mun_uf],0),5) -> 0.616 | G132: =INDEX(tb_MHDI[],MATCH(Table3[[#This Row],[city_name]],tb_MHDI[mun_uf],0),6) -> 0.602 | H132: =INDEX(tb_MHDI[],MATCH(Table3[[#This Row],[city_name]],tb_MHDI[mun_uf],0),7) -> 0.769 | I132: =INDEX(tb_MHDI[],MATCH(Table3[[#This Row],[city_name]],tb_MHDI[mun_uf],0),8) -> 0.505 | J132: =_xlfn.NUMBERVALUE(INDEX(tb_SVI[],MATCH(Table3[[#This Row],[city_name]],tb_SVI[city_name_uf],0),8),".") -> 0.577 | K132: =_xlfn.NUMBERVALUE(INDEX(tb_SVI[],MATCH(Table3[[#This Row],[city_name]],tb_SVI[city_name_uf],0),9),".") -> 0.645 | L132: =_xlfn.NUMBERVALUE(INDEX(tb_SVI[],MATCH(Table3[[#This Row],[city_name]],tb_SVI[city_name_uf],0),10),".") -> 0.582 | M132: =_xlfn.NUMBERVALUE(INDEX(tb_SVI[],MATCH(Table3[[#This Row],[city_name]],tb_SVI[city_name_uf],0),11),".") -> 0.504 | N132: =_xlfn.PERCENTRANK.INC(Table3[MHDI_tot],Table3[[#This Row],[MHDI_tot]],3) -> 0.318
A133: =SVI!F133 -> São Sebastião do Uatumã/AM | B133: =INDEX(tb_SVI[],MATCH(Table3[[#This Row],[ibge_cod]],tb_SVI[Município],0),1) -> AM | C133: =INDEX(tb_SVI[],MATCH(Table3[[#This Row],[city_name]],tb_SVI[city_name_uf],0),3) -> 1303957 | D133: BRA.4.52_1 | E133: =INDEX(tb_SVI[],MATCH(Table3[[#This Row],[city_name]],tb_SVI[city_name_uf],0),5) -> 14352 | F133: =INDEX(tb_MHDI[],MATCH(Table3[[#This Row],[city_name]],tb_MHDI[mun_uf],0),5) -> 0.577 | G133: =INDEX(tb_MHDI[],MATCH(Table3[[#This Row],[city_name]],tb_MHDI[mun_uf],0),6) -> 0.561 | H133: =INDEX(tb_MHDI[],MATCH(Table3[[#This Row],[city_name]],tb_MHDI[mun_uf],0),7) -> 0.739 | I133: =INDEX(tb_MHDI[],MATCH(Table3[[#This Row],[city_name]],tb_MHDI[mun_uf],0),8) -> 0.464 | J133: =_xlfn.NUMBERVALUE(INDEX(tb_SVI[],MATCH(Table3[[#This Row],[city_name]],tb_SVI[city_name_uf],0),8),".") -> 0.572 | K133: =_xlfn.NUMBERVALUE(INDEX(tb_SVI[],MATCH(Table3[[#This Row],[city_name]],tb_SVI[city_name_uf],0),9),".") -> 0.69 | L133: =_xlfn.NUMBERVALUE(INDEX(tb_SVI[],MATCH(Table3[[#This Row],[city_name]],tb_SVI[city_name_uf],0),10),".") -> 0.54 | M133: =_xlfn.NUMBERVALUE(INDEX(tb_SVI[],MATCH(Table3[[#This Row],[city_name]],tb_SVI[city_name_uf],0),11),".") -> 0.485 | N133: =_xlfn.PERCENTRANK.INC(Table3[MHDI_tot],Table3[[#This Row],[MHDI_tot]],3) -> 0.152
A134: =SVI!F134 -> São Paulo de Olivença/AM | B134: =INDEX(tb_SVI[],MATCH(Table3[[#This Row],[ibge_cod]],tb_SVI[Município],0),1) -> AM | C134: =INDEX(tb_SVI[],MATCH(Table3[[#This Row],[city_name]],tb_SVI[city_name_uf],0),3) -> 1303908 | D134: BRA.4.51_1 | E134: =INDEX(tb_SVI[],MATCH(Table3[[#This Row],[city_name]],tb_SVI[city_name_uf],0),5) -> 40073 | F134: =INDEX(tb_MHDI[],MATCH(Table3[[#This Row],[city_name]],tb_MHDI[mun_uf],0),5) -> 0.521 | G134: =INDEX(tb_MHDI[],MATCH(Table3[[#This Row],[city_name]],tb_MHDI[mun_uf],0),6) -> 0.471 | H134: =INDEX(tb_MHDI[],MATCH(Table3[[#This Row],[city_name]],tb_MHDI[mun_uf],0),7) -> 0.78 | I134: =INDEX(tb_MHDI[],MATCH(Table3[[#This Row],[city_name]],tb_MHDI[mun_uf],0),8) -> 0.386 | J134: =_xlfn.NUMBERVALUE(INDEX(tb_SVI[],MATCH(Table3[[#This Row],[city_name]],tb_SVI[city_name_uf],0),8),".") -> 0.693 | K134: =_xlfn.NUMBERVALUE(INDEX(tb_SVI[],MATCH(Table3[[#This Row],[city_name]],tb_SVI[city_name_uf],0),9),".") -> 0.841 | L134: =_xlfn.NUMBERVALUE(INDEX(tb_SVI[],MATCH(Table3[[#This Row],[city_name]],tb_SVI[city_name_uf],0),10),".") -> 0.59 | M134: =_xlfn.NUMBERVALUE(INDEX(tb_SVI[],MATCH(Table3[[#This Row],[city_name]],tb_SVI[city_name_uf],0),11),".") -> 0.648 | N134: =_xlfn.PERCENTRANK.INC(Table3[MHDI_tot],Table3[[#This Row],[MHDI_tot]],3) -> 0.019
A135: =SVI!F135 -> São Gabriel da Cachoeira/AM | B135: =INDEX(tb_SVI[],MATCH(Table3[[#This Row],[ibge_cod]],tb_SVI[Município],0),1) -> AM | C135: =INDEX(tb_SVI[],MATCH(Table3[[#This Row],[city_name]],tb_SVI[city_name_uf],0),3) -> 1303809 | D135: BRA.4.50_1 | E135: =INDEX(tb_SVI[],MATCH(Table3[[#This Row],[city_name]],tb_SVI[city_name_uf],0),5) -> 46303 | F135: =INDEX(tb_MHDI[],MATCH(Table3[[#This Row],[city_name]],tb_MHDI[mun_uf],0),5) -> 0.609 | G135: =INDEX(tb_MHDI[],MATCH(Table3[[#This Row],[city_name]],tb_MHDI[mun_uf],0),6) -> 0.61 | H135: =INDEX(tb_MHDI[],MATCH(Table3[[#This Row],[city_name]],tb_MHDI[mun_uf],0),7) -> 0.777 | I135: =INDEX(tb_MHDI[],MATCH(Table3[[#This Row],[city_name]],tb_MHDI[mun_uf],0),8) -> 0.476 | J135: =_xlfn.NUMBERVALUE(INDEX(tb_SVI[],MATCH(Table3[[#This Row],[city_name]],tb_SVI[city_name_uf],0),8),".") -> 0.492 | K135: =_xlfn.NUMBERVALUE(INDEX(tb_SVI[],MATCH(Table3[[#This Row],[city_name]],tb_SVI[city_name_uf],0),9),".") -> 0.356 | L135: =_xlfn.NUMBERVALUE(INDEX(tb_SVI[],MATCH(Table3[[#This Row],[city_name]],tb_SVI[city_name_uf],0),10),".") -> 0.55 | M135: =_xlfn.NUMBERVALUE(INDEX(tb_SVI[],MATCH(Table3[[#This Row],[city_name]],tb_SVI[city_name_uf],0),11),".") -> 0.569 | N135: =_xlfn.PERCENTRANK.INC(Table3[MHDI_tot],Table3[[#This Row],[MHDI_tot]],3) -> 0.289
A136: =SVI!F136 -> Silves/AM | B136: =INDEX(tb_SVI[],MATCH(Table3[[#This Row],[ibge_cod]],tb_SVI[Município],0),1) -> AM | C136: =INDEX(tb_SVI[],MATCH(Table3[[#This Row],[city_name]],tb_SVI[city_name_uf],0),3) -> 1304005 | D136: BRA.4.53_1 | E136: =INDEX(tb_SVI[],MATCH(Table3[[#This Row],[city_name]],tb_SVI[city_name_uf],0),5) -> 9230 | F136: =INDEX(tb_MHDI[],MATCH(Table3[[#This Row],[city_name]],tb_MHDI[mun_uf],0),5) -> 0.632 | G136: =INDEX(tb_MHDI[],MATCH(Table3[[#This Row],[city_name]],tb_MHDI[mun_uf],0),6) -> 0.546 | H136: =INDEX(tb_MHDI[],MATCH(Table3[[#This Row],[city_name]],tb_MHDI[mun_uf],0),7) -> 0.791 | I136: =INDEX(tb_MHDI[],MATCH(Table3[[#This Row],[city_name]],tb_MHDI[mun_uf],0),8) -> 0.584 | J136: =_xlfn.NUMBERVALUE(INDEX(tb_SVI[],MATCH(Table3[[#This Row],[city_name]],tb_SVI[city_name_uf],0),8),".") -> 0.598 | K136: =_xlfn.NUMBERVALUE(INDEX(tb_SVI[],MATCH(Table3[[#This Row],[city_name]],tb_SVI[city_name_uf],0),9),".") -> 0.7 | L136: =_xlfn.NUMBERVALUE(INDEX(tb_SVI[],MATCH(Table3[[#This Row],[city_name]],tb_SVI[city_name_uf],0),10),".") -> 0.563 | M136: =_xlfn.NUMBERVALUE(INDEX(tb_SVI[],MATCH(Table3[[#This Row],[city_name]],tb_SVI[city_name_uf],0),11),".") -> 0.532 | N136: =_xlfn.PERCENTRANK.INC(Table3[MHDI_tot],Table3[[#This Row],[MHDI_tot]],3) -> 0.376
... A164: =SVI!F164 -> Cametá/PA | B164: =INDEX(tb_SVI[],MATCH(Table3[[#This Row],[ibge_cod]],tb_SVI[Município],0),1) -> PA | C164: =INDEX(tb_SVI[],MATCH(Table3[[#This Row],[city_name]],tb_SVI[city_name_uf],0),3) -> 1502103 | D164: BRA.14.32_1 | E164: =INDEX(tb_SVI[],MATCH(Table3[[#This Row],[city_name]],tb_SVI[city_name_uf],0),5) -> 139364 | F164: =INDEX(tb_MHDI[],MATCH(Table3[[#This Row],[city_name]],tb_MHDI[mun_uf],0),5) -> 0.577 | G164: =INDEX(tb_MHDI[],MATCH(Table3[[#This Row],[city_name]],tb_MHDI[mun_uf],0),6) -> 0.538 | H164: =INDEX(tb_MHDI[],MATCH(Table3[[#This Row],[city_name]],tb_MHDI[mun_uf],0),7) -> 0.754 | I164: =INDEX(tb_MHDI[],MATCH(Table3[[#This Row],[city_name]],tb_MHDI[mun_uf],0),8) -> 0.474 | J164: =_xlfn.NUMBERVALUE(INDEX(tb_SVI[],MATCH(Table3[[#This Row],[city_name]],tb_SVI[city_name_uf],0),8),".") -> 0.541 | K164: =_xlfn.NUMBERVALUE(INDEX(tb_SVI[],MATCH(Table3[[#This Row],[city_name]],tb_SVI[city_name_uf],0),9),".") -> 0.522 | L164: =_xlfn.NUMBERVALUE(INDEX(tb_SVI[],MATCH(Table3[[#This Row],[city_name]],tb_SVI[city_name_uf],0),10),".") -> 0.487 | M164: =_xlfn.NUMBERVALUE(INDEX(tb_SVI[],MATCH(Table3[[#This Row],[city_name]],tb_SVI[city_name_uf],0),11),".") -> 0.613 | N164: =_xlfn.PERCENTRANK.INC(Table3[MHDI_tot],Table3[[#This Row],[MHDI_tot]],3) -> 0.152
A165: =SVI!F117 -> Santa Isabel do Rio Negro/AM | B165: =INDEX(tb_SVI[],MATCH(Table3[[#This Row],[ibge_cod]],tb_SVI[Município],0),1) -> AM | C165: =INDEX(tb_SVI[],MATCH(Table3[[#This Row],[city_name]],tb_SVI[city_name_uf],0),3) -> 1303601 | D165: BRA.4.48_1 | E165: =INDEX(tb_SVI[],MATCH(Table3[[#This Row],[city_name]],tb_SVI[city_name_uf],0),5) -> 25865 | F165: =INDEX(tb_MHDI[],MATCH(Table3[[#This Row],[city_name]],tb_MHDI[mun_uf],0),5) -> 0.479 | G165: =INDEX(tb_MHDI[],MATCH(Table3[[#This Row],[city_name]],tb_MHDI[mun_uf],0),6) -> 0.461 | H165: =INDEX(tb_MHDI[],MATCH(Table3[[#This Row],[city_name]],tb_MHDI[mun_uf],0),7) -> 0.737 | I165: =INDEX(tb_MHDI[],MATCH(Table3[[#This Row],[city_name]],tb_MHDI[mun_uf],0),8) -> 0.323 | J165: =_xlfn.NUMBERVALUE(INDEX(tb_SVI[],MATCH(Table3[[#This Row],[city_name]],tb_SVI[city_name_uf],0),8),".") -> 0.616 | K165: =_xlfn.NUMBERVALUE(INDEX(tb_SVI[],MATCH(Table3[[#This Row],[city_name]],tb_SVI[city_name_uf],0),9),".") -> 0.388 | L165: =_xlfn.NUMBERVALUE(INDEX(tb_SVI[],MATCH(Table3[[#This Row],[city_name]],tb_SVI[city_name_uf],0),10),".") -> 0.751 | M165: =_xlfn.NUMBERVALUE(INDEX(tb_SVI[],MATCH(Table3[[#This Row],[city_name]],tb_SVI[city_name_uf],0),11),".") -> 0.71 | N165: =_xlfn.PERCENTRANK.INC(Table3[MHDI_tot],Table3[[#This Row],[MHDI_tot]],3) -> 0.001
A166: =SVI!F166 -> Colares/PA | B166: =INDEX(tb_SVI[],MATCH(Table3[[#This Row],[ibge_cod]],tb_SVI[Município],0),1) -> PA | C166: =INDEX(tb_SVI[],MATCH(Table3[[#This Row],[city_name]],tb_SVI[city_name_uf],0),3) -> 1502608 | D166: BRA.14.38_1 | E166: =INDEX(tb_SVI[],MATCH(Table3[[#This Row],[city_name]],tb_SVI[city_name_uf],0),5) -> 12131 | F166: =INDEX(tb_MHDI[],MATCH(Table3[[#This Row],[city_name]],tb_MHDI[mun_uf],0),5) -> 0.602 | G166: =INDEX(tb_MHDI[],MATCH(Table3[[#This Row],[city_name]],tb_MHDI[mun_uf],0),6) -> 0.541 | H166: =INDEX(tb_MHDI[],MATCH(Table3[[#This Row],[city_name]],tb_MHDI[mun_uf],0),7) -> 0.763 | I166: =INDEX(tb_MHDI[],MATCH(Table3[[#This Row],[city_name]],tb_MHDI[mun_uf],0),8) -> 0.528 | J166: =_xlfn.NUMBERVALUE(INDEX(tb_SVI[],MATCH(Table3[[#This Row],[city_name]],tb_SVI[city_name_uf],0),8),".") -> 0.491 | K166: =_xlfn.NUMBERVALUE(INDEX(tb_SVI[],MATCH(Table3[[#This Row],[city_name]],tb_SVI[city_name_uf],0),9),".") -> 0.535 | L166: =_xlfn.NUMBERVALUE(INDEX(tb_SVI[],MATCH(Table3[[#This Row],[city_name]],tb_SVI[city_name_uf],0),10),".") -> 0.455 | M166: =_xlfn.NUMBERVALUE(INDEX(tb_SVI[],MATCH(Table3[[#This Row],[city_name]],tb_SVI[city_name_uf],0),11),".") -> 0.483 | N166: =_xlfn.PERCENTRANK.INC(Table3[MHDI_tot],Table3[[#This Row],[MHDI_tot]],3) -> 0.259
A167: =SVI!F167 -> Cachoeira do Arari/PA | B167: =INDEX(tb_SVI[],MATCH(Table3[[#This Row],[ibge_cod]],tb_SVI[Município],0),1) -> PA | C167: =INDEX(tb_SVI[],MATCH(Table3[[#This Row],[city_name]],tb_SVI[city_name_uf],0),3) -> 1502004 | D167: BRA.14.30_1 | E167: =INDEX(tb_SVI[],MATCH(Table3[[#This Row],[city_name]],tb_SVI[city_name_uf],0),5) -> 24064 | F167: =INDEX(tb_MHDI[],MATCH(Table3[[#This Row],[city_name]],tb_MHDI[mun_uf],0),5) -> 0.546 | G167: =INDEX(tb_MHDI[],MATCH(Table3[[#This Row],[city_name]],tb_MHDI[mun_uf],0),6) -> 0.525 | H167: =INDEX(tb_MHDI[],MATCH(Table3[[#This Row],[city_name]],tb_MHDI[mun_uf],0),7) -> 0.778 | I167: =INDEX(tb_MHDI[],MATCH(Table3[[#This Row],[city_name]],tb_MHDI[mun_uf],0),8) -> 0.398 | J167: =_xlfn.NUMBERVALUE(INDEX(tb_SVI[],MATCH(Table3[[#This Row],[city_name]],tb_SVI[city_name_uf],0),8),".") -> 0.606 | K167: =_xlfn.NUMBERVALUE(INDEX(tb_SVI[],MATCH(Table3[[#This Row],[city_name]],tb_SVI[city_name_uf],0),9),".") -> 0.597 | L167: =_xlfn.NUMBERVALUE(INDEX(tb_SVI[],MATCH(Table3[[#This Row],[city_name]],tb_SVI[city_name_uf],0),10),".") -> 0.589 | M167: =_xlfn.NUMBERVALUE(INDEX(tb_SVI[],MATCH(Table3[[#This Row],[city_name]],tb_SVI[city_name_uf],0),11),".") -> 0.633 | N167: =_xlfn.PERCENTRANK.INC(Table3[MHDI_tot],Table3[[#This Row],[MHDI_tot]],3) -> 0.053
A168: =SVI!F168 -> Bujaru/PA | B168: =INDEX(tb_SVI[],MATCH(Table3[[#This Row],[ibge_cod]],tb_SVI[Município],0),1) -> PA | C168: =INDEX(tb_SVI[],MATCH(Table3[[#This Row],[city_name]],tb_SVI[city_name_uf],0),3) -> 1501907 | D168: BRA.14.29_1 | E168: =INDEX(tb_SVI[],MATCH(Table3[[#This Row],[city_name]],tb_SVI[city_name_uf],0),5) -> 29427 | F168: =INDEX(tb_MHDI[],MATCH(Table3[[#This Row],[city_name]],tb_MHDI[mun_uf],0),5) -> 0.552 | G168: =INDEX(tb_MHDI[],MATCH(Table3[[#This Row],[city_name]],tb_MHDI[mun_uf],0),6) -> 0.495 | H168: =INDEX(tb_MHDI[],MATCH(Table3[[#This Row],[city_name]],tb_MHDI[mun_uf],0),7) -> 0.779 | I168: =INDEX(tb_MHDI[],MATCH(Table3[[#This Row],[city_name]],tb_MHDI[mun_uf],0),8) -> 0.437 | J168: =_xlfn.NUMBERVALUE(INDEX(tb_SVI[],MATCH(Table3[[#This Row],[city_name]],tb_SVI[city_name_uf],0),8),".") -> 0.532 | K168: =_xlfn.NUMBERVALUE(INDEX(tb_SVI[],MATCH(Table3[[#This Row],[city_name]],tb_SVI[city_name_uf],0),9),".") -> 0.496 | L168: =_xlfn.NUMBERVALUE(INDEX(tb_SVI[],MATCH(Table3[[#This Row],[city_name]],tb_SVI[city_name_uf],0),10),".") -> 0.512 | M168: =_xlfn.NUMBERVALUE(INDEX(tb_SVI[],MATCH(Table3[[#This Row],[city_name]],tb_SVI[city_name_uf],0),11),".") -> 0.587 | N168: =_xlfn.PERCENTRANK.INC(Table3[MHDI_tot],Table3[[#This Row],[MHDI_tot]],3) -> 0.068
A169: =SVI!F169 -> Breves/PA | B169: =INDEX(tb_SVI[],MATCH(Table3[[#This Row],[ibge_cod]],tb_SVI[Município],0),1) -> PA | C169: =INDEX(tb_SVI[],MATCH(Table3[[#This Row],[city_name]],tb_SVI[city_name_uf],0),3) -> 1501808 | D169: BRA.14.28_1 | E169: =INDEX(tb_SVI[],MATCH(Table3[[#This Row],[city_name]],tb_SVI[city_name_uf],0),5) -> 103497 | F169: =INDEX(tb_MHDI[],MATCH(Table3[[#This Row],[city_name]],tb_MHDI[mun_uf],0),5) -> 0.503 | G169: =INDEX(tb_MHDI[],MATCH(Table3[[#This Row],[city_name]],tb_MHDI[mun_uf],0),6) -> 0.524 | H169: =INDEX(tb_MHDI[],MATCH(Table3[[#This Row],[city_name]],tb_MHDI[mun_uf],0),7) -> 0.778 | I169: =INDEX(tb_MHDI[],MATCH(Table3[[#This Row],[city_name]],tb_MHDI[mun_uf],0),8) -> 0.312 | J169: =_xlfn.NUMBERVALUE(INDEX(tb_SVI[],MATCH(Table3[[#This Row],[city_name]],tb_SVI[city_name_uf],0),8),".") -> 0.603 | K169: =_xlfn.NUMBERVALUE(INDEX(tb_SVI[],MATCH(Table3[[#This Row],[city_name]],tb_SVI[city_name_uf],0),9),".") -> 0.493 | L169: =_xlfn.NUMBERVALUE(INDEX(tb_SVI[],MATCH(Table3[[#This Row],[city_name]],tb_SVI[city_name_uf],0),10),".") -> 0.685 | M169: =_xlfn.NUMBERVALUE(INDEX(tb_SVI[],MATCH(Table3[[#This Row],[city_name]],tb_SVI[city_name_uf],0),11),".") -> 0.63 | N169: =_xlfn.PERCENTRANK.INC(Table3[MHDI_tot],Table3[[#This Row],[MHDI_tot]],3) -> 0.007
A170: =SVI!F170 -> Breu Branco/PA | B170: =INDEX(tb_SVI[],MATCH(Table3[[#This Row],[ibge_cod]],tb_SVI[Município],0),1) -> PA | C170: =INDEX(tb_SVI[],MATCH(Table3[[#This Row],[city_name]],tb_SVI[city_name_uf],0),3) -> 1501782 | D170: BRA.14.27_1 | E170: =INDEX(tb_SVI[],MATCH(Table3[[#This Row],[city_name]],tb_SVI[city_name_uf],0),5) -> 67332 | F170: =INDEX(tb_MHDI[],MATCH(Table3[[#This Row],[city_name]],tb_MHDI[mun_uf],0),5) -> 0.568 | G170: =INDEX(tb_MHDI[],MATCH(Table3[[#This Row],[city_name]],tb_MHDI[mun_uf],0),6) -> 0.555 | H170: =INDEX(tb_MHDI[],MATCH(Table3[[#This Row],[city_name]],tb_MHDI[mun_uf],0),7) -> 0.781 | I170: =INDEX(tb_MHDI[],MATCH(Table3[[#This Row],[city_name]],tb_MHDI[mun_uf],0),8) -> 0.422 | J170: =_xlfn.NUMBERVALUE(INDEX(tb_SVI[],MATCH(Table3[[#This Row],[city_name]],tb_SVI[city_name_uf],0),8),".") -> 0.528 | K170: =_xlfn.NUMBERVALUE(INDEX(tb_SVI[],MATCH(Table3[[#This Row],[city_name]],tb_SVI[city_name_uf],0),9),".") -> 0.428 | L170: =_xlfn.NUMBERVALUE(INDEX(tb_SVI[],MATCH(Table3[[#This Row],[city_name]],tb_SVI[city_name_uf],0),10),".") -> 0.616 | M170: =_xlfn.NUMBERVALUE(INDEX(tb_SVI[],MATCH(Table3[[#This Row],[city_name]],tb_SVI[city_name_uf],0),11),".") -> 0.539 | N170: =_xlfn.PERCENTRANK.INC(Table3[MHDI_tot],Table3[[#This Row],[MHDI_tot]],3) -> 0.119
A171: =SVI!F171 -> Brejo Grande do Araguaia/PA | B171: =INDEX(tb_SVI[],MATCH(Table3[[#This Row],[ibge_cod]],tb_SVI[Município],0),1) -> PA | C171: =INDEX(tb_SVI[],MATCH(Table3[[#This Row],[city_name]],tb_SVI[city_name_uf],0),3) -> 1501758 | D171: BRA.14.26_1 | E171: =INDEX(tb_SVI[],MATCH(Table3[[#This Row],[city_name]],tb_SVI[city_name_uf],0),5) -> 7368 | F171: =INDEX(tb_MHDI[],MATCH(Table3[[#This Row],[city_name]],tb_MHDI[mun_uf],0),5) -> 0.591 | G171: =INDEX(tb_MHDI[],MATCH(Table3[[#This Row],[city_name]],tb_MHDI[mun_uf],0),6) -> 0.588 | H171: =INDEX(tb_MHDI[],MATCH(Table3[[#This Row],[city_name]],tb_MHDI[mun_uf],0),7) -> 0.743 | I171: =INDEX(tb_MHDI[],MATCH(Table3[[#This Row],[city_name]],tb_MHDI[mun_uf],0),8) -> 0.473 | J171: =_xlfn.NUMBERVALUE(INDEX(tb_SVI[],MATCH(Table3[[#This Row],[city_name]],tb_SVI[city_name_uf],0),8),".") -> 0.558 | K171: =_xlfn.NUMBERVALUE(INDEX(tb_SVI[],MATCH(Table3[[#This Row],[city_name]],tb_SVI[city_name_uf],0),9),".") -> 0.627 | L171: =_xlfn.NUMBERVALUE(INDEX(tb_SVI[],MATCH(Table3[[#This Row],[city_name]],tb_SVI[city_name_uf],0),10),".") -> 0.594 | M171: =_xlfn.NUMBERVALUE(INDEX(tb_SVI[],MATCH(Table3[[#This Row],[city_name]],tb_SVI[city_name_uf],0),11),".") -> 0.454 | N171: =_xlfn.PERCENTRANK.INC(Table3[MHDI_tot],Table3[[#This Row],[MHDI_tot]],3) -> 0.21
A172: =SVI!F172 -> Brasil Novo/PA | B172: =INDEX(tb_SVI[],MATCH(Table3[[#This Row],[ibge_cod]],tb_SVI[Município],0),1) -> PA | C172: =INDEX(tb_SVI[],MATCH(Table3[[#This Row],[city_name]],tb_SVI[city_name_uf],0),3) -> 1501725 | D172: BRA.14.25_1 | E172: =INDEX(tb_SVI[],MATCH(Table3[[#This Row],[city_name]],tb_SVI[city_name_uf],0),5) -> 14983 | F172: =INDEX(tb_MHDI[],MATCH(Table3[[#This Row],[city_name]],tb_MHDI[mun_uf],0),5) -> 0.613 | G172: =INDEX(tb_MHDI[],MATCH(Table3[[#This Row],[city_name]],tb_MHDI[mun_uf],0),6) -> 0.632 | H172: =INDEX(tb_MHDI[],MATCH(Table3[[#This Row],[city_name]],tb_MHDI[mun_uf],0),7) -> 0.809 | I172: =INDEX(tb_MHDI[],MATCH(Table3[[#This Row],[city_name]],tb_MHDI[mun_uf],0),8) -> 0.451 | J172: =_xlfn.NUMBERVALUE(INDEX(tb_SVI[],MATCH(Table3[[#This Row],[city_name]],tb_SVI[city_name_uf],0),8),".") -> 0.482 | K172: =_xlfn.NUMBERVALUE(INDEX(tb_SVI[],MATCH(Table3[[#This Row],[city_name]],tb_SVI[city_name_uf],0),9),".") -> 0.403 | L172: =_xlfn.NUMBERVALUE(INDEX(tb_SVI[],MATCH(Table3[[#This Row],[city_name]],tb_SVI[city_name_uf],0),10),".") -> 0.528 | M172: =_xlfn.NUMBERVALUE(INDEX(tb_SVI[],MATCH(Table3[[#This Row],[city_name]],tb_SVI[city_name_uf],0),11),".") -> 0.514 | N172: =_xlfn.PERCENTRANK.INC(Table3[MHDI_tot],Table3[[#This Row],[MHDI_tot]],3) -> 0.305
A173: =SVI!F173 -> Bragança/PA | B173: =INDEX(tb_SVI[],MATCH(Table3[[#This Row],[ibge_cod]],tb_SVI[Município],0),1) -> PA | C173: =INDEX(tb_SVI[],MATCH(Table3[[#This Row],[city_name]],tb_SVI[city_name_uf],0),3) -> 1501709 | D173: BRA.14.24_1 | E173: =INDEX(tb_SVI[],MATCH(Table3[[#This Row],[city_name]],tb_SVI[city_name_uf],0),5) -> 128914 | F173: =INDEX(tb_MHDI[],MATCH(Table3[[#This Row],[city_name]],tb_MHDI[mun_uf],0),5) -> 0.6 | G173: =INDEX(tb_MHDI[],MATCH(Table3[[#This Row],[city_name]],tb_MHDI[mun_uf],0),6) -> 0.589 | H173: =INDEX(tb_MHDI[],MATCH(Table3[[#This Row],[city_name]],tb_MHDI[mun_uf],0),7) -> 0.755 | I173: =INDEX(tb_MHDI[],MATCH(Table3[[#This Row],[city_name]],tb_MHDI[mun_uf],0),8) -> 0.486 | J173: =_xlfn.NUMBERVALUE(INDEX(tb_SVI[],MATCH(Table3[[#This Row],[city_name]],tb_SVI[city_name_uf],0),8),".") -> 0.511 | K173: =_xlfn.NUMBERVALUE(INDEX(tb_SVI[],MATCH(Table3[[#This Row],[city_name]],tb_SVI[city_name_uf],0),9),".") -> 0.489 | L173: =_xlfn.NUMBERVALUE(INDEX(tb_SVI[],MATCH(Table3[[#This Row],[city_name]],tb_SVI[city_name_uf],0),10),".") -> 0.563 | M173: =_xlfn.NUMBERVALUE(INDEX(tb_SVI[],MATCH(Table3[[#This Row],[city_name]],tb_SVI[city_name_uf],0),11),".") -> 0.482 | N173: =_xlfn.PERCENTRANK.INC(Table3[MHDI_tot],Table3[[#This Row],[MHDI_tot]],3) -> 0.251
A174: =SVI!F174 -> Bonito/PA | B174: =INDEX(tb_SVI[],MATCH(Table3[[#This Row],[ibge_cod]],tb_SVI[Município],0),1) -> PA | C174: =INDEX(tb_SVI[],MATCH(Table3[[#This Row],[city_name]],tb_SVI[city_name_uf],0),3) -> 1501600 | D174: BRA.14.23_1 | E174: =INDEX(tb_SVI[],MATCH(Table3[[#This Row],[city_name]],tb_SVI[city_name_uf],0),5) -> 16530 | F174: =INDEX(tb_MHDI[],MATCH(Table3[[#This Row],[city_name]],tb_MHDI[mun_uf],0),5) -> 0.546 | G174: =INDEX(tb_MHDI[],MATCH(Table3[[#This Row],[city_name]],tb_MHDI[mun_uf],0),6) -> 0.531 | H174: =INDEX(tb_MHDI[],MATCH(Table3[[#This Row],[city_name]],tb_MHDI[mun_uf],0),7) -> 0.77 | I174: =INDEX(tb_MHDI[],MATCH(Table3[[#This Row],[city_name]],tb_MHDI[mun_uf],0),8) -> 0.398 | J174: =_xlfn.NUMBERVALUE(INDEX(tb_SVI[],MATCH(Table3[[#This Row],[city_name]],tb_SVI[city_name_uf],0),8),".") -> 0.555 | K174: =_xlfn.NUMBERVALUE(INDEX(tb_SVI[],MATCH(Table3[[#This Row],[city_name]],tb_SVI[city_name_uf],0),9),".") -> 0.506 | L174: =_xlfn.NUMBERVALUE(INDEX(tb_SVI[],MATCH(Table3[[#This Row],[city_name]],tb_SVI[city_name_uf],0),10),".") -> 0.608 | M174: =_xlfn.NUMBERVALUE(INDEX(tb_SVI[],MATCH(Table3[[#This Row],[city_name]],tb_SVI[city_name_uf],0),11),".") -> 0.55 | N174: =_xlfn.PERCENTRANK.INC(Table3[MHDI_tot],Table3[[#This Row],[MHDI_tot]],3) -> 0.053
A175: =SVI!F175 -> Bom Jesus do Tocantins/PA | B175: =INDEX(tb_SVI[],MATCH(Table3[[#This Row],[ibge_cod]],tb_SVI[Município],0),1) -> PA | C175: =INDEX(tb_SVI[],MATCH(Table3[[#This Row],[city_name]],tb_SVI[city_name_uf],0),3) -> 1501576 | D175: BRA.14.22_1 | E175: =INDEX(tb_SVI[],MATCH(Table3[[#This Row],[city_name]],tb_SVI[city_name_uf],0),5) -> 17118 | F175: =INDEX(tb_MHDI[],MATCH(Table3[[#This Row],[city_name]],tb_MHDI[mun_uf],0),5) -> 0.589 | G175: =INDEX(tb_MHDI[],MATCH(Table3[[#This Row],[city_name]],tb_MHDI[mun_uf],0),6) -> 0.601 | H175: =INDEX(tb_MHDI[],MATCH(Table3[[#This Row],[city_name]],tb_MHDI[mun_uf],0),7) -> 0.777 | I175: =INDEX(tb_MHDI[],MATCH(Table3[[#This Row],[city_name]],tb_MHDI[mun_uf],0),8) -> 0.437 | J175: =_xlfn.NUMBERVALUE(INDEX(tb_SVI[],MATCH(Table3[[#This Row],[city_name]],tb_SVI[city_name_uf],0),8),".") -> 0.49 | K175: =_xlfn.NUMBERVALUE(INDEX(tb_SVI[],MATCH(Table3[[#This Row],[city_name]],tb_SVI[city_name_uf],0),9),".") -> 0.432 | L175: =_xlfn.NUMBERVALUE(INDEX(tb_SVI[],MATCH(Table3[[#This Row],[city_name]],tb_SVI[city_name_uf],0),10),".") -> 0.587 | M175: =_xlfn.NUMBERVALUE(INDEX(tb_SVI[],MATCH(Table3[[#This Row],[city_name]],tb_SVI[city_name_uf],0),11),".") -> 0.451 | N175: =_xlfn.PERCENTRANK.INC(Table3[MHDI_tot],Table3[[#This Row],[MHDI_tot]],3) -> 0.201
A176: =SVI!F176 -> Belterra/PA | B176: =INDEX(tb_SVI[],MATCH(Table3[[#This Row],[ibge_cod]],tb_SVI[Município],0),1) -> PA | C176: =INDEX(tb_SVI[],MATCH(Table3[[#This Row],[city_name]],tb_SVI[city_name_uf],0),3) -> 1501451 | D176: BRA.14.20_1 | E176: =INDEX(tb_SVI[],MATCH(Table3[[#This Row],[city_name]],tb_SVI[city_name_uf],0),5) -> 17839 | F176: =INDEX(tb_MHDI[],MATCH(Table3[[#This Row],[city_name]],tb_MHDI[mun_uf],0),5) -> 0.588 | G176: =INDEX(tb_MHDI[],MATCH(Table3[[#This Row],[city_name]],tb_MHDI[mun_uf],0),6) -> 0.548 | H176: =INDEX(tb_MHDI[],MATCH(Table3[[#This Row],[city_name]],tb_MHDI[mun_uf],0),7) -> 0.775 | I176: =INDEX(tb_MHDI[],MATCH(Table3[[#This Row],[city_name]],tb_MHDI[mun_uf],0),8) -> 0.478 | J176: =_xlfn.NUMBERVALUE(INDEX(tb_SVI[],MATCH(Table3[[#This Row],[city_name]],tb_SVI[city_name_uf],0),8),".") -> 0.573 | K176: =_xlfn.NUMBERVALUE(INDEX(tb_SVI[],MATCH(Table3[[#This Row],[city_name]],tb_SVI[city_name_uf],0),9),".") -> 0.582 | L176: =_xlfn.NUMBERVALUE(INDEX(tb_SVI[],MATCH(Table3[[#This Row],[city_name]],tb_SVI[city_name_uf],0),10),".") -> 0.549 | M176: =_xlfn.NUMBERVALUE(INDEX(tb_SVI[],MATCH(Table3[[#This Row],[city_name]],tb_SVI[city_name_uf],0),11),".") -> 0.588 | N176: =_xlfn.PERCENTRANK.INC(Table3[MHDI_tot],Table3[[#This Row],[MHDI_tot]],3) -> 0.197
A177: =SVI!F177 -> Barcarena/PA | B177: =INDEX(tb_SVI[],MATCH(Table3[[#This Row],[ibge_cod]],tb_SVI[Município],0),1) -> PA | C177: =INDEX(tb_SVI[],MATCH(Table3[[#This Row],[city_name]],tb_SVI[city_name_uf],0),3) -> 1501303 | D177: BRA.14.18_1 | E177: =INDEX(tb_SVI[],MATCH(Table3[[#This Row],[city_name]],tb_SVI[city_name_uf],0),5) -> 127027 | F177: =INDEX(tb_MHDI[],MATCH(Table3[[#This Row],[city_name]],tb_MHDI[mun_uf],0),5) -> 0.662 | G177: =INDEX(tb_MHDI[],MATCH(Table3[[#This Row],[city_name]],tb_MHDI[mun_uf],0),6) -> 0.643 | H177: =INDEX(tb_MHDI[],MATCH(Table3[[#This Row],[city_name]],tb_MHDI[mun_uf],0),7) -> 0.801 | I177: =INDEX(tb_MHDI[],MATCH(Table3[[#This Row],[city_name]],tb_MHDI[mun_uf],0),8) -> 0.564 | J177: =_xlfn.NUMBERVALUE(INDEX(tb_SVI[],MATCH(Table3[[#This Row],[city_name]],tb_SVI[city_name_uf],0),8),".") -> 0.418 | K177: =_xlfn.NUMBERVALUE(INDEX(tb_SVI[],MATCH(Table3[[#This Row],[city_name]],tb_SVI[city_name_uf],0),9),".") -> 0.373 | L177: =_xlfn.NUMBERVALUE(INDEX(tb_SVI[],MATCH(Table3[[#This Row],[city_name]],tb_SVI[city_name_uf],0),10),".") -> 0.437 | M177: =_xlfn.NUMBERVALUE(INDEX(tb_SVI[],MATCH(Table3[[#This Row],[city_name]],tb_SVI[city_name_uf],0),11),".") -> 0.443 | N177: =_xlfn.PERCENTRANK.INC(Table3[MHDI_tot],Table3[[#This Row],[MHDI_tot]],3) -> 0.484
... A179: =SVI!F179 -> Baião/PA | B179: =INDEX(tb_SVI[],MATCH(Table3[[#This Row],[ibge_cod]],tb_SVI[Município],0),1) -> PA | C179: =INDEX(tb_SVI[],MATCH(Table3[[#This Row],[city_name]],tb_SVI[city_name_uf],0),3) -> 1501204 | D179: BRA.14.16_1 | E179: =INDEX(tb_SVI[],MATCH(Table3[[#This Row],[city_name]],tb_SVI[city_name_uf],0),5) -> 48459 | F179: =INDEX(tb_MHDI[],MATCH(Table3[[#This Row],[city_name]],tb_MHDI[mun_uf],0),5) -> 0.578 | G179: =INDEX(tb_MHDI[],MATCH(Table3[[#This Row],[city_name]],tb_MHDI[mun_uf],0),6) -> 0.538 | H179: =INDEX(tb_MHDI[],MATCH(Table3[[#This Row],[city_name]],tb_MHDI[mun_uf],0),7) -> 0.77 | I179: =INDEX(tb_MHDI[],MATCH(Table3[[#This Row],[city_name]],tb_MHDI[mun_uf],0),8) -> 0.467 | J179: =_xlfn.NUMBERVALUE(INDEX(tb_SVI[],MATCH(Table3[[#This Row],[city_name]],tb_SVI[city_name_uf],0),8),".") -> 0.606 | K179: =_xlfn.NUMBERVALUE(INDEX(tb_SVI[],MATCH(Table3[[#This Row],[city_name]],tb_SVI[city_name_uf],0),9),".") -> 0.771 | L179: =_xlfn.NUMBERVALUE(INDEX(tb_SVI[],MATCH(Table3[[#This Row],[city_name]],tb_SVI[city_name_uf],0),10),".") -> 0.531 | M179: =_xlfn.NUMBERVALUE(INDEX(tb_SVI[],MATCH(Table3[[#This Row],[city_name]],tb_SVI[city_name_uf],0),11),".") -> 0.516 | N179: =_xlfn.PERCENTRANK.INC(Table3[MHDI_tot],Table3[[#This Row],[MHDI_tot]],3) -> 0.156
A180: =SVI!F340 -> Rio Sono/TO | B180: =INDEX(tb_SVI[],MATCH(Table3[[#This Row],[ibge_cod]],tb_SVI[Município],0),1) -> TO | C180: =INDEX(tb_SVI[],MATCH(Table3[[#This Row],[city_name]],tb_SVI[city_name_uf],0),3) -> 1718758 | D180: BRA.27.111_1 | E180: =INDEX(tb_SVI[],MATCH(Table3[[#This Row],[city_name]],tb_SVI[city_name_uf],0),5) -> 6488 | F180: =INDEX(tb_MHDI[],MATCH(Table3[[#This Row],[city_name]],tb_MHDI[mun_uf],0),5) -> 0.6 | G180: =INDEX(tb_MHDI[],MATCH(Table3[[#This Row],[city_name]],tb_MHDI[mun_uf],0),6) -> 0.574 | H180: =INDEX(tb_MHDI[],MATCH(Table3[[#This Row],[city_name]],tb_MHDI[mun_uf],0),7) -> 0.779 | I180: =INDEX(tb_MHDI[],MATCH(Table3[[#This Row],[city_name]],tb_MHDI[mun_uf],0),8) -> 0.482 | J180: =_xlfn.NUMBERVALUE(INDEX(tb_SVI[],MATCH(Table3[[#This Row],[city_name]],tb_SVI[city_name_uf],0),8),".") -> 0.366 | K180: =_xlfn.NUMBERVALUE(INDEX(tb_SVI[],MATCH(Table3[[#This Row],[city_name]],tb_SVI[city_name_uf],0),9),".") -> 0.063 | L180: =_xlfn.NUMBERVALUE(INDEX(tb_SVI[],MATCH(Table3[[#This Row],[city_name]],tb_SVI[city_name_uf],0),10),".") -> 0.489 | M180: =_xlfn.NUMBERVALUE(INDEX(tb_SVI[],MATCH(Table3[[#This Row],[city_name]],tb_SVI[city_name_uf],0),11),".") -> 0.547 | N180: =_xlfn.PERCENTRANK.INC(Table3[MHDI_tot],Table3[[#This Row],[MHDI_tot]],3) -> 0.251
A181: =SVI!F181 -> Aveiro/PA | B181: =INDEX(tb_SVI[],MATCH(Table3[[#This Row],[ibge_cod]],tb_SVI[Município],0),1) -> PA | C181: =INDEX(tb_SVI[],MATCH(Table3[[#This Row],[city_name]],tb_SVI[city_name_uf],0),3) -> 1501006 | D181: BRA.14.14_1 | E181: =INDEX(tb_SVI[],MATCH(Table3[[#This Row],[city_name]],tb_SVI[city_name_uf],0),5) -> 16404 | F181: =INDEX(tb_MHDI[],MATCH(Table3[[#This Row],[city_name]],tb_MHDI[mun_uf],0),5) -> 0.541 | G181: =INDEX(tb_MHDI[],MATCH(Table3[[#This Row],[city_name]],tb_MHDI[mun_uf],0),6) -> 0.47 | H181: =INDEX(tb_MHDI[],MATCH(Table3[[#This Row],[city_name]],tb_MHDI[mun_uf],0),7) -> 0.748 | I181: =INDEX(tb_MHDI[],MATCH(Table3[[#This Row],[city_name]],tb_MHDI[mun_uf],0),8) -> 0.45 | J181: =_xlfn.NUMBERVALUE(INDEX(tb_SVI[],MATCH(Table3[[#This Row],[city_name]],tb_SVI[city_name_uf],0),8),".") -> 0.769 | K181: =_xlfn.NUMBERVALUE(INDEX(tb_SVI[],MATCH(Table3[[#This Row],[city_name]],tb_SVI[city_name_uf],0),9),".") -> 0.974 | L181: =_xlfn.NUMBERVALUE(INDEX(tb_SVI[],MATCH(Table3[[#This Row],[city_name]],tb_SVI[city_name_uf],0),10),".") -> 0.576 | M181: =_xlfn.NUMBERVALUE(INDEX(tb_SVI[],MATCH(Table3[[#This Row],[city_name]],tb_SVI[city_name_uf],0),11),".") -> 0.758 | N181: =_xlfn.PERCENTRANK.INC(Table3[MHDI_tot],Table3[[#This Row],[MHDI_tot]],3) -> 0.043
A182: =SVI!F182 -> Aurora do Pará/PA | B182: =INDEX(tb_SVI[],MATCH(Table3[[#This Row],[ibge_cod]],tb_SVI[Município],0),1) -> PA | C182: =INDEX(tb_SVI[],MATCH(Table3[[#This Row],[city_name]],tb_SVI[city_name_uf],0),3) -> 1500958 | D182: BRA.14.13_1 | E182: =INDEX(tb_SVI[],MATCH(Table3[[#This Row],[city_name]],tb_SVI[city_name_uf],0),5) -> 31773 | F182: =INDEX(tb_MHDI[],MATCH(Table3[[#This Row],[city_name]],tb_MHDI[mun_uf],0),5) -> 0.519 | G182: =INDEX(tb_MHDI[],MATCH(Table3[[#This Row],[city_name]],tb_MHDI[mun_uf],0),6) -> 0.504 | H182: =INDEX(tb_MHDI[],MATCH(Table3[[#This Row],[city_name]],tb_MHDI[mun_uf],0),7) -> 0.773 | I182: =INDEX(tb_MHDI[],MATCH(Table3[[#This Row],[city_name]],tb_MHDI[mun_uf],0),8) -> 0.358 | J182: =_xlfn.NUMBERVALUE(INDEX(tb_SVI[],MATCH(Table3[[#This Row],[city_name]],tb_SVI[city_name_uf],0),8),".") -> 0.584 | K182: =_xlfn.NUMBERVALUE(INDEX(tb_SVI[],MATCH(Table3[[#This Row],[city_name]],tb_SVI[city_name_uf],0),9),".") -> 0.445 | L182: =_xlfn.NUMBERVALUE(INDEX(tb_SVI[],MATCH(Table3[[#This Row],[city_name]],tb_SVI[city_name_uf],0),10),".") -> 0.7 | M182: =_xlfn.NUMBERVALUE(INDEX(tb_SVI[],MATCH(Table3[[#This Row],[city_name]],tb_SVI[city_name_uf],0),11),".") -> 0.607 | N182: =_xlfn.PERCENTRANK.INC(Table3[MHDI_tot],Table3[[#This Row],[MHDI_tot]],3) -> 0.017
A183: =SVI!F183 -> Augusto Corrêa/PA | B183: =INDEX(tb_SVI[],MATCH(Table3[[#This Row],[ibge_cod]],tb_SVI[Município],0),1) -> PA | C183: =INDEX(tb_SVI[],MATCH(Table3[[#This Row],[city_name]],tb_SVI[city_name_uf],0),3) -> 1500909 | D183: BRA.14.12_1 | E183: =INDEX(tb_SVI[],MATCH(Table3[[#This Row],[city_name]],tb_SVI[city_name_uf],0),5) -> 46471 | F183: =INDEX(tb_MHDI[],MATCH(Table3[[#This Row],[city_name]],tb_MHDI[mun_uf],0),5) -> 0.52 | G183: =INDEX(tb_MHDI[],MATCH(Table3[[#This Row],[city_name]],tb_MHDI[mun_uf],0),6) -> 0.48 | H183: =INDEX(tb_MHDI[],MATCH(Table3[[#This Row],[city_name]],tb_MHDI[mun_uf],0),7) -> 0.772 | I183: =INDEX(tb_MHDI[],MATCH(Table3[[#This Row],[city_name]],tb_MHDI[mun_uf],0),8) -> 0.38 | J183: =_xlfn.NUMBERVALUE(INDEX(tb_SVI[],MATCH(Table3[[#This Row],[city_name]],tb_SVI[city_name_uf],0),8),".") -> 0.661 | K183: =_xlfn.NUMBERVALUE(INDEX(tb_SVI[],MATCH(Table3[[#This Row],[city_name]],tb_SVI[city_name_uf],0),9),".") -> 0.671 | L183: =_xlfn.NUMBERVALUE(INDEX(tb_SVI[],MATCH(Table3[[#This Row],[city_name]],tb_SVI[city_name_uf],0),10),".") -> 0.678 | M183: =_xlfn.NUMBERVALUE(INDEX(tb_SVI[],MATCH(Table3[[#This Row],[city_name]],tb_SVI[city_name_uf],0),11),".") -> 0.635 | N183: =_xlfn.PERCENTRANK.INC(Table3[MHDI_tot],Table3[[#This Row],[MHDI_tot]],3) -> 0.018
A184: =SVI!F184 -> Anapu/PA | B184: =INDEX(tb_SVI[],MATCH(Table3[[#This Row],[ibge_cod]],tb_SVI[Município],0),1) -> PA | C184: =INDEX(tb_SVI[],MATCH(Table3[[#This Row],[city_name]],tb_SVI[city_name_uf],0),3) -> 1500859 | D184: BRA.14.11_1 | E184: =INDEX(tb_SVI[],MATCH(Table3[[#This Row],[city_name]],tb_SVI[city_name_uf],0),5) -> 28607 | F184: =INDEX(tb_MHDI[],MATCH(Table3[[#This Row],[city_name]],tb_MHDI[mun_uf],0),5) -> 0.548 | G184: =INDEX(tb_MHDI[],MATCH(Table3[[#This Row],[city_name]],tb_MHDI[mun_uf],0),6) -> 0.563 | H184: =INDEX(tb_MHDI[],MATCH(Table3[[#This Row],[city_name]],tb_MHDI[mun_uf],0),7) -> 0.788 | I184: =INDEX(tb_MHDI[],MATCH(Table3[[#This Row],[city_name]],tb_MHDI[mun_uf],0),8) -> 0.371 | J184: =_xlfn.NUMBERVALUE(INDEX(tb_SVI[],MATCH(Table3[[#This Row],[city_name]],tb_SVI[city_name_uf],0),8),".") -> 0.626 | K184: =_xlfn.NUMBERVALUE(INDEX(tb_SVI[],MATCH(Table3[[#This Row],[city_name]],tb_SVI[city_name_uf],0),9),".") -> 0.635 | L184: =_xlfn.NUMBERVALUE(INDEX(tb_SVI[],MATCH(Table3[[#This Row],[city_name]],tb_SVI[city_name_uf],0),10),".") -> 0.668 | M184: =_xlfn.NUMBERVALUE(INDEX(tb_SVI[],MATCH(Table3[[#This Row],[city_name]],tb_SVI[city_name_uf],0),11),".") -> 0.575 | N184: =_xlfn.PERCENTRANK.INC(Table3[MHDI_tot],Table3[[#This Row],[MHDI_tot]],3) -> 0.057
A185: =SVI!F185 -> Anajás/PA | B185: =INDEX(tb_SVI[],MATCH(Table3[[#This Row],[ibge_cod]],tb_SVI[Município],0),1) -> PA | C185: =INDEX(tb_SVI[],MATCH(Table3[[#This Row],[city_name]],tb_SVI[city_name_uf],0),3) -> 1500701 | D185: BRA.14.9_1 | E185: =INDEX(tb_SVI[],MATCH(Table3[[#This Row],[city_name]],tb_SVI[city_name_uf],0),5) -> 29688 | F185: =INDEX(tb_MHDI[],MATCH(Table3[[#This Row],[city_name]],tb_MHDI[mun_uf],0),5) -> 0.484 | G185: =INDEX(tb_MHDI[],MATCH(Table3[[#This Row],[city_name]],tb_MHDI[mun_uf],0),6) -> 0.506 | H185: =INDEX(tb_MHDI[],MATCH(Table3[[#This Row],[city_name]],tb_MHDI[mun_uf],0),7) -> 0.774 | I185: =INDEX(tb_MHDI[],MATCH(Table3[[#This Row],[city_name]],tb_MHDI[mun_uf],0),8) -> 0.29 | J185: =_xlfn.NUMBERVALUE(INDEX(tb_SVI[],MATCH(Table3[[#This Row],[city_name]],tb_SVI[city_name_uf],0),8),".") -> 0.659 | K185: =_xlfn.NUMBERVALUE(INDEX(tb_SVI[],MATCH(Table3[[#This Row],[city_name]],tb_SVI[city_name_uf],0),9),".") -> 0.603 | L185: =_xlfn.NUMBERVALUE(INDEX(tb_SVI[],MATCH(Table3[[#This Row],[city_name]],tb_SVI[city_name_uf],0),10),".") -> 0.726 | M185: =_xlfn.NUMBERVALUE(INDEX(tb_SVI[],MATCH(Table3[[#This Row],[city_name]],tb_SVI[city_name_uf],0),11),".") -> 0.647 | N185: =_xlfn.PERCENTRANK.INC(Table3[MHDI_tot],Table3[[#This Row],[MHDI_tot]],3) -> 0.002
A186: =SVI!F186 -> Altamira/PA | B186: =INDEX(tb_SVI[],MATCH(Table3[[#This Row],[ibge_cod]],tb_SVI[Município],0),1) -> PA | C186: =INDEX(tb_SVI[],MATCH(Table3[[#This Row],[city_name]],tb_SVI[city_name_uf],0),3) -> 1500602 | D186: BRA.14.8_1 | E186: =INDEX(tb_SVI[],MATCH(Table3[[#This Row],[city_name]],tb_SVI[city_name_uf],0),5) -> 115969 | F186: =INDEX(tb_MHDI[],MATCH(Table3[[#This Row],[city_name]],tb_MHDI[mun_uf],0),5) -> 0.665 | G186: =INDEX(tb_MHDI[],MATCH(Table3[[#This Row],[city_name]],tb_MHDI[mun_uf],0),6) -> 0.662 | H186: =INDEX(tb_MHDI[],MATCH(Table3[[#This Row],[city_name]],tb_MHDI[mun_uf],0),7) -> 0.811 | I186: =INDEX(tb_MHDI[],MATCH(Table3[[#This Row],[city_name]],tb_MHDI[mun_uf],0),8) -> 0.548 | J186: =_xlfn.NUMBERVALUE(INDEX(tb_SVI[],MATCH(Table3[[#This Row],[city_name]],tb_SVI[city_name_uf],0),8),".") -> 0.408 | K186: =_xlfn.NUMBERVALUE(INDEX(tb_SVI[],MATCH(Table3[[#This Row],[city_name]],tb_SVI[city_name_uf],0),9),".") -> 0.337 | L186: =_xlfn.NUMBERVALUE(INDEX(tb_SVI[],MATCH(Table3[[#This Row],[city_name]],tb_SVI[city_name_uf],0),10),".") -> 0.505 | M186: =_xlfn.NUMBERVALUE(INDEX(tb_SVI[],MATCH(Table3[[#This Row],[city_name]],tb_SVI[city_name_uf],0),11),".") -> 0.381 | N186: =_xlfn.PERCENTRANK.INC(Table3[MHDI_tot],Table3[[#This Row],[MHDI_tot]],3) -> 0.496
A187: =SVI!F187 -> Almeirim/PA | B187: =INDEX(tb_SVI[],MATCH(Table3[[#This Row],[ibge_cod]],tb_SVI[Município],0),1) -> PA | C187: =INDEX(tb_SVI[],MATCH(Table3[[#This Row],[city_name]],tb_SVI[city_name_uf],0),3) -> 1500503 | D187: BRA.14.7_1 | E187: =INDEX(tb_SVI[],MATCH(Table3[[#This Row],[city_name]],tb_SVI[city_name_uf],0),5) -> 34076 | F187: =INDEX(tb_MHDI[],MATCH(Table3[[#This Row],[city_name]],tb_MHDI[mun_uf],0),5) -> 0.642 | G187: =INDEX(tb_MHDI[],MATCH(Table3[[#This Row],[city_name]],tb_MHDI[mun_uf],0),6) -> 0.659 | H187: =INDEX(tb_MHDI[],MATCH(Table3[[#This Row],[city_name]],tb_MHDI[mun_uf],0),7) -> 0.809 | I187: =INDEX(tb_MHDI[],MATCH(Table3[[#This Row],[city_name]],tb_MHDI[mun_uf],0),8) -> 0.497 | J187: =_xlfn.NUMBERVALUE(INDEX(tb_SVI[],MATCH(Table3[[#This Row],[city_name]],tb_SVI[city_name_uf],0),8),".") -> 0.525 | K187: =_xlfn.NUMBERVALUE(INDEX(tb_SVI[],MATCH(Table3[[#This Row],[city_name]],tb_SVI[city_name_uf],0),9),".") -> 0.58 | L187: =_xlfn.NUMBERVALUE(INDEX(tb_SVI[],MATCH(Table3[[#This Row],[city_name]],tb_SVI[city_name_uf],0),10),".") -> 0.52 | M187: =_xlfn.NUMBERVALUE(INDEX(tb_SVI[],MATCH(Table3[[#This Row],[city_name]],tb_SVI[city_name_uf],0),11),".") -> 0.475 | N187: =_xlfn.PERCENTRANK.INC(Table3[MHDI_tot],Table3[[#This Row],[MHDI_tot]],3) -> 0.411
...

Sheet SVI
A1: UF | B1: Nome da UF | C1: Município | D1: Nome Município | E1: pop_IBGE2020 | F1: city_name_uf | G1: Ano | H1: SVI | I1: SVI_infra | J1: SVI_hum | K1: SVI_wrk
A2: =INDEX(UF_acronyms!$A$1:$C$28,MATCH(B2,UF_acronyms!$C$1:$C$28,0),2) -> RO | B2: Rondônia | C2: 1100072 | D2: Corumbiara | E2: 7220 | F2: =CONCATENATE(tb_SVI[[#This Row],[Nome Município]],"/",tb_SVI[[#This Row],[UF]]) -> Corumbiara/RO | G2: 2010 | H2: 0.336 | I2: 0.201 | J2: 0.427 | K2: 0.381
A3: =INDEX(UF_acronyms!$A$1:$C$28,MATCH(B3,UF_acronyms!$C$1:$C$28,0),2) -> RO | B3: Rondônia | C3: 1100064 | D3: Colorado do Oeste | E3: 15544 | F3: =CONCATENATE(tb_SVI[[#This Row],[Nome Município]],"/",tb_SVI[[#This Row],[UF]]) -> Colorado do Oeste/RO | G3: 2010 | H3: 0.28 | I3: 0.114 | J3: 0.394 | K3: 0.333
A4: =INDEX(UF_acronyms!$A$1:$C$28,MATCH(B4,UF_acronyms!$C$1:$C$28,0),2) -> RO | B4: Rondônia | C4: 1100924 | D4: Chupinguaia | E4: 11472 | F4: =CONCATENATE(tb_SVI[[#This Row],[Nome Município]],"/",tb_SVI[[#This Row],[UF]]) -> Chupinguaia/RO | G4: 2010 | H4: 0.338 | I4: 0.285 | J4: 0.383 | K4: 0.347
A5: =INDEX(UF_acronyms!$A$1:$C$28,MATCH(B5,UF_acronyms!$C$1:$C$28,0),2) -> RO | B5: Rondônia | C5: 1100304 | D5: Vilhena | E5: 102211 | F5: =CONCATENATE(tb_SVI[[#This Row],[Nome Município]],"/",tb_SVI[[#This Row],[UF]]) -> Vilhena/RO | G5: 2010 | H5: 0.239 | I5: 0.103 | J5: 0.339 | K5: 0.274
A6: =INDEX(UF_acronyms!$A$1:$C$28,MATCH(B6,UF_acronyms!$C$1:$C$28,0),2) -> RO | B6: Rondônia | C6: 1101807 | D6: Vale do Paraíso | E6: 6656 | F6: =CONCATENATE(tb_SVI[[#This Row],[Nome Município]],"/",tb_SVI[[#This Row],[UF]]) -> Vale do Paraíso/RO | G6: 2010 | H6: 0.309 | I6: 0.131 | J6: 0.438 | K6: 0.358
A7: =INDEX(UF_acronyms!$A$1:$C$28,MATCH(B7,UF_acronyms!$C$1:$C$28,0),2) -> RO | B7: Rondônia | C7: 1101757 | D7: Vale do Anari | E7: 11377 | F7: =CONCATENATE(tb_SVI[[#This Row],[Nome Município]],"/",tb_SVI[[#This Row],[UF]]) -> Vale do Anari/RO | G7: 2010 | H7: 0.402 | I7: 0.200 | J7: 0.526 | K7: 0.481
A8: =INDEX(UF_acronyms!$A$1:$C$28,MATCH(B8,UF_acronyms!$C$1:$C$28,0),2) -> RO | B8: Rondônia | C8: 1101708 | D8: Urupá | E8: 11272 | F8: =CONCATENATE(tb_SVI[[#This Row],[Nome Município]],"/",tb_SVI[[#This Row],[UF]]) -> Urupá/RO | G8: 2010 | H8: 0.386 | I8: 0.194 | J8: 0.445 | K8: 0.520
A9: =INDEX(UF_acronyms!$A$1:$C$28,MATCH(B9,UF_acronyms!$C$1:$C$28,0),2) -> RO | B9: Rondônia | C9: 1101609 | D9: Theobroma | E9: 10395 | F9: =CONCATENATE(tb_SVI[[#This Row],[Nome Município]],"/",tb_SVI[[#This Row],[UF]]) -> Theobroma/RO | G9: 2010 | H9: 0.352 | I9: 0.164 | J9: 0.388 | K9: 0.505
A10: =INDEX(UF_acronyms!$A$1:$C$28,MATCH(B10,UF_acronyms!$C$1:$C$28,0),2) -> RO | B10: Rondônia | C10: 1101559 | D10: Teixeirópolis | E10: 4233 | F10: =CONCATENATE(tb_SVI[[#This Row],[Nome Município]],"/",tb_SVI[[#This Row],[UF]]) -> Teixeirópolis/RO | G10: 2010 | H10: 0.299 | I10: 0.197 | J10: 0.322 | K10: 0.377
A11: =INDEX(UF_acronyms!$A$1:$C$28,MATCH(B11,UF_acronyms!$C$1:$C$28,0),2) -> RO | B11: Rondônia | C11: 1100320 | D11: São Miguel do Guaporé | E11: 23077 | F11: =CONCATENATE(tb_SVI[[#This Row],[Nome Município]],"/",tb_SVI[[#This Row],[UF]]) -> São Miguel do Guaporé/RO | G11: 2010 | H11: 0.338 | I11: 0.127 | J11: 0.466 | K11: 0.421
A12: =INDEX(UF_acronyms!$A$1:$C$28,MATCH(B12,UF_acronyms!$C$1:$C$28,0),2) -> RO | B12: Rondônia | C12: 1101492 | D12: São Francisco do Guaporé | E12: 20681 | F12: =CONCATENATE(tb_SVI[[#This Row],[Nome Município]],"/",tb_SVI[[#This Row],[UF]]) -> São Francisco do Guaporé/RO | G12: 2010 | H12: 0.429 | I12: 0.282 | J12: 0.554 | K12: 0.451
A13: =INDEX(UF_acronyms!$A$1:$C$28,MATCH(B13,UF_acronyms!$C$1:$C$28,0),2) -> RO | B13: Rondônia | C13: 1101484 | D13: São Felipe D'Oeste | E13: 5066 | F13: =CONCATENATE(tb_SVI[[#This Row],[Nome Município]],"/",tb_SVI[[#This Row],[UF]]) -> São Felipe D'Oeste/RO | G13: 2010 | H13: 0.338 | I13: 0.159 | J13: 0.447 | K13: 0.407
... A5566: =INDEX(UF_acronyms!$A$1:$C$28,MATCH(B5566,UF_acronyms!$C$1:$C$28,0),2) -> DF | B5566: Distrito Federal | C5566: 5300108 | D5566: Brasília | E5566: 3055149 | F5566: =CONCATENATE(tb_SVI[[#This Row],[Nome Município]],"/",tb_SVI[[#This Row],[UF]]) -> Brasília/DF | G5566: 2010 | H5566: 0.294 | I5566: 0.412 | J5566: 0.265 | K5566: 0.204

Sheet MHDI
A1: Territorialidades | B1: Município | C1: UF | D1: mun_uf | E1: IDHM 2010 | F1: IDHM Renda 2010 | G1: IDHM Longevidade 2010 | H1: IDHM Educação 2010 | I1: IDHM Educação 2011
A2: Abadia de Goiás /GO) | B2: =LEFT(tb_MHDI[[#This Row],[Territorialidades]],(FIND("/",tb_MHDI[[#This Row],[Territorialidades]])-2)) -> Abadia de Goiás | C2: =LEFT(RIGHT(tb_MHDI[[#This Row],[Territorialidades]],3),2) -> GO | D2: =CONCATENATE(tb_MHDI[[#This Row],[Município]],"/",tb_MHDI[[#This Row],[UF]]) -> Abadia de Goiás/GO | E2: 0.708 | F2: 0.687 | G2: 0.83 | H2: 0.622 | I2: =_xlfn.NUMBERVALUE(INDEX(tb_SVI[],MATCH(tb_MHDI[[#This Row],[mun_uf]],tb_SVI[city_name_uf],0),7),".") -> 2010
A3: Abadia dos Dourados /MG) | B3: =LEFT(tb_MHDI[[#This Row],[Territorialidades]],(FIND("/",tb_MHDI[[#This Row],[Territorialidades]])-2)) -> Abadia dos Dourados | C3: =LEFT(RIGHT(tb_MHDI[[#This Row],[Territorialidades]],3),2) -> MG | D3: =CONCATENATE(tb_MHDI[[#This Row],[Município]],"/",tb_MHDI[[#This Row],[UF]]) -> Abadia dos Dourados/MG | E3: 0.689 | F3: 0.693 | G3: 0.839 | H3: 0.563 | I3: =_xlfn.NUMBERVALUE(INDEX(tb_SVI[],MATCH(tb_MHDI[[#This Row],[mun_uf]],tb_SVI[city_name_uf],0),7),".") -> 2010
A4: Abadiânia /GO) | B4: =LEFT(tb_MHDI[[#This Row],[Territorialidades]],(FIND("/",tb_MHDI[[#This Row],[Territorialidades]])-2)) -> Abadiânia | C4: =LEFT(RIGHT(tb_MHDI[[#This Row],[Territorialidades]],3),2) -> GO | D4: =CONCATENATE(tb_MHDI[[#This Row],[Município]],"/",tb_MHDI[[#This Row],[UF]]) -> Abadiânia/GO | E4: 0.689 | F4: 0.671 | G4: 0.841 | H4: 0.579 | I4: =_xlfn.NUMBERVALUE(INDEX(tb_SVI[],MATCH(tb_MHDI[[#This Row],[mun_uf]],tb_SVI[city_name_uf],0),7),".") -> 2010
A5: Abaeté /MG) | B5: =LEFT(tb_MHDI[[#This Row],[Territorialidades]],(FIND("/",tb_MHDI[[#This Row],[Territorialidades]])-2)) -> Abaeté | C5: =LEFT(RIGHT(tb_MHDI[[#This Row],[Territorialidades]],3),2) -> MG | D5: =CONCATENATE(tb_MHDI[[#This Row],[Município]],"/",tb_MHDI[[#This Row],[UF]]) -> Abaeté/MG | E5: 0.698 | F5: 0.72 | G5: 0.848 | H5: 0.556 | I5: =_xlfn.NUMBERVALUE(INDEX(tb_SVI[],MATCH(tb_MHDI[[#This Row],[mun_uf]],tb_SVI[city_name_uf],0),7),".") -> 2010
A6: Abaetetuba /PA) | B6: =LEFT(tb_MHDI[[#This Row],[Territorialidades]],(FIND("/",tb_MHDI[[#This Row],[Territorialidades]])-2)) -> Abaetetuba | C6: =LEFT(RIGHT(tb_MHDI[[#This Row],[Territorialidades]],3),2) -> PA | D6: =CONCATENATE(tb_MHDI[[#This Row],[Município]],"/",tb_MHDI[[#This Row],[UF]]) -> Abaetetuba/PA | E6: 0.628 | F6: 0.579 | G6: 0.798 | H6: 0.537 | I6: =_xlfn.NUMBERVALUE(INDEX(tb_SVI[],MATCH(tb_MHDI[[#This Row],[mun_uf]],tb_SVI[city_name_uf],0),7),".") -> 2010
A7: Abaiara /CE) | B7: =LEFT(tb_MHDI[[#This Row],[Territorialidades]],(FIND("/",tb_MHDI[[#This Row],[Territorialidades]])-2)) -> Abaiara | C7: =LEFT(RIGHT(tb_MHDI[[#This Row],[Territorialidades]],3),2) -> CE | D7: =CONCATENATE(tb_MHDI[[#This Row],[Município]],"/",tb_MHDI[[#This Row],[UF]]) -> Abaiara/CE | E7: 0.628 | F7: 0.54 | G7: 0.748 | H7: 0.612 | I7: =_xlfn.NUMBERVALUE(INDEX(tb_SVI[],MATCH(tb_MHDI[[#This Row],[mun_uf]],tb_SVI[city_name_uf],0),7),".") -> 2010
A8: Abaíra /BA) | B8: =LEFT(tb_MHDI[[#This Row],[Territorialidades]],(FIND("/",tb_MHDI[[#This Row],[Territorialidades]])-2)) -> Abaíra | C8: =LEFT(RIGHT(tb_MHDI[[#This Row],[Territorialidades]],3),2) -> BA | D8: =CONCATENATE(tb_MHDI[[#This Row],[Município]],"/",tb_MHDI[[#This Row],[UF]]) -> Abaíra/BA | E8: 0.603 | F8: 0.577 | G8: 0.746 | H8: 0.51 | I8: =_xlfn.NUMBERVALUE(INDEX(tb_SVI[],MATCH(tb_MHDI[[#This Row],[mun_uf]],tb_SVI[city_name_uf],0),7),".") -> 2010
A9: Abaré /BA) | B9: =LEFT(tb_MHDI[[#This Row],[Territorialidades]],(FIND("/",tb_MHDI[[#This Row],[Territorialidades]])-2)) -> Abaré | C9: =LEFT(RIGHT(tb_MHDI[[#This Row],[Territorialidades]],3),2) -> BA | D9: =CONCATENATE(tb_MHDI[[#This Row],[Município]],"/",tb_MHDI[[#This Row],[UF]]) -> Abaré/BA | E9: 0.575 | F9: 0.533 | G9: 0.776 | H9: 0.46 | I9: =_xlfn.NUMBERVALUE(INDEX(tb_SVI[],MATCH(tb_MHDI[[#This Row],[mun_uf]],tb_SVI[city_name_uf],0),7),".") -> 2010
A10: Abatiá /PR) | B10: =LEFT(tb_MHDI[[#This Row],[Territorialidades]],(FIND("/",tb_MHDI[[#This Row],[Territorialidades]])-2)) -> Abatiá | C10: =LEFT(RIGHT(tb_MHDI[[#This Row],[Territorialidades]],3),2) -> PR | D10: =CONCATENATE(tb_MHDI[[#This Row],[Município]],"/",tb_MHDI[[#This Row],[UF]]) -> Abatiá/PR | E10: 0.687 | F10: 0.676 | G10: 0.804 | H10: 0.596 | I10: =_xlfn.NUMBERVALUE(INDEX(tb_SVI[],MATCH(tb_MHDI[[#This Row],[mun_uf]],tb_SVI[city_name_uf],0),7),".") -> 2010
A11: Abdon Batista /SC) | B11: =LEFT(tb_MHDI[[#This Row],[Territorialidades]],(FIND("/",tb_MHDI[[#This Row],[Territorialidades]])-2)) -> Abdon Batista | C11: =LEFT(RIGHT(tb_MHDI[[#This Row],[Territorialidades]],3),2) -> SC | D11: =CONCATENATE(tb_MHDI[[#This Row],[Município]],"/",tb_MHDI[[#This Row],[UF]]) -> Abdon Batista/SC | E11: 0.694 | F11: 0.66 | G11: 0.812 | H11: 0.625 | I11: =_xlfn.NUMBERVALUE(INDEX(tb_SVI[],MATCH(tb_MHDI[[#This Row],[mun_uf]],tb_SVI[city_name_uf],0),7),".") -> 2010
A12: Abelardo Luz /SC) | B12: =LEFT(tb_MHDI[[#This Row],[Territorialidades]],(FIND("/",tb_MHDI[[#This Row],[Territorialidades]])-2)) -> Abelardo Luz | C12: =LEFT(RIGHT(tb_MHDI[[#This Row],[Territorialidades]],3),2) -> SC | D12: =CONCATENATE(tb_MHDI[[#This Row],[Município]],"/",tb_MHDI[[#This Row],[UF]]) -> Abelardo Luz/SC | E12: 0.696 | F12: 0.684 | G12: 0.852 | H12: 0.578 | I12: =_xlfn.NUMBERVALUE(INDEX(tb_SVI[],MATCH(tb_MHDI[[#This Row],[mun_uf]],tb_SVI[city_name_uf],0),7),".") -> 2010
A13: Abel Figueiredo /PA) | B13: =LEFT(tb_MHDI[[#This Row],[Territorialidades]],(FIND("/",tb_MHDI[[#This Row],[Territorialidades]])-2)) -> Abel Figueiredo | C13: =LEFT(RIGHT(tb_MHDI[[#This Row],[Territorialidades]],3),2) -> PA | D13: =CONCATENATE(tb_MHDI[[#This Row],[Município]],"/",tb_MHDI[[#This Row],[UF]]) -> Abel Figueiredo/PA | E13: 0.622 | F13: 0.625 | G13: 0.8 | H13: 0.481 | I13: =_xlfn.NUMBERVALUE(INDEX(tb_SVI[],MATCH(tb_MHDI[[#This Row],[mun_uf]],tb_SVI[city_name_uf],0),7),".") -> 2010
... A5566: Jaçanã /RN) | B5566: =LEFT(tb_MHDI[[#This Row],[Territorialidades]],(FIND("/",tb_MHDI[[#This Row],[Territorialidades]])-2)) -> Jaçanã | C5566: =LEFT(RIGHT(tb_MHDI[[#This Row],[Territorialidades]],3),2) -> RN | D5566: =CONCATENATE(tb_MHDI[[#This Row],[Município]],"/",tb_MHDI[[#This Row],[UF]]) -> Jaçanã/RN | E5566: 0.604 | F5566: 0.559 | G5566: 0.773 | H5566: 0.509 | I5566: =_xlfn.NUMBERVALUE(INDEX(tb_SVI[],MATCH(tb_MHDI[[#This Row],[mun_uf]],tb_SVI[city_name_uf],0),7),".") -> 2010
A5568: Brasil | E5568: 0.727 | F5568: 0.739 | G5568: 0.816 | H5568: 0.637
A5569: Elaboração: Atlas do Desenvolvimento Humano no Brasil. Pnud Brasil, Ipea e FJP, 2020.
A5570: Fontes: dados do IBGE e de registros administrativos, conforme especificados nos metadados disponíveis disponíveis em: http://atlasbrasil.org.br/acervo/biblioteca.

Sheet Dicionário
A1: Sigla | B1: Nome | C1: Definição
A2: ano | B2: Ano | C2: Ano de referência das informações
A3: brasil | B3: Brasil | C3: Brasil
A4: regiao | B4: Macrorregião | C4: Macrorregião
A5: nome_regiao | B5: Nome da macrorregião | C5: Nome da macrorregião
A6: uf | B6: Código da Unidade da Federação | C6: Código da Unidade da Federação
A7: nome_uf | B7: Nome da Unidade da Federação | C7: Nome da Unidade da Federação
A8: rm | B8: Código da Região Metropolitana | C8: Código da Região Metropolitana
A9: nome_rm | B9: Nome da Região Metropolitana | C9: Nome da Região Metropolitana
A10: municipio | B10: Código do Município (7 dígitos) | C10: Código utilizado pelo IBGE para identificação do município (com digito verificador).
A11: Municipio_6digt | B11: Código do Município (6 dígitos) | C11: Código utilizado pelo IBGE para identificação do município.
A12: nome_municipio | B12: Nome do Município | C12: Nome do Município
... A102: Label_sit_dom | B102: Situação de Domicílio | C102: Desagregação das informações por situação de domicílio.

Sheet UF_acronyms
A1: cod_uf | B1: acronym_uf | C1: name_uf
A2: 11 | B2: RO | C2: Rondônia
A3: 12 | B3: AC | C3: Acre
A4: 13 | B4: AM | C4: Amazonas
A5: 14 | B5: RR | C5: Roraima
A6: 15 | B6: PA | C6: Pará
A7: 16 | B7: AP | C7: Amapá
A8: 17 | B8: TO | C8: Tocantins
A9: 21 | B9: MA | C9: Maranhão
A10: 22 | B10: PI | C10: Piauí
A11: 23 | B11: CE | C11: Ceará
A12: 24 | B12: RN | C12: Rio Grande do Norte
A13: 25 | B13: PB | C13: Paraíba
... A28: 53 | B28: DF | C28: Distrito Federal
